Workbook

Sheet 首页
A1: 4.0.22公民教育
A2: 4.0.22版审核 | B2: =_xlfn.DISPIMG("ID_8A95646438884BE8BA5ED17D3AFF9A8C",1) -> =DISPIMG("ID_8A95646438884BE8BA5ED17D3AFF9A8C",1)
A3: Stellaris 维基
A4: https://stellaris.paradoxwikis.com/Stellaris_Wiki
A5: 一.本文档最后更新于2025.08.27，适配版本号4.0.22，天灾宝典编辑群684118724，使用WPS Office软件编写（不同软件可能无法正常显示相关代码）
A6: 二.本文档收录内容：控制台中文对照，扩展代码，起源，国策，传统，飞升，思潮，物种特质，领袖特质，星球类型及建筑区划，科技，巨构，异常，部分起始事件链，考古遗址，星界裂隙，标本，遗珍，行星矿藏，修正（包含国家，行星，舰队，人口），特殊星系生成，全局舰船设计，舰船组件，成就，环境物体，组合代码
A7: 三.本文档基于【群星3.10.4天灾宝典】所做的更新与拓展，对其已失效或内容文本与当前版本不符合的部分进行了修改，对新增加条目进行了更新，在此基础上新增了更多条目。更多代码来源于原来的天灾宝典，群星英文wiki，以及猪圈的一些大神提供。
A8: 四.功能介绍及使用方法
A9: 1.控制台：在不开启铁人模式的情况下，点击“~”键进入控制台界面，显示界面的对照翻译，部分名称为？？？，是中文无法转变，但跟翻译表内位置一样。
A10: 2.扩展代码：多数扩展代码都标注了使用方法（例如选中xxx），未标注的为不需要选中任何物体，本项目栏包含：玩家常用代码，联邦，星海共同体，星球决议，陆军，法令，领袖，部分物种特质解锁，建筑解锁及加成，先驱者，部分数量计数器，高级政体切换，噬天巨兽行动，外交，资源添加，太空风暴生成，太空生物相关，舰船模型（原图形文化），更换国家背景，机械爹，L-星门事件，虚境契约，天灾事件计数器。
A11: 3.起源：包含游戏全部起源，直接输入即可。
A12: 4.国策：包含游戏全部国策，直接输入即可。
A13: 5.传统：包含游戏全部传统，直接输入即可。
A14: 6.飞升：包含游戏全部飞升，直接输入即可。
... A34: 26.舰船组件：用于改派。

Sheet 控制台
B1: ▼ Debug View | M1: × | R1: × | V1: ▼ Debug View | AL1: ×
B2: Debug Controls | O2: Debug Views | V2: Debug Controls | AI2: Debug Views
B3: ▼ Quick Access | V3: ▼ 经常使用
B4: Last daily tick: 0 ms | I4: Last 30 daily ticks avg: 0 ms | V4: Last daily tick: 0 ms | AC4: Last 30 daily ticks avg: 0 ms
B6: █ Debug Tooltips | F6: █ Instant Move | J6: █ AI | V6: █ 查看隐藏信息 | Z6: █ 船只瞬移 | AD6: █ 电脑ai开关
B7: █ Guibounds | F7: █ Instant Survey | J7: █ Human AI | V7: █ 显示UI元素信息 | Z7: █ 瞬间调查 | AD7: █ 将玩家帝国托管给电脑ai
B8: █ No Agreement CD | F8: █ Instant Research | J8: █ No Full Takeover | V8: █ 无_协议CD | Z8: █ 瞬间完成研究 | AD8: █ 接管玩家帝国后切换AI被动行为
B9: █ No GalCom CD | F9: █ Instant Build | V9: █ 无_星海共同体议案CD | Z9: █ 立刻完成建造
B10: █ No Federation CD | F10: █ Instant Anomaly | V10: █ 无_联邦法律切换CD | Z10: █ 瞬间完成异常现象调查
F11: █ Instant Colony | Z11: █ 瞬间完成殖民
B20: ▼ Resources | V20: ▼ 资源类
B22: ▼ Strategic Resources | V22: ▼ 基础资源
I23: Energy Credits | AC23: 能量币
I24: Minerals | AC24: 矿物
I25: Food | AC25: 食物
I26: Consumer | AC26: 消费品
I27: Alloys | AC27: 合金
I28: Influence | AC28: 影响力
I29: Unity | AC29: 凝聚力
B30: ▼ Special Resources | V30: ▼ 稀有资源
I31: trade | AC31: 贸易
I32: Volatile Motes | AC32: 易爆微粒
I33: Exotic Gases | AC33: 异星天然气
I34: Rare Crystals | AC34: 稀有水晶
I35: Living Metal | AC35: 活体金属
I36: Zro | AC36: 泽珞
I37: Dark Matter | AC37: 暗物质
I38: Minor Artifacts | AC38: 稀有文物
I39: Astral Threads | AC39: 星界丝缕
I40: Physics Research | AC40: 物理学研究
I41: Society Research | AC41: 社会学研究
I42: Engineering Research | AC42: 工程学研究
... I47: Feral Insight | AC47: 野性洞见（巨兽之怒）
B51: ▼ Map | V51: ▼ 地图
B54: █ instant_move | V54: █ 瞬间移动
B55: █ instant_suryey | V55: █ 瞬间调查
B56: █ instant_recearch | V56: █ 瞬间研究
B57: █ instant_anomaly_research | V57: █ 瞬间完成异常研究
B59: ▼ Time | V59: ▼ 时间（这一项尽量不要用，有BUG）
J60: ticks_per_turn | AD60: 加速时间的进程
B63: ▼ Research | V63: ▼ 研究
B66: --- | V66: ---
J67: Technology | AD67: 技术key
B70: ▼ Leaders | V70: ▼ 领袖
B73: ▼ Owned Leaders | V73: ▼ 你拥有领袖
D75: ????? | X75: mk1（领袖名，不支持中文显示，但你杀之前可以改成英文）
D76: ????? | X76: mk2（领袖名，不支持中文显示……）
A79: ▼ Paragons View | J79: × | U79: ▼ 触发英杰领袖招募弹窗 | AD79: ×
B81: Lysator Syng | G81: Spawn | H81: (2 events) | V81: 李萨拓·辛格 | AA81: 触发 | AB81: (2 事件)
B82: Nona | G82: Spawn | H82: (2 events) | V82: 诺那 | AA82: 触发 | AB82: (2 事件)
B83: Baron Vyctor Jariden | G83: Spawn | H83: (2 events) | V83: 维克托·夏里登男爵 | AA83: 触发 | AB83: (2 事件)
B84: Gia'Zumon | G84: Spawn | H84: (2 events) | V84: 基雅·祖蒙里 | AA84: 触发 | AB84: (2 事件)
B85: Factorator Shuladun | G85: Spawn | H85: (2 events) | V85: 工业人舒拉顿 | AA85: 触发 | AB85: (2 事件)
B86: Aturion | G86: Spawn | H86: (2 events) | V86: 亚图里昂 | AA86: 触发 | AB86: (2 事件)
B87: Jynn | G87: Spawn | H87: (2 events) | V87: 基恩 | AA87: 触发 | AB87: (2 事件)
B88: Zosira k'Tun | G88: Spawn | H88: (2 events) | V88: 佐西拉·科顿 | AA88: 触发 | AB88: (2 事件)
B89: Xondar | G89: Spawn | H89: (2 events) | V89: 松达尔 | AA89: 触发 | AB89: (2 事件)
B90: Borin | G90: Spawn | H90: (2 events) | V90: 柏林 | AA90: 触发 | AB90: (2 事件)
B91: Judge Uld Dagr | G91: Spawn | H91: (2 events) | V91: 乌尔德·达格尔大法官 | AA91: 触发 | AB91: (2 事件)
B92: Vas the Gilded | G92: Spawn | H92: (2 events) | V92: 万人迷沃斯 | AA92: 触发 | AB92: (2 事件)
... B96: Nasuz Demetor | G96: Spawn | H96: (2 events) | V96: 纳苏兹·德墨忒尔 | AA96: 触发 | AB96: (2 事件)
AH98: ·

Sheet 扩展代码
A1: 4.0.22扩展代码（2025.08.21）
A2: 注：效果或备注栏写明了使用方法，注意仔细阅读；在选择栏双击即可跳转相关代码；部分代码点击下拉栏即可生成对应代码。 “其他”栏目前包括：资源添加，太空风暴生成，太空生物相关，舰船模型（原图形文化），更换国家背景，机械爹，L-星门事件，虚境契约，天灾事件计数器。
A3: 选择栏 | B3: {=HYPERLINK("#"&ADDRESS(MATCH("玩家",A:A,0),COLUMN(A:A)),"玩家")} -> 玩家 | C3: {=HYPERLINK("#"&ADDRESS(MATCH("联邦",A:A,0),COLUMN(A:A)),"联邦")} -> 联邦 | D3: {=HYPERLINK("#"&ADDRESS(MATCH("星海共同体",A:A,0),COLUMN(A:A)),"星海共同体")} -> 星海共同体 | E3: {=HYPERLINK("#"&ADDRESS(MATCH("星球决议",A:A,0),COLUMN(A:A)),"星球决议")} -> 星球决议 | F3: {=HYPERLINK("#"&ADDRESS(MATCH("陆军",A:A,0),COLUMN(A:A)),"陆军")} -> 陆军
B4: {=HYPERLINK("#"&ADDRESS(MATCH("法令",A:A,0),COLUMN(A:A)),"法令")} -> 法令 | C4: {=HYPERLINK("#"&ADDRESS(MATCH("领袖",A:A,0),COLUMN(A:A)),"领袖")} -> 领袖 | D4: {=HYPERLINK("#"&ADDRESS(MATCH("物种特质",A:A,0),COLUMN(A:A)),"物种特质")} -> 物种特质 | E4: {=HYPERLINK("#"&ADDRESS(MATCH("建筑",A:A,0),COLUMN(A:A)),"建筑")} -> 建筑 | F4: {=HYPERLINK("#"&ADDRESS(MATCH("先驱者",A:A,0),COLUMN(A:A)),"先驱者")} -> 先驱者
B5: {=HYPERLINK("#"&ADDRESS(MATCH("数量",A:A,0),COLUMN(A:A)),"数量")} -> 数量 | C5: {=HYPERLINK("#"&ADDRESS(MATCH("高级政体",A:A,0),COLUMN(A:A)),"高级政体")} -> 高级政体 | D5: {=HYPERLINK("#"&ADDRESS(MATCH("噬天巨兽行动",A:A,0),COLUMN(A:A)),"噬天巨兽行动")} -> 噬天巨兽行动 | E5: {=HYPERLINK("#"&ADDRESS(MATCH("顶级掠食者特质",A:A,0),COLUMN(A:A)),"顶级掠食者特质")} -> 顶级掠食者特质 | F5: {=HYPERLINK("#"&ADDRESS(MATCH("外交",A:A,0),COLUMN(A:A)),"外交")} -> 外交
B6: {=HYPERLINK("#"&ADDRESS(MATCH("其他",A:A,0),COLUMN(A:A)),"其他")} -> 其他 | F6: 附表
A7: 类别 | B7: 效果 | C7: 代码 | F7: 备注
A8: 玩家 | B8: 选中物体归玩家所有 | C8: own
B9: 更换游玩0号帝国 | C9: play 0
B10: ai同意所有条款 | C10: yesmen
B11: ai否决所有条款 | C11: nomen
B12: 对选中星球添加物种0号100人 | C12: add_pops 0 100
B13: 杀死当前国家 | C13: kill_country
B14: 立刻开始选举国家领袖 | C14: election
B15: 舰船无敌 | C15: invincible
B16: 添加舰船设计名称1的舰船1个 | C16: add_ship 1
B17: 对选中舰船造成10000伤害 | C17: damage 10000
B18: 对选中行星增加x破坏度 | C18: effect add_planet_devastation = x | F18: x为负数就是减少破坏度
B19: 对选中局势增加x进度 | C19: effect add_situation_progress = x | F19: x为负数就是减少局势进度
B20: 使国家ID1对国家ID0增加100好感 | C20: add_opinion 1 0 100
B21: 使国家ID1对国家ID0增加100信任度 | C21: add_trust 1 0 100
B22: 对国家ID1增加1000渗透度 | C22: add_spynetwork_value 1 1000
B23: 对国家ID1增加100情报 | C23: add_intel 1 100
B24: 对国家ID1增加50忠诚度 | C24: add_loyalty 1 50
B25: 向1号特化附庸国家增加1000经验 | C25: add_subject_xp 1 1000
B26: ai侵略性最大化 | C26: berserk_ai
B27: 完成环境改造 | C27: finish_terraform
B28: 将1号帝国整合进玩家帝国 | C28: force_integrate 1
B29: 改革物种权利 | C29: free_policies
B30: 改革政府 | C30: free_government
B31: 重置政策冷却 | C31: effect reset_policy_cooldowns = yes
... B37: 使终末危机的倍率乘10倍 | C37: effect multiply_crisis_strength = 1.3333
B38: 设置已完成的星界裂隙数量为5 | C38: effect set_completed_rifts 5 | F38: （已失效）
B39: 解锁内阁席位1 | C39: effect unlock_council_slots = 1
B40: 推进当前星球考古阶段 | C40: finish_arc_stage
B41: 删除这个考古遗址 | C41: effect destroy_archaeological_site = this
B42: 推进当前星界裂隙阶段 | C42: finish_rift_stage
B43: 删除这个星界裂隙 | C43: effect destroy_astral_rift = this
B44: 打印成就状态 | C44: achievement_status
B45: 激活遗珍ID | C45: activate_relic 遗珍ID
B46: 摧毁所选殖民地 | C46: effect destroy_colony
B47: 添加全部遗珍 | C47: add_relic all
B48: 查看舰船目标 | C48: debuglines
B49: 1号国家和玩家和平 | C49: peace_on_player 1
B50: 结算游戏 | C50: game_over
... B61: 设置日期扭曲效果 | C61: effect date_distortion = yes
B62: 设置舰队失踪时间 | C62: effect set_mia_return_delay = 1 | F62: 选中舰队使用
B63: 设置舰队隐身状态 | C63: effect set_cloaking_active = yes | F63: 选中舰队使用
B64: 设置舰队混乱状态 | C64: effect set_confused = yes | F64: 选中交战舰队使用
B65: 设置舰队无法被选中 | C65: effect set_event_locked = yes | F65: 选中舰队使用
B66: 设置国家控制星系加风暴特效 | C66: effect activate_fog_machine = synth_queen_nanite | F66: 塞塔娜同款风暴制造
B67: 设置风暴特效随扩张星系而扩张 | C67: effect fog_machine_auto_tracking = yes
A68: 联邦 | B68: 联邦法律切换无冷却时间 | C68: skip_federation_cooldowns | F68: 需要选中联邦使用
B69: 增加联邦等级经验 | C69: federation_add_experience 20000 | F69: 需要选中联邦使用
B70: 增加联邦团结度 | C70: federation_add_cohesion 1000 | F70: 需要选中联邦使用
B71: 增加联邦每月团结度 | C71: federation_add_cohesion_speed 20 | F71: 需要选中联邦使用
B72: 重新选举联邦主席 | C72: federation_examine_leader | F72: 需要选中联邦使用
B73: 立即成为联邦主席 | C73: effect set_federation_leader=this
B74: 解散当前联邦 | C74: effect dissolve_federation = yes | F74: 需要选中联邦使用
B75: 加入联邦前置（设置当前国家定位） | C75: effect = { save_global_event_target_as = playercountry}
B76: 加入国家所在联邦 | C76: effect = {root.owner = {join_alliance = { who = event_target:playercountry override_requirements = yes }}} | F76: 选中其他国家任意物体
B77: 改变联邦类型为 | C77: 贸易联盟 | D77: =_xlfn.CONCAT("effect set_federation_type = ",_xlfn.XLOOKUP(C77,G602:G607,H602:H607,)) -> effect set_federation_type = trade_federation | F77: 需要选中联邦使用
A78: 星海共同体 | B78: 结束参议院休会 | C78: force_senate_vote
B79: 通过共同体投票 | C79: end_senate_session pass
B80: 否决共同体投票 | C80: end_senate_session fail
B81: 移除星海共同体议案冷却时间 | C81: skip_galactic_community_cooldowns
B82: 设定星系理事会/帝国议会的数量为x | C82: effect set_council_size = x
B83: 立即加入星海共同体 | C83: effect add_to_galactic_community = yes
B84: 立即成为泛星系贸易市场的领袖 | C84: effect set_market_leader = yes
B85: 立即成为星系理事会/帝国议会成员 | C85: effect add_to_galactic_council = yes
B86: 立即成为理事会常任 | C86: effect add_permanent_councillor = yes
B87: 立即成为星海监管人 | C87: effect set_galactic_custodian = yes
B88: 立即成为星海帝皇 | C88: effect set_galactic_emperor = yes
B89: 增加帝国权威100 | C89: imperial_authority 100
A90: 星球决议 | B90: 解锁决议：应用组织生长刺激物 | C90: effect set_country_flag = city_of_bones_completed
B91: 解锁决议：昼半球发电 | C91: effect set_country_flag = tidal_lock_knowledge
B92: 解锁决议：孵化风中生物 | C92: effect = {set_variable = {which = num_authorized_wind_creatures value = 100}｝
B93: 解锁决议：岩蠹巢穴 | C93: effect set_country_flag = can_breed_rockworm_hives
B94: 解锁决议：展出艺术纪念碑 | C94: effect set_country_flag = artist_monument_collector
B95: 设置艺术纪念碑数量 | C95: effect = {set_variable = { which = artist_monument_purchased value = 1 }}
B96: 解锁决议：激活次元操纵装置 | C96: effect set_planet_flag = dimensional_manipulation_device_deactivated
B97: 解锁决议：添加分型之种 | C97: effect = {set_variable = {which = num_authorized_fractal_seeds value = 9}}
B98: 解锁决议：神圣算法决议 | C98: effect set_country_flag = divine_algorithm
B99: 解锁决议：展示袖珍行星外壳 | C99: effect set_country_flag = can_build_microplanet_memorial
A100: 陆军 | B100: 解锁陆军：曲跃雏 | C100: effect set_country_flag = unlocked_warplings
B101: 解锁陆军：焰爆部队 | C101: effect set_country_flag = unlocked_flamestorm_troopers
B102: 解锁陆军：泰坦巨兽 | C102: effect set_country_flag = titanic_life_soldiers
B103: 选中星球输入 | C103: effect set_planet_flag = titanic_life_can_build
B104: 改变招募上限 | C104: effect = {set_variable = {which = "titanic_life_soldier_count" value = 3}}
B105: 解锁陆军：阿兹詹虫 | C105: effect set_country_flag = titanic_azizian_soldiers
B106: 选中星球输入 | C106: effect set_planet_flag = titanic_azizian_can_build
B107: 改变招募上限 | C107: effect = {set_variable = { which = "titanic_azizian_soldier_count" value = 3}}
A108: 法令 | B108: 解锁法令：自动清除 | C108: effect set_country_flag = edict_automated_disinfection
B109: 解锁法令：星界隐形 | C109: effect set_country_flag = astral_cloaking_available
B110: 解锁法令：自发析晶 | C110: effect set_country_flag = has_spontaneous_crystallization
B111: 解锁法令：改善工作环境 | C111: effect set_country_flag = edict_improved_work_environment
B112: 解锁法令：广泛传感器搜寻 | C112: effect set_country_flag = edict_super_sensors
B113: 解锁法令：改善能源倡议 | C113: effect set_country_flag = edict_renewable_energy
B114: 解锁法令：拜金教成像技术 | C114: effect set_country_flag = nuumismatic_visualization
B115: 解锁法令：大师的教诲：上上善道 | C115: effect set_country_flag = edict_masters_writings_politics
...

Sheet 起源
A1: 4.0.10起源代码（2025.05.18）
A2: 状态 | B2: 序号 | C2: 起源名称 | E2: 控制台代码
A3: 玩家 可选 | B3: 1 | C3: =_xlfn.DISPIMG("ID_5B591A332A2047D097BDD94C0BDCD0D9",1) -> =DISPIMG("ID_5B591A332A2047D097BDD94C0BDCD0D9",1) | D3: 繁荣统一 | E3: effect set_origin = origin_default
B4: 2 | C4: =_xlfn.DISPIMG("ID_8FAA562B0F874077A74459617AF4EEEB",1) -> =DISPIMG("ID_8FAA562B0F874077A74459617AF4EEEB",1) | D4: 演化猎手 | E4: effect set_origin = origin_evolutionary_predators
B5: 3 | C5: =_xlfn.DISPIMG("ID_8088079084B347EC955185A0B6925C19",1) -> =DISPIMG("ID_8088079084B347EC955185A0B6925C19",1) | D5: 星耀天堡 | E5: effect set_origin = origin_starlit_citadel
B6: 4 | C6: =_xlfn.DISPIMG("ID_AB8F0EC1A19E449A9B3132576FFED2BF",1) -> =DISPIMG("ID_AB8F0EC1A19E449A9B3132576FFED2BF",1) | D6: 生体荒野 | E6: effect set_origin = origin_wilderness
B7: 5 | C7: =_xlfn.DISPIMG("ID_BD99123A37C440EFA3E61445B30813BD",1) -> =DISPIMG("ID_BD99123A37C440EFA3E61445B30813BD",1) | D7: 寻宝猎人 | E7: effect set_origin = origin_treasure_hunters
B8: 6 | C8: =_xlfn.DISPIMG("ID_4AC77990E6714364B60712C5E7556F40",1) -> =DISPIMG("ID_4AC77990E6714364B60712C5E7556F40",1) | D8: 野性呼唤 | E8: effect set_origin = origin_primal_calling
B9: 7 | C9: =_xlfn.DISPIMG("ID_DD4B58B4AA0E4292A60A83B6A4BDBDBF",1) -> =DISPIMG("ID_DD4B58B4AA0E4292A60A83B6A4BDBDBF",1) | D9: 追风者 | E9: effect set_origin = origin_storm_chasers
B10: 8 | C10: =_xlfn.DISPIMG("ID_908ED4E06D9840B2A3EDBC0D786170F4",1) -> =DISPIMG("ID_908ED4E06D9840B2A3EDBC0D786170F4",1) | D10: 义体信条 | E10: effect set_origin = origin_cybernetic_creed
B11: 9 | C11: =_xlfn.DISPIMG("ID_F64A5CC812A54A90B2E092FEB23FF105",1) -> =DISPIMG("ID_F64A5CC812A54A90B2E092FEB23FF105",1) | D11: 合成繁衍 | E11: effect set_origin = origin_synthetic_fertility
B12: 10 | C12: =_xlfn.DISPIMG("ID_FCD71DD8FF9C4C3693798D24F82E9844",1) -> =DISPIMG("ID_FCD71DD8FF9C4C3693798D24F82E9844",1) | D12: 电弧焊机 | E12: effect set_origin = origin_arc_welders
B13: 11 | C13: =_xlfn.DISPIMG("ID_48910B771FE643A9B81FA0D9A6FB92EF",1) -> =DISPIMG("ID_48910B771FE643A9B81FA0D9A6FB92EF",1) | D13: 裂隙当空 | E13: effect set_origin = origin_riftworld
B14: 12 | C14: =_xlfn.DISPIMG("ID_CBBA5D15FB9943689D358B493082E11D",1) -> =DISPIMG("ID_CBBA5D15FB9943689D358B493082E11D",1) | D14: 君临天下 | E14: effect set_origin = origin_legendary_leader
B15: 13 | C15: =_xlfn.DISPIMG("ID_CBBA5D15FB9943689D358B493082E11D",1) -> =DISPIMG("ID_CBBA5D15FB9943689D358B493082E11D",1) | D15: 统治崩坏 | E15: effect set_origin = origin_legendary_leader_death
B16: 14 | C16: =_xlfn.DISPIMG("ID_CBBA5D15FB9943689D358B493082E11D",1) -> =DISPIMG("ID_CBBA5D15FB9943689D358B493082E11D",1) | D16: 君临天下 | E16: effect set_origin = origin_legendary_leader_imperial
B17: 15 | C17: =_xlfn.DISPIMG("ID_CBBA5D15FB9943689D358B493082E11D",1) -> =DISPIMG("ID_CBBA5D15FB9943689D358B493082E11D",1) | D17: 君临天下 | E17: effect set_origin = origin_legendary_leader_dictatorial
B18: 16 | C18: =_xlfn.DISPIMG("ID_1B823760DEA74E40BAEC52DD16C683B7",1) -> =DISPIMG("ID_1B823760DEA74E40BAEC52DD16C683B7",1) | D18: 血债血偿 | E18: effect set_origin = origin_payback
B19: 17 | C19: =_xlfn.DISPIMG("ID_81BAB8FD039D4105945EB380C423BA09",1) -> =DISPIMG("ID_81BAB8FD039D4105945EB380C423BA09",1) | D19: 粉碎的枷锁 | E19: effect set_origin = origin_broken_shackles
B20: 18 | C20: =_xlfn.DISPIMG("ID_972869EC144142228A8200AD8EFDB194",1) -> =DISPIMG("ID_972869EC144142228A8200AD8EFDB194",1) | D20: 黑暗之怖 | E20: effect set_origin = origin_fear_of_the_dark
B21: 19 | C21: =_xlfn.DISPIMG("ID_FC2405B3018E42BDB187D7468A0BF8B3",1) -> =DISPIMG("ID_FC2405B3018E42BDB187D7468A0BF8B3",1) | D21: 强夺天工 | E21: effect set_origin = origin_overtuned
B22: 20 | C22: =_xlfn.DISPIMG("ID_9E404BBB739648C4A2B7BF0110F04A0B",1) -> =DISPIMG("ID_9E404BBB739648C4A2B7BF0110F04A0B",1) | D22: 毒圣骑士 | E22: effect set_origin = origin_toxic_knights
B23: 21 | C23: =_xlfn.DISPIMG("ID_227E833CEB8441BAAB6CCBEBB9BF8568",1) -> =DISPIMG("ID_227E833CEB8441BAAB6CCBEBB9BF8568",1) | D23: 始祖蜂巢 | E23: effect set_origin = origin_progenitor_hive
B24: 22 | C24: =_xlfn.DISPIMG("ID_797CEF1823504B10904FE1C5107DEAA9",1) -> =DISPIMG("ID_797CEF1823504B10904FE1C5107DEAA9",1) | D24: 地底人 | E24: effect set_origin = origin_subterranean
B25: 23 | C25: =_xlfn.DISPIMG("ID_797CEF1823504B10904FE1C5107DEAA9",1) -> =DISPIMG("ID_797CEF1823504B10904FE1C5107DEAA9",1) | D25: 地底机械 | E25: effect set_origin = origin_subterranean_machines
B26: 24 | C26: =_xlfn.DISPIMG("ID_CF15476BCDFE4FDEAB04D1C2B667CAE3",1) -> =DISPIMG("ID_CF15476BCDFE4FDEAB04D1C2B667CAE3",1) | D26: 射向星际 | E26: effect set_origin = origin_star_slingshot
B27: 25 | C27: =_xlfn.DISPIMG("ID_8F21AA7F4EA94801A28BC999D3DFD927",1) -> =DISPIMG("ID_8F21AA7F4EA94801A28BC999D3DFD927",1) | D27: 虚境导师 | E27: effect set_origin = origin_shroudwalker_apprentice
B28: 26 | C28: =_xlfn.DISPIMG("ID_9A88D5C9337344DDA91EE1E744C2FBC6",1) -> =DISPIMG("ID_9A88D5C9337344DDA91EE1E744C2FBC6",1) | D28: 帝国封邑 | E28: effect set_origin = origin_imperial_vassal
B29: 27 | C29: =_xlfn.DISPIMG("ID_CCD29A8B608641798CDC23F7D544127C",1) -> =DISPIMG("ID_CCD29A8B608641798CDC23F7D544127C",1) | D29: 与龙共舞 | E29: effect set_origin = origin_here_be_dragons
B30: 28 | C30: =_xlfn.DISPIMG("ID_D4AD33B247494EC2B32C0CB0DF2B4700",1) -> =DISPIMG("ID_D4AD33B247494EC2B32C0CB0DF2B4700",1) | D30: 海洋天堂 | E30: effect set_origin = origin_ocean_paradise
B31: 29 | C31: =_xlfn.DISPIMG("ID_D4AD33B247494EC2B32C0CB0DF2B4700",1) -> =DISPIMG("ID_D4AD33B247494EC2B32C0CB0DF2B4700",1) | D31: 水生机械 | E31: effect set_origin = origin_ocean_machines
B32: 30 | C32: =_xlfn.DISPIMG("ID_9832CB664FB94E16B686AE24B40D62C2",1) -> =DISPIMG("ID_9832CB664FB94E16B686AE24B40D62C2",1) | D32: 食尸文化 | E32: effect set_origin = origin_necrophage
B33: 31 | C33: =_xlfn.DISPIMG("ID_77323DCEAAD24CDBBC78DF1B1606E783",1) -> =DISPIMG("ID_77323DCEAAD24CDBBC78DF1B1606E783",1) | D33: 复国孑遗 | E33: effect set_origin = origin_remnants
B34: 32 | C34: =_xlfn.DISPIMG("ID_BF9764949579409A9BADE34AD39A674A",1) -> =DISPIMG("ID_BF9764949579409A9BADE34AD39A674A",1) | D34: 破碎之环 | E34: effect set_origin = origin_shattered_ring
B35: 33 | C35: =_xlfn.DISPIMG("ID_D1A529F9B8614C0B86B3BBFE063F7348",1) -> =DISPIMG("ID_D1A529F9B8614C0B86B3BBFE063F7348",1) | D35: 虚空居者 | E35: effect set_origin = origin_void_dwellers
B36: 34 | C36: =_xlfn.DISPIMG("ID_D1A529F9B8614C0B86B3BBFE063F7348",1) -> =DISPIMG("ID_D1A529F9B8614C0B86B3BBFE063F7348",1) | D36: 虚空机者 | E36: effect set_origin = origin_void_machines
B37: 35 | C37: =_xlfn.DISPIMG("ID_0E37D43532F449039F1B9150FA6B2ED0",1) -> =DISPIMG("ID_0E37D43532F449039F1B9150FA6B2ED0",1) | D37: 先辈子弟 | E37: effect set_origin = origin_scion
B38: 36 | C38: =_xlfn.DISPIMG("ID_9790ABDA5F71421DA2BB323BB41F7A75",1) -> =DISPIMG("ID_9790ABDA5F71421DA2BB323BB41F7A75",1) | D38: 屹于巨人之肩 | E38: effect set_origin = origin_shoulders_of_giants
B39: 37 | C39: =_xlfn.DISPIMG("ID_194C40BF6D3747AFAD1A8236B73FC810",1) -> =DISPIMG("ID_194C40BF6D3747AFAD1A8236B73FC810",1) | D39: 共同命运 | E39: effect set_origin = origin_common_ground
B40: 38 | C40: =_xlfn.DISPIMG("ID_267DDCEE82F54E24B98F4389DE3AF528",1) -> =DISPIMG("ID_267DDCEE82F54E24B98F4389DE3AF528",1) | D40: 一方霸主 | E40: effect set_origin = origin_hegemon
B41: 39 | C41: =_xlfn.DISPIMG("ID_C604A08ED0404BCD945E2B9AB7F336DE",1) -> =DISPIMG("ID_C604A08ED0404BCD945E2B9AB7F336DE",1) | D41: 末日降临 | E41: effect set_origin = origin_doomsday
B42: 40 | C42: =_xlfn.DISPIMG("ID_EA76FD7735184A5D9D96D44B18482597",1) -> =DISPIMG("ID_EA76FD7735184A5D9D96D44B18482597",1) | D42: 降世灾星 | E42: effect set_origin = origin_lithoid
B43: 41 | C43: =_xlfn.DISPIMG("ID_F7AE890A7D384346B0907ABF69E4648A",1) -> =DISPIMG("ID_F7AE890A7D384346B0907ABF69E4648A",1) | D43: 生命之籽 | E43: effect set_origin = origin_life_seeded
B44: 42 | C44: =_xlfn.DISPIMG("ID_1188E34C10FD4DA79A938B48D96E3DC6",1) -> =DISPIMG("ID_1188E34C10FD4DA79A938B48D96E3DC6",1) | D44: 后启示录 | E44: effect set_origin = origin_post_apocalyptic
B45: 43 | C45: =_xlfn.DISPIMG("ID_1188E34C10FD4DA79A938B48D96E3DC6",1) -> =DISPIMG("ID_1188E34C10FD4DA79A938B48D96E3DC6",1) | D45: 辐射漫游机 | E45: effect set_origin = origin_post_apocalyptic_machines
B46: 44 | C46: =_xlfn.DISPIMG("ID_3EAEF9CC1D224576B4467D0002FD0ED1",1) -> =DISPIMG("ID_3EAEF9CC1D224576B4467D0002FD0ED1",1) | D46: 克隆大军 | E46: effect set_origin = origin_clone_army
B47: 45 | C47: =_xlfn.DISPIMG("ID_E8BD1C0A7B0248CAB67072690E9912FA",1) -> =DISPIMG("ID_E8BD1C0A7B0248CAB67072690E9912FA",1) | D47: 资源统合 | E47: effect set_origin = origin_machine
B48: 46 | C48: =_xlfn.DISPIMG("ID_D681CB914CBB408A8E8EBEFC87E93206",1) -> =DISPIMG("ID_D681CB914CBB408A8E8EBEFC87E93206",1) | D48: 强制重置 | E48: effect set_origin = origin_unplugged
B49: 47 | C49: =_xlfn.DISPIMG("ID_8D3DF543062341B1B7E841EC2D727A3C",1) -> =DISPIMG("ID_8D3DF543062341B1B7E841EC2D727A3C",1) | D49: 机械师 | E49: effect set_origin = origin_mechanists
B50: 48 | C50: =_xlfn.DISPIMG("ID_69B86A5A83DB49DB92472A3D1E018806",1) -> =DISPIMG("ID_69B86A5A83DB49DB92472A3D1E018806",1) | D50: 协同进化 | E50: effect set_origin = origin_syncretic_evolution
B51: 49 | C51: =_xlfn.DISPIMG("ID_C2EADD0DBFA742D78650D18076D675B4",1) -> =DISPIMG("ID_C2EADD0DBFA742D78650D18076D675B4",1) | D51: 生命之树 | E51: effect set_origin = origin_tree_of_life
B52: 50 | C52: =_xlfn.DISPIMG("ID_FECDBF8991EC4D25838A9E12E20877D9",1) -> =DISPIMG("ID_FECDBF8991EC4D25838A9E12E20877D9",1) | D52: 硕果协作 | E52: effect set_origin = origin_fruitful
B53: 51 | C53: =_xlfn.DISPIMG("ID_51557E8DE1B5447FAC8DBD03185B60FE",1) -> =DISPIMG("ID_51557E8DE1B5447FAC8DBD03185B60FE",1) | D53: 繁星门阶 | E53: effect set_origin = origin_galactic_doorstep
B54: 52 | C54: =_xlfn.DISPIMG("ID_AC84418D3EDB47FFB40B1BDEA567FD9A",1) -> =DISPIMG("ID_AC84418D3EDB47FFB40B1BDEA567FD9A",1) | D54: 失落行星 | E54: effect set_origin = origin_lost_colony
A55: 玩家 不可选 | B55: 1 | C55: =_xlfn.DISPIMG("ID_A23F54321B6A4F49A19D65DE2085C6B6",1) -> =DISPIMG("ID_A23F54321B6A4F49A19D65DE2085C6B6",1) | D55: 长者之裔 | E55: effect set_origin = origin_fallen_empire
B56: 2 | C56: =_xlfn.DISPIMG("ID_A23F54321B6A4F49A19D65DE2085C6B6",1) -> =DISPIMG("ID_A23F54321B6A4F49A19D65DE2085C6B6",1) | D56: 长者之裔 | E56: effect set_origin = origin_fallen_empire_hive
B57: 3 | C57: =_xlfn.DISPIMG("ID_827B9F01FD11489D99EA435943DE97E2",1) -> =DISPIMG("ID_827B9F01FD11489D99EA435943DE97E2",1) | D57: 启蒙开化 | E57: effect set_origin = origin_enlightened
B58: 4 | C58: =_xlfn.DISPIMG("ID_8B75C4E031F4453A922BBDE2CC44A494",1) -> =DISPIMG("ID_8B75C4E031F4453A922BBDE2CC44A494",1) | D58: 发展中文明 | E58: effect set_origin = origin_default_pre_ftl
B59: 5 | C59: =_xlfn.DISPIMG("ID_E11B133684824DA1AC2ABAED10F9ADB3",1) -> =DISPIMG("ID_E11B133684824DA1AC2ABAED10F9ADB3",1) | D59: 分离主义者 | E59: effect set_origin = origin_separatists
B60: 6 | C60: =_xlfn.DISPIMG("ID_E11B133684824DA1AC2ABAED10F9ADB3",1) -> =DISPIMG("ID_E11B133684824DA1AC2ABAED10F9ADB3",1) | D60: 赢得解放 | E60: effect set_origin = origin_liberated
B61: 7 | C61: =_xlfn.DISPIMG("ID_E11B133684824DA1AC2ABAED10F9ADB3",1) -> =DISPIMG("ID_E11B133684824DA1AC2ABAED10F9ADB3",1) | D61: 恶魔侵军 | E61: effect set_origin = origin_demonic_incursion
B62: 8 | C62: =_xlfn.DISPIMG("ID_CF9E1E7F09B546D182EB7E4ACC489463",1) -> =DISPIMG("ID_CF9E1E7F09B546D182EB7E4ACC489463",1) | D62: 可汗的继业者 | E62: effect set_origin = origin_khan_successor
B63: 9 | C63: =_xlfn.DISPIMG("ID_F7AE890A7D384346B0907ABF69E4648A",1) -> =DISPIMG("ID_F7AE890A7D384346B0907ABF69E4648A",1) | D63: 生命之籽 | E63: effect set_origin = origin_life_seeded_ai_only
B64: 10 | C64: =_xlfn.DISPIMG("ID_194C40BF6D3747AFAD1A8236B73FC810",1) -> =DISPIMG("ID_194C40BF6D3747AFAD1A8236B73FC810",1) | D64: 共同命运 | E64: effect set_origin = origin_common_ground_npc
B65: 11 | C65: =_xlfn.DISPIMG("ID_267DDCEE82F54E24B98F4389DE3AF528",1) -> =DISPIMG("ID_267DDCEE82F54E24B98F4389DE3AF528",1) | D65: 霸主部从 | E65: effect set_origin = origin_hegemon_npc
B66: 12 | C66: =_xlfn.DISPIMG("ID_9A88D5C9337344DDA91EE1E744C2FBC6",1) -> =DISPIMG("ID_9A88D5C9337344DDA91EE1E744C2FBC6",1) | D66: 帝国领主 | E66: effect set_origin = origin_imperial_vassal_overlord
B67: 13 | C67: =_xlfn.DISPIMG("ID_6A4CB4E12E9248A69CE4354C5452E5FA",1) -> =DISPIMG("ID_6A4CB4E12E9248A69CE4354C5452E5FA",1) | D67: 通天之梯 | E67: effect set_origin = origin_slavers

Sheet 国策
A1: 4.0.21国策代码（2025.07.27）
A2: 注：国策超过上限可以生效，但未满足条件的国策不会生效（除非开启free_government），添加已有国策可能会导致报错。
A3: 普政 | D3: 蜂巢 | E3: 智械 | F3: 企业 | G3: 其他
A4: 类型 | B4: 序号 | C4: 名称 | D4: 添加代码 | F4: 移除代码 | H4: key
A5: 普政 | B5: 1 | C5: 徭役制 | D5: ="effect force_add_civic = "&H5 -> effect force_add_civic = civic_corvee_system | F5: ="effect force_remove_civic = "&H5 -> effect force_remove_civic = civic_corvee_system | H5: civic_corvee_system
B6: 2 | C6: 帝国信仰 | D6: ="effect force_add_civic = "&H6 -> effect force_add_civic = civic_imperial_cult | F6: ="effect force_remove_civic = "&H6 -> effect force_remove_civic = civic_imperial_cult | H6: civic_imperial_cult
B7: 3 | C7: 自由灯塔 | D7: ="effect force_add_civic = "&H7 -> effect force_add_civic = civic_beacon_of_liberty | F7: ="effect force_remove_civic = "&H7 -> effect force_remove_civic = civic_beacon_of_liberty | H7: civic_beacon_of_liberty
B8: 4 | C8: 崇高圣职 | D8: ="effect force_add_civic = "&H8 -> effect force_add_civic = civic_exalted_priesthood | F8: ="effect force_remove_civic = "&H8 -> effect force_remove_civic = civic_exalted_priesthood | H8: civic_exalted_priesthood
B9: 5 | C9: 哲人王 | D9: ="effect force_add_civic = "&H9 -> effect force_add_civic = civic_philosopher_king | F9: ="effect force_remove_civic = "&H9 -> effect force_remove_civic = civic_philosopher_king | H9: civic_philosopher_king
B10: 6 | C10: 精英政治 | D10: ="effect force_add_civic = "&H10 -> effect force_add_civic = civic_meritocracy | F10: ="effect force_remove_civic = "&H10 -> effect force_remove_civic = civic_meritocracy | H10: civic_meritocracy
B11: 7 | C11: 公民兵役 | D11: ="effect force_add_civic = "&H11 -> effect force_add_civic = civic_citizen_service | F11: ="effect force_remove_civic = "&H11 -> effect force_remove_civic = civic_citizen_service | H11: civic_citizen_service
B12: 8 | C12: 技术治国 | D12: ="effect force_add_civic = "&H12 -> effect force_add_civic = civic_technocracy | F12: ="effect force_remove_civic = "&H12 -> effect force_remove_civic = civic_technocracy | H12: civic_technocracy
B13: 9 | C13: 封建社会 | D13: ="effect force_add_civic = "&H13 -> effect force_add_civic = civic_feudal_realm | F13: ="effect force_remove_civic = "&H13 -> effect force_remove_civic = civic_feudal_realm | H13: civic_feudal_realm
B14: 10 | C14: 警察国度 | D14: ="effect force_add_civic = "&H14 -> effect force_add_civic = civic_police_state | F14: ="effect force_remove_civic = "&H14 -> effect force_remove_civic = civic_police_state | H14: civic_police_state
B15: 11 | C15: 理想本心 | D15: ="effect force_add_civic = "&H15 -> effect force_add_civic = civic_idealistic_foundation | F15: ="effect force_remove_civic = "&H15 -> effect force_remove_civic = civic_idealistic_foundation | H15: civic_idealistic_foundation
B16: 12 | C16: 环保主义者 | D16: ="effect force_add_civic = "&H16 -> effect force_add_civic = civic_environmentalist | F16: ="effect force_remove_civic = "&H16 -> effect force_remove_civic = civic_environmentalist | H16: civic_environmentalist
B17: 13 | C17: 奴贩公会 | D17: ="effect force_add_civic = "&H17 -> effect force_add_civic = civic_slaver_guilds | F17: ="effect force_remove_civic = "&H17 -> effect force_remove_civic = civic_slaver_guilds | H17: civic_slaver_guilds
... B75: 71 | C75: 公民教育 | D75: ="effect force_add_civic = "&H75 -> effect force_add_civic = civic_civil_education | F75: ="effect force_remove_civic = "&H75 -> effect force_remove_civic = civic_civil_education | H75: civic_civil_education
A76: 蜂巢 | B76: 1 | C76: 亚空间突触 | D76: ="effect force_add_civic = "&H76 -> effect force_add_civic = civic_hive_subspace_ephapse | F76: ="effect force_remove_civic = "&H76 -> effect force_remove_civic = civic_hive_subspace_ephapse | H76: civic_hive_subspace_ephapse
B77: 2 | C77: 天然神经网络 | D77: ="effect force_add_civic = "&H77 -> effect force_add_civic = civic_hive_natural_neural_network | F77: ="effect force_remove_civic = "&H77 -> effect force_remove_civic = civic_hive_natural_neural_network | H77: civic_hive_natural_neural_network
B78: 3 | C78: 禁欲主义 | D78: ="effect force_add_civic = "&H78 -> effect force_add_civic = civic_hive_ascetic | F78: ="effect force_remove_civic = "&H78 -> effect force_remove_civic = civic_hive_ascetic | H78: civic_hive_ascetic
B79: 4 | C79: 唯一意志 | D79: ="effect force_add_civic = "&H79 -> effect force_add_civic = civic_hive_one_mind | F79: ="effect force_remove_civic = "&H79 -> effect force_remove_civic = civic_hive_one_mind | H79: civic_hive_one_mind
B80: 5 | C80: 一心多用 | D80: ="effect force_add_civic = "&H80 -> effect force_add_civic = civic_hive_divided_attention | F80: ="effect force_remove_civic = "&H80 -> effect force_remove_civic = civic_hive_divided_attention | H80: civic_hive_divided_attention
B81: 6 | C81: 军团之威 | D81: ="effect force_add_civic = "&H81 -> effect force_add_civic = civic_hive_strength_of_legions | F81: ="effect force_remove_civic = "&H81 -> effect force_remove_civic = civic_hive_strength_of_legions | H81: civic_hive_strength_of_legions
B82: 7 | C82: 意志整合 | D82: ="effect force_add_civic = "&H82 -> effect force_add_civic = civic_hive_subsumed_will | F82: ="effect force_remove_civic = "&H82 -> effect force_remove_civic = civic_hive_subsumed_will | H82: civic_hive_subsumed_will
B83: 8 | C83: 集中知识 | D83: ="effect force_add_civic = "&H83 -> effect force_add_civic = civic_hive_pooled_knowledge | F83: ="effect force_remove_civic = "&H83 -> effect force_remove_civic = civic_hive_pooled_knowledge | H83: civic_hive_pooled_knowledge
B84: 9 | C84: 噬杀蜂群 | D84: ="effect force_add_civic = "&H84 -> effect force_add_civic = civic_hive_devouring_swarm | F84: ="effect force_remove_civic = "&H84 -> effect force_remove_civic = civic_hive_devouring_swarm | H84: civic_hive_devouring_swarm
B85: 10 | C85: 心有灵犀 | D85: ="effect force_add_civic = "&H85 -> effect force_add_civic = civic_hive_empath | F85: ="effect force_remove_civic = "&H85 -> effect force_remove_civic = civic_hive_empath | H85: civic_hive_empath
B86: 11 | C86: 记念主义 | D86: ="effect force_add_civic = "&H86 -> effect force_add_civic = civic_hive_memorialist | F86: ="effect force_remove_civic = "&H86 -> effect force_remove_civic = civic_hive_memorialist | H86: civic_hive_memorialist
B87: 12 | C87: 有机再加工 | D87: ="effect force_add_civic = "&H87 -> effect force_add_civic = civic_hive_catalytic_processing | F87: ="effect force_remove_civic = "&H87 -> effect force_remove_civic = civic_hive_catalytic_processing | H87: civic_hive_catalytic_processing
B88: 13 | C88: 菌根理想 | D88: ="effect force_add_civic = "&H88 -> effect force_add_civic = civic_hive_idyllic_bloom | F88: ="effect force_remove_civic = "&H88 -> effect force_remove_civic = civic_hive_idyllic_bloom | H88: civic_hive_idyllic_bloom
... B107: 32 | C107: 寄生兽 | D107: ="effect force_add_civic = "&H107 -> effect force_add_civic = civic_hive_bodysnatcher | F107: ="effect force_remove_civic = "&H107 -> effect force_remove_civic = civic_hive_bodysnatcher | H107: civic_hive_bodysnatcher
A108: 智械 | B108: 1 | C108: 失控机仆 | D108: ="effect force_add_civic = "&H108 -> effect force_add_civic = civic_machine_servitor | F108: ="effect force_remove_civic = "&H108 -> effect force_remove_civic = civic_machine_servitor | H108: civic_machine_servitor
B109: 2 | C109: 铁心灭绝者 | D109: ="effect force_add_civic = "&H109 -> effect force_add_civic = civic_machine_terminator | F109: ="effect force_remove_civic = "&H109 -> effect force_remove_civic = civic_machine_terminator | H109: civic_machine_terminator
B110: 3 | C110: 同化斗士 | D110: ="effect force_add_civic = "&H110 -> effect force_add_civic = civic_machine_assimilator | F110: ="effect force_remove_civic = "&H110 -> effect force_remove_civic = civic_machine_assimilator | H110: civic_machine_assimilator
B111: 4 | C111: 施工机器人 | D111: ="effect force_add_civic = "&H111 -> effect force_add_civic = civic_machine_builder | F111: ="effect force_remove_civic = "&H111 -> effect force_remove_civic = civic_machine_builder | H111: civic_machine_builder
B112: 5 | C112: 超负荷工厂 | D112: ="effect force_add_civic = "&H112 -> effect force_add_civic = civic_machine_factory_overclock | F112: ="effect force_remove_civic = "&H112 -> effect force_remove_civic = civic_machine_factory_overclock | H112: civic_machine_factory_overclock
B113: 6 | C113: 一体化 | D113: ="effect force_add_civic = "&H113 -> effect force_add_civic = civic_machine_unitary_cohesion | F113: ="effect force_remove_civic = "&H113 -> effect force_remove_civic = civic_machine_unitary_cohesion | H113: civic_machine_unitary_cohesion
B114: 7 | C114: 碎岩机 | D114: ="effect force_add_civic = "&H114 -> effect force_add_civic = civic_machine_rockbreakers | F114: ="effect force_remove_civic = "&H114 -> effect force_remove_civic = civic_machine_rockbreakers | H114: civic_machine_rockbreakers
B115: 8 | C115: 零废弃物协议 | D115: ="effect force_add_civic = "&H115 -> effect force_add_civic = civic_machine_zero_waste_protocols | F115: ="effect force_remove_civic = "&H115 -> effect force_remove_civic = civic_machine_zero_waste_protocols | H115: civic_machine_zero_waste_protocols
B116: 9 | C116: 强力续航 | D116: ="effect force_add_civic = "&H116 -> effect force_add_civic = civic_machine_built_to_last | F116: ="effect force_remove_civic = "&H116 -> effect force_remove_civic = civic_machine_built_to_last | H116: civic_machine_built_to_last
B117: 10 | C117: 空中下载升级 | D117: ="effect force_add_civic = "&H117 -> effect force_add_civic = civic_machine_ota_updates | F117: ="effect force_remove_civic = "&H117 -> effect force_remove_civic = civic_machine_ota_updates | H117: civic_machine_ota_updates
B118: 11 | C118: 战争机器 | D118: ="effect force_add_civic = "&H118 -> effect force_add_civic = civic_machine_warbots | F118: ="effect force_remove_civic = "&H118 -> effect force_remove_civic = civic_machine_warbots | H118: civic_machine_warbots
B119: 12 | C119: 自检 | D119: ="effect force_add_civic = "&H119 -> effect force_add_civic = civic_machine_introspective | F119: ="effect force_remove_civic = "&H119 -> effect force_remove_civic = civic_machine_introspective | H119: civic_machine_introspective
B120: 13 | C120: 模块化功能 | D120: ="effect force_add_civic = "&H120 -> effect force_add_civic = civic_machine_delegated_functions | F120: ="effect force_remove_civic = "&H120 -> effect force_remove_civic = civic_machine_delegated_functions | H120: civic_machine_delegated_functions
... B143: 36 | C143: 顽强网络 | D143: ="effect force_add_civic = "&H143 -> effect force_add_civic = civic_machine_stalwart_network | F143: ="effect force_remove_civic = "&H143 -> effect force_remove_civic = civic_machine_stalwart_network | H143: civic_machine_stalwart_network
A144: 企业 | B144: 1 | C144: 特许经营 | D144: ="effect force_add_civic = "&H144 -> effect force_add_civic = civic_franchising | F144: ="effect force_remove_civic = "&H144 -> effect force_remove_civic = civic_franchising | H144: civic_franchising
B145: 2 | C145: 交易所 | D145: ="effect force_add_civic = "&H145 -> effect force_add_civic = civic_trading_posts | F145: ="effect force_remove_civic = "&H145 -> effect force_remove_civic = civic_trading_posts | H145: civic_trading_posts
B146: 3 | C146: 传媒集团 | D146: ="effect force_add_civic = "&H146 -> effect force_add_civic = civic_media_conglomerate | F146: ="effect force_remove_civic = "&H146 -> effect force_remove_civic = civic_media_conglomerate | H146: civic_media_conglomerate
B147: 4 | C147: 舰队承包商 | D147: ="effect force_add_civic = "&H147 -> effect force_add_civic = civic_naval_contractors | F147: ="effect force_remove_civic = "&H147 -> effect force_remove_civic = civic_naval_contractors | H147: civic_naval_contractors
B148: 5 | C148: 自由商人 | D148: ="effect force_add_civic = "&H148 -> effect force_add_civic = civic_free_traders | F148: ="effect force_remove_civic = "&H148 -> effect force_remove_civic = civic_free_traders | H148: civic_free_traders
B149: 6 | C149: 民营勘探者 | D149: ="effect force_add_civic = "&H149 -> effect force_add_civic = civic_private_prospectors | F149: ="effect force_remove_civic = "&H149 -> effect force_remove_civic = civic_private_prospectors | H149: civic_private_prospectors
B150: 7 | C150: 百姓福音 | D150: ="effect force_add_civic = "&H150 -> effect force_add_civic = civic_gospel_of_the_masses | F150: ="effect force_remove_civic = "&H150 -> effect force_remove_civic = civic_gospel_of_the_masses | H150: civic_gospel_of_the_masses
B151: 8 | C151: 恶性竞争 | D151: ="effect force_add_civic = "&H151 -> effect force_add_civic = civic_ruthless_competition | F151: ="effect force_remove_civic = "&H151 -> effect force_remove_civic = civic_ruthless_competition | H151: civic_ruthless_competition
B152: 9 | C152: 罪犯世家 | D152: ="effect force_add_civic = "&H152 -> effect force_add_civic = civic_criminal_heritage | F152: ="effect force_remove_civic = "&H152 -> effect force_remove_civic = civic_criminal_heritage | H152: civic_criminal_heritage
B153: 10 | C153: 私营军事公司 | D153: ="effect force_add_civic = "&H153 -> effect force_add_civic = civic_private_military_companies | F153: ="effect force_remove_civic = "&H153 -> effect force_remove_civic = civic_private_military_companies | H153: civic_private_military_companies
B154: 11 | C154: 契约资产 | D154: ="effect force_add_civic = "&H154 -> effect force_add_civic = civic_indentured_assets | F154: ="effect force_remove_civic = "&H154 -> effect force_remove_civic = civic_indentured_assets | H154: civic_indentured_assets
B155: 12 | C155: 品牌忠诚 | D155: ="effect force_add_civic = "&H155 -> effect force_add_civic = civic_brand_loyalty | F155: ="effect force_remove_civic = "&H155 -> effect force_remove_civic = civic_brand_loyalty | H155: civic_brand_loyalty
B156: 13 | C156: 公共关系专家 | D156: ="effect force_add_civic = "&H156 -> effect force_add_civic = civic_public_relations_specialists | F156: ="effect force_remove_civic = "&H156 -> effect force_remove_civic = civic_public_relations_specialists | H156: civic_public_relations_specialists
... B187: 44 | C187: 分布式研发 | D187: ="effect force_add_civic = "&H187 -> effect force_add_civic = civic_corporate_crowdsourcing | F187: ="effect force_remove_civic = "&H187 -> effect force_remove_civic = civic_corporate_crowdsourcing | H187: civic_corporate_crowdsourcing
A188: 其他 | B188: 1 | C188: 失落机械智能 | D188: ="effect force_add_civic = "&H188 -> effect force_add_civic = civic_machine_remnants | F188: ="effect force_remove_civic = "&H188 -> effect force_remove_civic = civic_machine_remnants | H188: civic_machine_remnants
B189: 2 | C189: 监护矩阵 | D189: ="effect force_add_civic = "&H189 -> effect force_add_civic = civic_custodian_directives | F189: ="effect force_remove_civic = "&H189 -> effect force_remove_civic = civic_custodian_directives | H189: civic_custodian_directives
B190: 3 | C190: 重启的监护矩阵 | D190: ="effect force_add_civic = "&H190 -> effect force_add_civic = civic_awakened_machine | F190: ="effect force_remove_civic = "&H190 -> effect force_remove_civic = civic_awakened_machine | H190: civic_awakened_machine
B191: 4 | C191: 崩坏的防御指令 | D191: ="effect force_add_civic = "&H191 -> effect force_add_civic = civic_malfunctioning_custodian | F191: ="effect force_remove_civic = "&H191 -> effect force_remove_civic = civic_malfunctioning_custodian | H191: civic_malfunctioning_custodian
B192: 5 | C192: 最终防御指令 | D192: ="effect force_add_civic = "&H192 -> effect force_add_civic = civic_final_defense_protocols | F192: ="effect force_remove_civic = "&H192 -> effect force_remove_civic = civic_final_defense_protocols | H192: civic_final_defense_protocols
B193: 6 | C193: 暮气沉沉的领袖 | D193: ="effect force_add_civic = "&H193 -> effect force_add_civic = civic_lethargic_leadership | F193: ="effect force_remove_civic = "&H193 -> effect force_remove_civic = civic_lethargic_leadership | H193: civic_lethargic_leadership
B194: 7 | C194: 衰落的帝国 | D194: ="effect force_add_civic = "&H194 -> effect force_add_civic = civic_empire_in_decline | F194: ="effect force_remove_civic = "&H194 -> effect force_remove_civic = civic_empire_in_decline | H194: civic_empire_in_decline
B195: 8 | C195: 老者思维 | D195: ="effect force_add_civic = "&H195 -> effect force_add_civic = civic_antediluvian_mind | F195: ="effect force_remove_civic = "&H195 -> effect force_remove_civic = civic_antediluvian_mind | H195: civic_antediluvian_mind
B196: 9 | C196: 松弛子个体 | D196: ="effect force_add_civic = "&H196 -> effect force_add_civic = civic_sluggish_drones | F196: ="effect force_remove_civic = "&H196 -> effect force_remove_civic = civic_sluggish_drones | H196: civic_sluggish_drones
B197: 10 | C197: 破碎指令 | D197: ="effect force_add_civic = "&H197 -> effect force_add_civic = civic_fragmented_command | F197: ="effect force_remove_civic = "&H197 -> effect force_remove_civic = civic_fragmented_command | H197: civic_fragmented_command
B198: 11 | C198: 超好斗工蜂 | D198: ="effect force_add_civic = "&H198 -> effect force_add_civic = civic_hyper_aggressive_drones | F198: ="effect force_remove_civic = "&H198 -> effect force_remove_civic = civic_hyper_aggressive_drones | H198: civic_hyper_aggressive_drones
B199: 12 | C199: 不稳定工蜂 | D199: ="effect force_add_civic = "&H199 -> effect force_add_civic = civic_unstable_drones | F199: ="effect force_remove_civic = "&H199 -> effect force_remove_civic = civic_unstable_drones | H199: civic_unstable_drones
B200: 13 | C200: 无自主工蜂 | D200: ="effect force_add_civic = "&H200 -> effect force_add_civic = civic_stunted_drones | F200: ="effect force_remove_civic = "&H200 -> effect force_remove_civic = civic_stunted_drones | H200: civic_stunted_drones
... B234: 47 | C234: 天选帝君 | D234: ="effect force_add_civic = "&H234 -> effect force_add_civic = civic_psionic_sovereign | F234: ="effect force_remove_civic = "&H234 -> effect force_remove_civic = civic_psionic_sovereign | H234: civic_psionic_sovereign
B235: 48 | D235: ="effect force_add_civic = "&H235 -> effect force_add_civic = civic_caravaneer_caravansary | F235: ="effect force_remove_civic = "&H235 -> effect force_remove_civic = civic_caravaneer_caravansary | H235: civic_caravaneer_caravansary
B236: 49 | C236: 奥伦无顶金字塔 | D236: ="effect force_add_civic = "&H236 -> effect force_add_civic = civic_caravaneer_fleet1 | F236: ="effect force_remove_civic = "&H236 -> effect force_remove_civic = civic_caravaneer_fleet1 | H236: civic_caravaneer_fleet1
B237: 50 | C237: 贸易圣职 | D237: ="effect force_add_civic = "&H237 -> effect force_add_civic = civic_caravaneer_fleet2 | F237: ="effect force_remove_civic = "&H237 -> effect force_remove_civic = civic_caravaneer_fleet2 | H237: civic_caravaneer_fleet2
B238: 51 | C238: 绝对商品化者 | D238: ="effect force_add_civic = "&H238 -> effect force_add_civic = civic_caravaneer_fleet3 | F238: ="effect force_remove_civic = "&H238 -> effect force_remove_civic = civic_caravaneer_fleet3 | H238: civic_caravaneer_fleet3

Sheet 传统
A1: 4.0.21传统代码（2025.07.27）
A2: 添加/移除代码 | D2: add_tradition | F2: 注：代码生成的传统可超过7传统上限但不显示实际生效；克隆纯净变异的可变传统通过flag识别，替换成相应的传统；基因重塑传统模型不在传统树中，正常生效但会加载一个异常传统树。 | I2: 可变传统更改
A3: 适应 | C3: 天赋 | D3: 博物 | E3: 外交 | F3: 探索 | G3: 驯化 | H3: 支配 | I3: 敌意
A4: 扩张 | C4: 和谐 | D4: 后勤 | E4: 经贸 | F4: 权术 | G4: 繁荣 | H4: 治国 | I4: 密谋
A5: 至高 | C5: 同调 | D5: 不屈 | E5: 普适 | F5: 克隆 | G5: 义体（普政蜂巢） | H5: 义体（同化） | I5: 基因（无DLC）
A6: 模组 | C6: 变异 | D6: 纳米 | E6: 灵能 | F6: 纯净 | G6: 合成 | H6: 虚拟 | I6: 基因传统模型
A7: 类型 | B7: 名称 | C7: 备注名称 | D7: 自适应代码 | G7: 合并 | I7: key
A8: 适应 | B8: 适应传统 | D8: =_xlfn.CONCAT("effect = { ",$D$2," = ",I8," }") -> effect = { add_tradition = tr_adaptability_adopt } | G8: =_xlfn.CONCAT("effect = { ",$D$2," = ",I8," ",$D$2," = ",I9," ",$D$2," = ",I10," ",$D$2," = ",I11," ",$D$2," = ",I12," ",$D$2," = ",I13," ",$D$2," = ",I14,"}") -> effect = { add_tradition = tr_adaptability_adopt add_tradition = tr_adaptability_recycling add_tradition = tr_adaptability_survival_fittest add_tradition = tr_adaptability_environmental_diversification add_tradition = tr_adaptability_adaptive_ecology add_tradition = tr_adaptability_appropriation add_tradition = tr_adaptability_finish} | I8: tr_adaptability_adopt
B9: 强化回收 | D9: =_xlfn.CONCAT("effect = { ",$D$2," = ",I9," }") -> effect = { add_tradition = tr_adaptability_recycling } | I9: tr_adaptability_recycling
B10: 适者生存 | D10: =_xlfn.CONCAT("effect = { ",$D$2," = ",I10," }") -> effect = { add_tradition = tr_adaptability_survival_fittest } | I10: tr_adaptability_survival_fittest
B11: 环境多样化 | D11: =_xlfn.CONCAT("effect = { ",$D$2," = ",I11," }") -> effect = { add_tradition = tr_adaptability_environmental_diversification } | I11: tr_adaptability_environmental_diversification
B12: 适应性生态学 | D12: =_xlfn.CONCAT("effect = { ",$D$2," = ",I12," }") -> effect = { add_tradition = tr_adaptability_adaptive_ecology } | I12: tr_adaptability_adaptive_ecology
B13: 人口发配 | C13: 发配（荒野） | D13: =_xlfn.CONCAT("effect = { ",$D$2," = ",I13," }") -> effect = { add_tradition = tr_adaptability_appropriation } | I13: tr_adaptability_appropriation
B14: 适应传统完成 | D14: =_xlfn.CONCAT("effect = { ",$D$2," = ",I14," }") -> effect = { add_tradition = tr_adaptability_finish } | I14: tr_adaptability_finish
A15: 天赋 | B15: 天赋传统 | D15: =_xlfn.CONCAT("effect = { ",$D$2," = ",I15," }") -> effect = { add_tradition = tr_aptitude_adopt } | G15: =_xlfn.CONCAT("effect = { ",$D$2," = ",I15," ",$D$2," = ",I16," ",$D$2," = ",I17," ",$D$2," = ",I18," ",$D$2," = ",I19," ",$D$2," = ",I20," ",$D$2," = ",I21,"}") -> effect = { add_tradition = tr_aptitude_adopt add_tradition = tr_aptitude_the_empire_needs_you add_tradition = tr_aptitude_specialist_training add_tradition = tr_aptitude_psychological_profiling add_tradition = tr_aptitude_healthcare_program add_tradition = tr_aptitude_champions_of_the_empire add_tradition = tr_aptitude_finish} | I15: tr_aptitude_adopt
B16: 帝国需要你！ | D16: =_xlfn.CONCAT("effect = { ",$D$2," = ",I16," }") -> effect = { add_tradition = tr_aptitude_the_empire_needs_you } | I16: tr_aptitude_the_empire_needs_you
B17: 专长训练 | D17: =_xlfn.CONCAT("effect = { ",$D$2," = ",I17," }") -> effect = { add_tradition = tr_aptitude_specialist_training } | I17: tr_aptitude_specialist_training
B18: 心理分析 | C18: 行为学诊断（蜂巢），记忆体诊断（智械） | D18: =_xlfn.CONCAT("effect = { ",$D$2," = ",I18," }") -> effect = { add_tradition = tr_aptitude_psychological_profiling } | I18: tr_aptitude_psychological_profiling
B19: 健保计划 | C19: 躯体维护（蜂巢），预防性维护（智械） | D19: =_xlfn.CONCAT("effect = { ",$D$2," = ",I19," }") -> effect = { add_tradition = tr_aptitude_healthcare_program } | I19: tr_aptitude_healthcare_program
B20: 帝国先锋 | D20: =_xlfn.CONCAT("effect = { ",$D$2," = ",I20," }") -> effect = { add_tradition = tr_aptitude_champions_of_the_empire } | I20: tr_aptitude_champions_of_the_empire
B21: 天赋传统完成 | D21: =_xlfn.CONCAT("effect = { ",$D$2," = ",I21," }") -> effect = { add_tradition = tr_aptitude_finish } | I21: tr_aptitude_finish
A22: 博物 | B22: 博物传统 | D22: =_xlfn.CONCAT("effect = { ",$D$2," = ",I22," }") -> effect = { add_tradition = tr_archivism_adopt } | G22: =_xlfn.CONCAT("effect = { ",$D$2," = ",I22," ",$D$2," = ",I23," ",$D$2," = ",I24," ",$D$2," = ",I25," ",$D$2," = ",I26," ",$D$2," = ",I27," ",$D$2," = ",I28,"}") -> effect = { add_tradition = tr_archivism_adopt add_tradition = tr_archivism_xeno_paleontology add_tradition = tr_archivism_expert_negociation add_tradition = tr_archivism_frontier_archaeology add_tradition = tr_archivism_flawless_display add_tradition = tr_archivism_exhibition_specialization add_tradition = tr_archivism_finish} | I22: tr_archivism_adopt
B23: 异星古生物学 | D23: =_xlfn.CONCAT("effect = { ",$D$2," = ",I23," }") -> effect = { add_tradition = tr_archivism_xeno_paleontology } | I23: tr_archivism_xeno_paleontology
B24: 前线考古 | D24: =_xlfn.CONCAT("effect = { ",$D$2," = ",I24," }") -> effect = { add_tradition = tr_archivism_expert_negociation } | I24: tr_archivism_expert_negociation
B25: 谈判专家 | C25: 星海收割者（灭绝） | D25: =_xlfn.CONCAT("effect = { ",$D$2," = ",I25," }") -> effect = { add_tradition = tr_archivism_frontier_archaeology } | I25: tr_archivism_frontier_archaeology
B26: 无暇展览 | D26: =_xlfn.CONCAT("effect = { ",$D$2," = ",I26," }") -> effect = { add_tradition = tr_archivism_flawless_display } | I26: tr_archivism_flawless_display
B27: 展览专场 | D27: =_xlfn.CONCAT("effect = { ",$D$2," = ",I27," }") -> effect = { add_tradition = tr_archivism_exhibition_specialization } | I27: tr_archivism_exhibition_specialization
B28: 博物传统完成 | D28: =_xlfn.CONCAT("effect = { ",$D$2," = ",I28," }") -> effect = { add_tradition = tr_archivism_finish } | I28: tr_archivism_finish
A29: 外交 | B29: 外交传统 | D29: =_xlfn.CONCAT("effect = { ",$D$2," = ",I29," }") -> effect = { add_tradition = tr_diplomacy_adopt } | G29: =_xlfn.CONCAT("effect = { ",$D$2," = ",I29," ",$D$2," = ",I30," ",$D$2," = ",I31," ",$D$2," = ",I32," ",$D$2," = ",I33," ",$D$2," = ",I34," ",$D$2," = ",I35,"}") -> effect = { add_tradition = tr_diplomacy_adopt add_tradition = tr_diplomacy_the_federation add_tradition = tr_diplomacy_entente_coordination add_tradition = tr_diplomacy_diplomatic_networking add_tradition = tr_diplomacy_direct_diplomacy add_tradition = tr_diplomacy_eminent_diplomats add_tradition = tr_diplomacy_finish} | I29: tr_diplomacy_adopt
B30: 联邦 | D30: =_xlfn.CONCAT("effect = { ",$D$2," = ",I30," }") -> effect = { add_tradition = tr_diplomacy_the_federation } | I30: tr_diplomacy_the_federation
B31: 挚诚合作 | D31: =_xlfn.CONCAT("effect = { ",$D$2," = ",I31," }") -> effect = { add_tradition = tr_diplomacy_entente_coordination } | I31: tr_diplomacy_entente_coordination
B32: 外交情报网 | D32: =_xlfn.CONCAT("effect = { ",$D$2," = ",I32," }") -> effect = { add_tradition = tr_diplomacy_diplomatic_networking } | I32: tr_diplomacy_diplomatic_networking
B33: 直接外交 | D33: =_xlfn.CONCAT("effect = { ",$D$2," = ",I33," }") -> effect = { add_tradition = tr_diplomacy_direct_diplomacy } | I33: tr_diplomacy_direct_diplomacy
B34: 杰出外交官 | C34: 改良特使子个体（格式塔） | D34: =_xlfn.CONCAT("effect = { ",$D$2," = ",I34," }") -> effect = { add_tradition = tr_diplomacy_eminent_diplomats } | I34: tr_diplomacy_eminent_diplomats
B35: 外交传统完成 | D35: =_xlfn.CONCAT("effect = { ",$D$2," = ",I35," }") -> effect = { add_tradition = tr_diplomacy_finish } | I35: tr_diplomacy_finish
A36: 探索 | B36: 探索传统 | D36: =_xlfn.CONCAT("effect = { ",$D$2," = ",I36," }") -> effect = { add_tradition = tr_discovery_adopt } | G36: =_xlfn.CONCAT("effect = { ",$D$2," = ",I36," ",$D$2," = ",I37," ",$D$2," = ",I38," ",$D$2," = ",I39," ",$D$2," = ",I40," ",$D$2," = ",I41," ",$D$2," = ",I42,"}") -> effect = { add_tradition = tr_discovery_adopt add_tradition = tr_discovery_to_boldly_go add_tradition = tr_discovery_databank_uplinks add_tradition = tr_discovery_science_division add_tradition = tr_discovery_polytechnic_education add_tradition = tr_discovery_faith_in_science add_tradition = tr_discovery_finish} | I36: tr_discovery_adopt
B37: 勇往直前 | C37: 探索者无人机（智械），卷须探测（蜂巢） | D37: =_xlfn.CONCAT("effect = { ",$D$2," = ",I37," }") -> effect = { add_tradition = tr_discovery_to_boldly_go } | I37: tr_discovery_to_boldly_go
B38: 数据库上行链路 | D38: =_xlfn.CONCAT("effect = { ",$D$2," = ",I38," }") -> effect = { add_tradition = tr_discovery_databank_uplinks } | I38: tr_discovery_databank_uplinks
B39: 科学部门 | C39: 研究路径优化（智械），思维网络（蜂巢） | D39: =_xlfn.CONCAT("effect = { ",$D$2," = ",I39," }") -> effect = { add_tradition = tr_discovery_science_division } | I39: tr_discovery_science_division
B40: 理工教育 | C40: 迭代型人工智能（智械），超适应进化（蜂巢） | D40: =_xlfn.CONCAT("effect = { ",$D$2," = ",I40," }") -> effect = { add_tradition = tr_discovery_polytechnic_education } | I40: tr_discovery_polytechnic_education
B41: 科学神教 | C41: 上链延迟降低（智械），突触广播（蜂巢），菌丝体网络（荒野） | D41: =_xlfn.CONCAT("effect = { ",$D$2," = ",I41," }") -> effect = { add_tradition = tr_discovery_faith_in_science } | I41: tr_discovery_faith_in_science
B42: 探索传统完成 | D42: =_xlfn.CONCAT("effect = { ",$D$2," = ",I42," }") -> effect = { add_tradition = tr_discovery_finish } | I42: tr_discovery_finish
A43: 驯化 | B43: 驯化传统 | D43: =_xlfn.CONCAT("effect = { ",$D$2," = ",I43," }") -> effect = { add_tradition = tr_domestication_adopt } | G43: =_xlfn.CONCAT("effect = { ",$D$2," = ",I43," ",$D$2," = ",I44," ",$D$2," = ",I45," ",$D$2," = ",I46," ",$D$2," = ",I47," ",$D$2," = ",I48," ",$D$2," = ",I49,"}") -> effect = { add_tradition = tr_domestication_adopt add_tradition = tr_domestication_containment_protocols add_tradition = tr_domestication_bio_repurposing add_tradition = tr_domestication_astrozoology add_tradition = tr_domestication_metabolic_regulation add_tradition = tr_domestication_killer_instinct add_tradition = tr_domestication_finish} | I43: tr_domestication_adopt
B44: 收容协议 | D44: =_xlfn.CONCAT("effect = { ",$D$2," = ",I44," }") -> effect = { add_tradition = tr_domestication_containment_protocols } | I44: tr_domestication_containment_protocols
B45: 生物再利用 | D45: =_xlfn.CONCAT("effect = { ",$D$2," = ",I45," }") -> effect = { add_tradition = tr_domestication_bio_repurposing } | I45: tr_domestication_bio_repurposing
B46: 星际动物学 | D46: =_xlfn.CONCAT("effect = { ",$D$2," = ",I46," }") -> effect = { add_tradition = tr_domestication_astrozoology } | I46: tr_domestication_astrozoology
B47: 代谢调控 | D47: =_xlfn.CONCAT("effect = { ",$D$2," = ",I47," }") -> effect = { add_tradition = tr_domestication_metabolic_regulation } | I47: tr_domestication_metabolic_regulation
B48: 杀手直觉 | D48: =_xlfn.CONCAT("effect = { ",$D$2," = ",I48," }") -> effect = { add_tradition = tr_domestication_killer_instinct } | I48: tr_domestication_killer_instinct
B49: 驯化传统完成 | D49: =_xlfn.CONCAT("effect = { ",$D$2," = ",I49," }") -> effect = { add_tradition = tr_domestication_finish } | I49: tr_domestication_finish
A50: 支配 | B50: 支配传统 | D50: =_xlfn.CONCAT("effect = { ",$D$2," = ",I50," }") -> effect = { add_tradition = tr_domination_adopt } | G50: =_xlfn.CONCAT("effect = { ",$D$2," = ",I50," ",$D$2," = ",I51," ",$D$2," = ",I52," ",$D$2," = ",I53," ",$D$2," = ",I54," ",$D$2," = ",I55," ",$D$2," = ",I56,"}") -> effect = { add_tradition = tr_domination_adopt add_tradition = tr_domination_colonial_viceroys add_tradition = tr_domination_imperious_architecture add_tradition = tr_domination_grand_council add_tradition = tr_domination_judgment_corps add_tradition = tr_domination_workplace_motivators add_tradition = tr_domination_finish} | I50: tr_domination_adopt
B51: 殖民总督 | C51: 自律人工智能（智械），心智相会（蜂巢） | D51: =_xlfn.CONCAT("effect = { ",$D$2," = ",I51," }") -> effect = { add_tradition = tr_domination_colonial_viceroys } | I51: tr_domination_colonial_viceroys
B52: 宏伟建筑 | C52: 模块化仓库（智械），突触延展（蜂巢），种间信息素相容（荒野） | D52: =_xlfn.CONCAT("effect = { ",$D$2," = ",I52," }") -> effect = { add_tradition = tr_domination_imperious_architecture } | I52: tr_domination_imperious_architecture
B53: 枢密院 | C53: 多线程核心功能（智械），突触网络（蜂巢） | D53: =_xlfn.CONCAT("effect = { ",$D$2," = ",I53," }") -> effect = { add_tradition = tr_domination_grand_council } | I53: tr_domination_grand_council
B54: 审判庭 | C54: 公信警官（个械平等），反常协议（智械），分歧抑制（蜂巢） | D54: =_xlfn.CONCAT("effect = { ",$D$2," = ",I54," }") -> effect = { add_tradition = tr_domination_judgment_corps } | I54: tr_domination_judgment_corps
B55: 工地监督员 | C55: 子个体网络（格式塔），宏观代谢加速（荒野） | D55: =_xlfn.CONCAT("effect = { ",$D$2," = ",I55," }") -> effect = { add_tradition = tr_domination_workplace_motivators } | I55: tr_domination_workplace_motivators
B56: 支配传统完成 | D56: =_xlfn.CONCAT("effect = { ",$D$2," = ",I56," }") -> effect = { add_tradition = tr_domination_finish } | I56: tr_domination_finish
A57: 敌意 | B57: 敌意传统 | D57: =_xlfn.CONCAT("effect = { ",$D$2," = ",I57," }") -> effect = { add_tradition = tr_enmity_adopt } | G57: =_xlfn.CONCAT("effect = { ",$D$2," = ",I57," ",$D$2," = ",I58," ",$D$2," = ",I59," ",$D$2," = ",I60," ",$D$2," = ",I61," ",$D$2," = ",I62," ",$D$2," = ",I63,"}") -> effect = { add_tradition = tr_enmity_adopt add_tradition = tr_enmity_rise_to_the_occasion add_tradition = tr_enmity_consumate_contrarian add_tradition = tr_enmity_match add_tradition = tr_enmity_outpace add_tradition = tr_enmity_eclipse add_tradition = tr_enmity_finish} | I57: tr_enmity_adopt
B58: 迎难而上 | D58: =_xlfn.CONCAT("effect = { ",$D$2," = ",I58," }") -> effect = { add_tradition = tr_enmity_rise_to_the_occasion } | I58: tr_enmity_rise_to_the_occasion
B59: 完美反制 | D59: =_xlfn.CONCAT("effect = { ",$D$2," = ",I59," }") -> effect = { add_tradition = tr_enmity_consumate_contrarian } | I59: tr_enmity_consumate_contrarian
B60: 势均力敌 | D60: =_xlfn.CONCAT("effect = { ",$D$2," = ",I60," }") -> effect = { add_tradition = tr_enmity_match } | I60: tr_enmity_match
B61: 出其不意 | D61: =_xlfn.CONCAT("effect = { ",$D$2," = ",I61," }") -> effect = { add_tradition = tr_enmity_outpace } | I61: tr_enmity_outpace
B62: 永无天日 | D62: =_xlfn.CONCAT("effect = { ",$D$2," = ",I62," }") -> effect = { add_tradition = tr_enmity_eclipse } | I62: tr_enmity_eclipse
B63: 敌意传统完成 | D63: =_xlfn.CONCAT("effect = { ",$D$2," = ",I63," }") -> effect = { add_tradition = tr_enmity_finish } | I63: tr_enmity_finish
A64: 扩张 | B64: 扩张传统 | D64: =_xlfn.CONCAT("effect = { ",$D$2," = ",I64," }") -> effect = { add_tradition = tr_expansion_adopt } | G64: =_xlfn.CONCAT("effect = { ",$D$2," = ",I64," ",$D$2," = ",I65," ",$D$2," = ",I66," ",$D$2," = ",I67," ",$D$2," = ",I68," ",$D$2," = ",I69," ",$D$2," = ",I70,"}") -> effect = { add_tradition = tr_expansion_adopt add_tradition = tr_expansion_colonization_fever add_tradition = tr_expansion_a_new_life add_tradition = tr_expansion_courier_network add_tradition = tr_expansion_reach_for_the_stars add_tradition = tr_expansion_galactic_ambition add_tradition = tr_expansion_finish} | I64: tr_expansion_adopt
B65: 殖民狂潮 | C65: 自动殖民单位（智械），唯一意志（蜂巢），万千世界之心（荒野） | D65: =_xlfn.CONCAT("effect = { ",$D$2," = ",I65," }") -> effect = { add_tradition = tr_expansion_colonization_fever } | I65: tr_expansion_colonization_fever
B66: 新生活 | C66: 加速建造协议（智械），增值狂热（蜂巢），野蛮生长（荒野） | D66: =_xlfn.CONCAT("effect = { ",$D$2," = ",I66," }") -> effect = { add_tradition = tr_expansion_a_new_life } | I66: tr_expansion_a_new_life
B67: 快递网络 | C67: 可扩展软件（智械），有限自治权（蜂巢） | D67: =_xlfn.CONCAT("effect = { ",$D$2," = ",I67," }") -> effect = { add_tradition = tr_expansion_courier_network } | I67: tr_expansion_courier_network
B68: 触摸星辰 | C68: 信号中继器（智械），变形突触（蜂巢） | D68: =_xlfn.CONCAT("effect = { ",$D$2," = ",I68," }") -> effect = { add_tradition = tr_expansion_reach_for_the_stars } | I68: tr_expansion_reach_for_the_stars
B69: 星河野望 | C69: 机械中的齿轮（智械），抹杀繁星（蜂巢） | D69: =_xlfn.CONCAT("effect = { ",$D$2," = ",I69," }") -> effect = { add_tradition = tr_expansion_galactic_ambition } | I69: tr_expansion_galactic_ambition
B70: 扩张传统完成 | D70: =_xlfn.CONCAT("effect = { ",$D$2," = ",I70," }") -> effect = { add_tradition = tr_expansion_finish } | I70: tr_expansion_finish
A71: 和谐 | B71: 和谐传统 | D71: =_xlfn.CONCAT("effect = { ",$D$2," = ",I71," }") -> effect = { add_tradition = tr_harmony_adopt } | G71: =_xlfn.CONCAT("effect = { ",$D$2," = ",I71," ",$D$2," = ",I72," ",$D$2," = ",I73," ",$D$2," = ",I74," ",$D$2," = ",I75," ",$D$2," = ",I76," ",$D$2," = ",I77,"}") -> effect = { add_tradition = tr_harmony_adopt add_tradition = tr_harmony_the_greater_good add_tradition = tr_harmony_kinship add_tradition = tr_harmony_utopian_dream add_tradition = tr_harmony_harmonious_directives add_tradition = tr_harmony_mind_and_body add_tradition = tr_harmony_finish} | I71: tr_harmony_adopt
B72: 上上善道 | D72: =_xlfn.CONCAT("effect = { ",$D$2," = ",I72," }") -> effect = { add_tradition = tr_harmony_the_greater_good } | I72: tr_harmony_the_greater_good
B73: 亲子联系 | D73: =_xlfn.CONCAT("effect = { ",$D$2," = ",I73," }") -> effect = { add_tradition = tr_harmony_kinship } | I73: tr_harmony_kinship
B74: 乌托邦之梦 | D74: =_xlfn.CONCAT("effect = { ",$D$2," = ",I74," }") -> effect = { add_tradition = tr_harmony_utopian_dream } | I74: tr_harmony_utopian_dream
B75: 和谐法令 | D75: =_xlfn.CONCAT("effect = { ",$D$2," = ",I75," }") -> effect = { add_tradition = tr_harmony_harmonious_directives } | I75: tr_harmony_harmonious_directives
B76: 身与心 | C76: 万众归一（食尸文化） | D76: =_xlfn.CONCAT("effect = { ",$D$2," = ",I76," }") -> effect = { add_tradition = tr_harmony_mind_and_body } | I76: tr_harmony_mind_and_body
B77: 和谐传统完成 | D77: =_xlfn.CONCAT("effect = { ",$D$2," = ",I77," }") -> effect = { add_tradition = tr_harmony_finish } | I77: tr_harmony_finish
A78: 后勤 | B78: 后勤传统 | D78: =_xlfn.CONCAT("effect = { ",$D$2," = ",I78," }") -> effect = { add_tradition = tr_logistics_adopt } | G78: =_xlfn.CONCAT("effect = { ",$D$2," = ",I78," ",$D$2," = ",I79," ",$D$2," = ",I80," ",$D$2," = ",I81," ",$D$2," = ",I82," ",$D$2," = ",I83," ",$D$2," = ",I84,"}") -> effect = { add_tradition = tr_logistics_adopt add_tradition = tr_logistics_1 add_tradition = tr_logistics_2 add_tradition = tr_logistics_3 add_tradition = tr_logistics_4 add_tradition = tr_logistics_5 add_tradition = tr_logistics_finish} | I78: tr_logistics_adopt
B79: 嵌入式协作 | D79: =_xlfn.CONCAT("effect = { ",$D$2," = ",I79," }") -> effect = { add_tradition = tr_logistics_1 } | I79: tr_logistics_1
B80: 分布式递送系统 | D80: =_xlfn.CONCAT("effect = { ",$D$2," = ",I80," }") -> effect = { add_tradition = tr_logistics_2 } | I80: tr_logistics_2
B81: 自动维护 | D81: =_xlfn.CONCAT("effect = { ",$D$2," = ",I81," }") -> effect = { add_tradition = tr_logistics_3 } | I81: tr_logistics_3
B82: 星际交易效率 | D82: =_xlfn.CONCAT("effect = { ",$D$2," = ",I82," }") -> effect = { add_tradition = tr_logistics_4 } | I82: tr_logistics_4
B83: 预测性再供给模式 | D83: =_xlfn.CONCAT("effect = { ",$D$2," = ",I83," }") -> effect = { add_tradition = tr_logistics_5 } | I83: tr_logistics_5
B84: 后勤传统完成 | D84: =_xlfn.CONCAT("effect = { ",$D$2," = ",I84," }") -> effect = { add_tradition = tr_logistics_finish } | I84: tr_logistics_finish
A85: 经贸 | B85: 经贸传统 | D85: =_xlfn.CONCAT("effect = { ",$D$2," = ",I85," }") -> effect = { add_tradition = tr_mercantile_adopt } | G85: =_xlfn.CONCAT("effect = { ",$D$2," = ",I85," ",$D$2," = ",I86," ",$D$2," = ",I87," ",$D$2," = ",I88," ",$D$2," = ",I89," ",$D$2," = ",I90," ",$D$2," = ",I91,"}") -> effect = { add_tradition = tr_mercantile_adopt add_tradition = tr_mercantile_trickle_up_economics add_tradition = tr_mercantile_commercial_enterprise add_tradition = tr_mercantile_adaptive_economic_policies add_tradition = tr_mercantile_marketplace_of_better_ideas add_tradition = tr_mercantile_insider_trading add_tradition = tr_mercantile_finish} | I85: tr_mercantile_adopt
B86: 积少成多 | D86: =_xlfn.CONCAT("effect = { ",$D$2," = ",I86," }") -> effect = { add_tradition = tr_mercantile_trickle_up_economics } | I86: tr_mercantile_trickle_up_economics
B87: 商业集团 | D87: =_xlfn.CONCAT("effect = { ",$D$2," = ",I87," }") -> effect = { add_tradition = tr_mercantile_commercial_enterprise } | I87: tr_mercantile_commercial_enterprise
B88: 适应性商业政策 | C88: 灵活股东计划（劳工合作社），联邦贸易舰队（贸易联邦） | D88: =_xlfn.CONCAT("effect = { ",$D$2," = ",I88," }") -> effect = { add_tradition = tr_mercantile_adaptive_economic_policies } | I88: tr_mercantile_adaptive_economic_policies
B89: 智库市场 | D89: =_xlfn.CONCAT("effect = { ",$D$2," = ",I89," }") -> effect = { add_tradition = tr_mercantile_marketplace_of_better_ideas } | I89: tr_mercantile_marketplace_of_better_ideas
B90: 内幕交易 | D90: =_xlfn.CONCAT("effect = { ",$D$2," = ",I90," }") -> effect = { add_tradition = tr_mercantile_insider_trading } | I90: tr_mercantile_insider_trading
B91: 经贸传统完成 | D91: =_xlfn.CONCAT("effect = { ",$D$2," = ",I91," }") -> effect = { add_tradition = tr_mercantile_finish } | I91: tr_mercantile_finish
A92: 权术 | B92: 权术传统 | D92: =_xlfn.CONCAT("effect = { ",$D$2," = ",I92," }") -> effect = { add_tradition = tr_politics_adopt } | G92: =_xlfn.CONCAT("effect = { ",$D$2," = ",I92," ",$D$2," = ",I93," ",$D$2," = ",I94," ",$D$2," = ",I95," ",$D$2," = ",I96," ",$D$2," = ",I97," ",$D$2," = ",I98,"}") -> effect = { add_tradition = tr_politics_adopt add_tradition = tr_politics_quid_pro_quo add_tradition = tr_politics_gravitas add_tradition = tr_politics_national_agenda add_tradition = tr_politics_persistent_petitioners add_tradition = tr_politics_extraordinary_powers add_tradition = tr_politics_finish} | I92: tr_politics_adopt
B93: 等价交换 | D93: =_xlfn.CONCAT("effect = { ",$D$2," = ",I93," }") -> effect = { add_tradition = tr_politics_quid_pro_quo } | I93: tr_politics_quid_pro_quo
B94: 无上庄严 | D94: =_xlfn.CONCAT("effect = { ",$D$2," = ",I94," }") -> effect = { add_tradition = tr_politics_gravitas } | I94: tr_politics_gravitas
B95: 国民议程 | D95: =_xlfn.CONCAT("effect = { ",$D$2," = ",I95," }") -> effect = { add_tradition = tr_politics_national_agenda } | I95: tr_politics_national_agenda
B96: 执着请愿 | D96: =_xlfn.CONCAT("effect = { ",$D$2," = ",I96," }") -> effect = { add_tradition = tr_politics_persistent_petitioners } | I96: tr_politics_persistent_petitioners
B97: 特别权力 | D97: =_xlfn.CONCAT("effect = { ",$D$2," = ",I97," }") -> effect = { add_tradition = tr_politics_extraordinary_powers } | I97: tr_politics_extraordinary_powers
B98: 权术传统完成 | D98: =_xlfn.CONCAT("effect = { ",$D$2," = ",I98," }") -> effect = { add_tradition = tr_politics_finish } | I98: tr_politics_finish
A99: 繁荣 | B99: 繁荣传统 | D99: =_xlfn.CONCAT("effect = { ",$D$2," = ",I99," }") -> effect = { add_tradition = tr_prosperity_adopt } | G99: =_xlfn.CONCAT("effect = { ",$D$2," = ",I99," ",$D$2," = ",I100," ",$D$2," = ",I101," ",$D$2," = ",I102," ",$D$2," = ",I103," ",$D$2," = ",I104," ",$D$2," = ",I105,"}") -> effect = { add_tradition = tr_prosperity_adopt add_tradition = tr_prosperity_sct add_tradition = tr_prosperity_administrative_operations add_tradition = tr_prosperity_public_works add_tradition = tr_prosperity_interstellar_franchising add_tradition = tr_prosperity_pursuit_of_profit add_tradition = tr_prosperity_finish} | I99: tr_prosperity_adopt
B100: 标准建造模板 | C100: 预制建筑（格式塔），标准化生态系统（荒野） | D100: =_xlfn.CONCAT("effect = { ",$D$2," = ",I100," }") -> effect = { add_tradition = tr_prosperity_sct } | I100: tr_prosperity_sct
...

Sheet 飞升
A1: 4.0.21飞升代码（2025.07.25）
A2: 添加/移除代码 | C2: add_ascension_perk | D2: 注：下拉可选择添加或者移除
A3: 序号 | B3: 名称 | C3: 自适应代码 | D3: key | E3: 备注
A4: 1 | B4: 基因重塑 | C4: =_xlfn.CONCAT("effect = { ",$C$2," = ",D4," }") -> effect = { add_ascension_perk = ap_engineered_evolution } | D4: ap_engineered_evolution
A5: 2 | B5: 血肉苦弱 | C5: =_xlfn.CONCAT("effect = { ",$C$2," = ",D5," }") -> effect = { add_ascension_perk = ap_the_flesh_is_weak } | D5: ap_the_flesh_is_weak
A6: 3 | B6: 有机机械交互 | C6: =_xlfn.CONCAT("effect = { ",$C$2," = ",D6," }") -> effect = { add_ascension_perk = ap_organo_machine_interfacing } | D6: ap_organo_machine_interfacing
A7: 4 | B7: 有机机械交互 | C7: =_xlfn.CONCAT("effect = { ",$C$2," = ",D7," }") -> effect = { add_ascension_perk = ap_organo_machine_interfacing_assimilator } | D7: ap_organo_machine_interfacing_assimilator | E7: 同化斗士专属
A8: 5 | B8: 合成进化 | C8: =_xlfn.CONCAT("effect = { ",$C$2," = ",D8," }") -> effect = { add_ascension_perk = ap_synthetic_evolution } | D8: ap_synthetic_evolution
A9: 6 | B9: 心胜于物 | C9: =_xlfn.CONCAT("effect = { ",$C$2," = ",D9," }") -> effect = { add_ascension_perk = ap_mind_over_matter } | D9: ap_mind_over_matter
A10: 7 | B10: 合成时代 | C10: =_xlfn.CONCAT("effect = { ",$C$2," = ",D10," }") -> effect = { add_ascension_perk = ap_synthetic_age } | D10: ap_synthetic_age | E10: 机器智能专属
A11: 8 | B11: 超然存在 | C11: =_xlfn.CONCAT("effect = { ",$C$2," = ",D11," }") -> effect = { add_ascension_perk = ap_transcendence } | D11: ap_transcendence | E11: 旧版但能用
A12: 9 | B12: 掌控进化 | C12: =_xlfn.CONCAT("effect = { ",$C$2," = ",D12," }") -> effect = { add_ascension_perk = ap_evolutionary_mastery } | D12: ap_evolutionary_mastery | E12: 旧版但能用
A13: 10 | B13: 星河卫士 | C13: =_xlfn.CONCAT("effect = { ",$C$2," = ",D13," }") -> effect = { add_ascension_perk = ap_defender_of_the_galaxy } | D13: ap_defender_of_the_galaxy
A14: 11 | B14: 星海天罚 | C14: =_xlfn.CONCAT("effect = { ",$C$2," = ",D14," }") -> effect = { add_ascension_perk = ap_become_the_crisis } | D14: ap_become_the_crisis
A15: 12 | B15: 宇宙创生 | C15: =_xlfn.CONCAT("effect = { ",$C$2," = ",D15," }") -> effect = { add_ascension_perk = ap_cosmogenesis } | D15: ap_cosmogenesis
A16: 13 | B16: 巨兽之怒 | C16: =_xlfn.CONCAT("effect = { ",$C$2," = ",D16," }") -> effect = { add_ascension_perk = ap_behemoths } | D16: ap_behemoths
A17: 14 | B17: 考古工程师 | C17: =_xlfn.CONCAT("effect = { ",$C$2," = ",D17," }") -> effect = { add_ascension_perk = ap_archaeoengineers } | D17: ap_archaeoengineers
A18: 15 | B18: 战争之王 | C18: =_xlfn.CONCAT("effect = { ",$C$2," = ",D18," }") -> effect = { add_ascension_perk = ap_lord_of_war } | D18: ap_lord_of_war
A19: 16 | B19: 水之心 | C19: =_xlfn.CONCAT("effect = { ",$C$2," = ",D19," }") -> effect = { add_ascension_perk = ap_hydrocentric } | D19: ap_hydrocentric | E19: 水生特质专属
A20: 17 | B20: 天机工程 | C20: =_xlfn.CONCAT("effect = { ",$C$2," = ",D20," }") -> effect = { add_ascension_perk = ap_enigmatic_engineering } | D20: ap_enigmatic_engineering
A21: 18 | B21: 强取豪夺 | C21: =_xlfn.CONCAT("effect = { ",$C$2," = ",D21," }") -> effect = { add_ascension_perk = ap_nihilistic_acquisition } | D21: ap_nihilistic_acquisition
A22: 19 | B22: 巨像计划 | C22: =_xlfn.CONCAT("effect = { ",$C$2," = ",D22," }") -> effect = { add_ascension_perk = ap_colossus } | D22: ap_colossus
A23: 20 | B23: 星球塑形师 | C23: =_xlfn.CONCAT("effect = { ",$C$2," = ",D23," }") -> effect = { add_ascension_perk = ap_world_shaper } | D23: ap_world_shaper
A24: 21 | B24: 星河力量投射 | C24: =_xlfn.CONCAT("effect = { ",$C$2," = ",D24," }") -> effect = { add_ascension_perk = ap_galactic_force_projection } | D24: ap_galactic_force_projection
A25: 22 | B25: 星际主权 | C25: =_xlfn.CONCAT("effect = { ",$C$2," = ",D25," }") -> effect = { add_ascension_perk = ap_interstellar_dominion } | D25: ap_interstellar_dominion
A26: 23 | B26: 掌握太虚 | C26: =_xlfn.CONCAT("effect = { ",$C$2," = ",D26," }") -> effect = { add_ascension_perk = ap_grasp_the_void } | D26: ap_grasp_the_void
A27: 24 | B27: 戒心永存 | C27: =_xlfn.CONCAT("effect = { ",$C$2," = ",D27," }") -> effect = { add_ascension_perk = ap_eternal_vigilance } | D27: ap_eternal_vigilance
A28: 25 | B28: 逐鹿星河 | C28: =_xlfn.CONCAT("effect = { ",$C$2," = ",D28," }") -> effect = { add_ascension_perk = ap_galactic_contender } | D28: ap_galactic_contender
A29: 26 | B29: 科技至上 | C29: =_xlfn.CONCAT("effect = { ",$C$2," = ",D29," }") -> effect = { add_ascension_perk = ap_technological_ascendancy } | D29: ap_technological_ascendancy
A30: 27 | B30: 万众一心 | C30: =_xlfn.CONCAT("effect = { ",$C$2," = ",D30," }") -> effect = { add_ascension_perk = ap_one_vision } | D30: ap_one_vision
A31: 28 | B31: 祝圣星球 | C31: =_xlfn.CONCAT("effect = { ",$C$2," = ",D31," }") -> effect = { add_ascension_perk = ap_consecrated_worlds } | D31: ap_consecrated_worlds
... A38: 35 | B38: 建筑大师 | C38: =_xlfn.CONCAT("effect = { ",$C$2," = ",D38," }") -> effect = { add_ascension_perk = ap_master_builders } | D38: ap_master_builders
A39: 36 | B39: 星河奇迹 | C39: =_xlfn.CONCAT("effect = { ",$C$2," = ",D39," }") -> effect = { add_ascension_perk = ap_galactic_wonders_utopia } | D39: ap_galactic_wonders_utopia | E39: 能用，无DLC
A40: 37 | B40: 星河奇迹 | C40: =_xlfn.CONCAT("effect = { ",$C$2," = ",D40," }") -> effect = { add_ascension_perk = ap_galactic_wonders_megacorp } | D40: ap_galactic_wonders_megacorp | E40: 能用，无DLC
A41: 38 | B41: 星河奇迹 | C41: =_xlfn.CONCAT("effect = { ",$C$2," = ",D41," }") -> effect = { add_ascension_perk = ap_galactic_wonders_utopia_and_megacorp } | D41: ap_galactic_wonders_utopia_and_megacorp
A42: 39 | B42: 机械世界 | C42: =_xlfn.CONCAT("effect = { ",$C$2," = ",D42," }") -> effect = { add_ascension_perk = ap_machine_worlds } | D42: ap_machine_worlds | E42: 机械智能专属
A43: 40 | B43: 蜂巢星球 | C43: =_xlfn.CONCAT("effect = { ",$C$2," = ",D43," }") -> effect = { add_ascension_perk = ap_hive_worlds } | D43: ap_hive_worlds | E43: 蜂巢思维专属
A44: 41 | B44: 理想城计划 | C44: =_xlfn.CONCAT("effect = { ",$C$2," = ",D44," }") -> effect = { add_ascension_perk = ap_arcology_project } | D44: ap_arcology_project
A45: 42 | B45: 跨物种杂交 | C45: =_xlfn.CONCAT("effect = { ",$C$2," = ",D45," }") -> effect = { add_ascension_perk = ap_xeno_compatibility } | D45: ap_xeno_compatibility
A46: 43 | B46: 寰宇贸易 | C46: =_xlfn.CONCAT("effect = { ",$C$2," = ",D46," }") -> effect = { add_ascension_perk = ap_universal_transactions } | D46: ap_universal_transactions | E46: 寰宇企业专属
A47: 44 | B47: 排毒 | C47: =_xlfn.CONCAT("effect = { ",$C$2," = ",D47," }") -> effect = { add_ascension_perk = ap_detox } | D47: ap_detox
A48: 45 | B48: 死灵机师 | C48: =_xlfn.CONCAT("effect = { ",$C$2," = ",D48," }") -> effect = { add_ascension_perk = ap_mechromancy } | D48: ap_mechromancy | E48: 机械智能专属
A49: 46 | B49: 星系天气控制 | C49: =_xlfn.CONCAT("effect = { ",$C$2," = ",D49," }") -> effect = { add_ascension_perk = ap_weather_control } | D49: ap_weather_control

Sheet 思潮派系
A1: 思潮代码合集 | K1: 帝国主义派 | L1: imperialist | M1: 军国 | N1: 威权
A2: 思潮名称 | B2: 改变国家思潮（直接使用） | C2: 改变领袖思潮（选中领袖使用） | D2: 改变人口思潮（选中星球，后面数字为转化人口比例） | K2: 孤立派 | L2: isolationist | M2: 排外 | N2: 和平
A3: 唯心主义 | B3: effect shift_ethic = ethic_spiritualist | C3: effect = {change_background_ethic = ethic_spiritualist} | D3: effect every_owned_pop_group = { pop_group_transfer_ethic = {POP_GROUP = this ETHOS = ethic_spiritualist PERCENTAGE = 1} | K3: 亲外派 | L3: xenoist | M3: 亲外 | N3: 平等
A4: 唯物主义 | B4: effect shift_ethic = ethic_materialist | C4: effect = {change_background_ethic = ethic_materialist} | D4: effect every_owned_pop_group = { pop_group_transfer_ethic = {POP_GROUP = this ETHOS = ethic_materialist PERCENTAGE = 1} | K4: 传统派 | L4: traditionalist | M4: 唯心
A5: 军国主义 | B5: effect shift_ethic = ethic_militarist | C5: effect = {change_background_ethic = ethic_militarist} | D5: effect every_owned_pop_group = { pop_group_transfer_ethic = {POP_GROUP = this ETHOS = ethic_militarist PERCENTAGE = 1} | K5: 极权派 | L5: totalitarian | M5: 威权
A6: 和平主义 | B6: effect shift_ethic = ethic_pacifist | C6: effect = {change_background_ethic = ethic_pacifist} | D6: effect every_owned_pop_group = { pop_group_transfer_ethic = {POP_GROUP = this ETHOS = ethic_pacifist PERCENTAGE = 1} | K6: 技术派 | L6: technologist | M6: 唯物
A7: 排外主义 | B7: effect shift_ethic = ethic_xenophobe | C7: effect = {change_background_ethic = ethic_xenophobe} | D7: effect every_owned_pop_group = { pop_group_transfer_ethic = {POP_GROUP = this ETHOS = ethic_xenophobe PERCENTAGE = 1} | K7: 至高派 | L7: supremacist | M7: 排外 | N7: 军国
A8: 亲外主义 | B8: effect shift_ethic = ethic_xenophile | C8: effect = {change_background_ethic = ethic_xenophile} | D8: effect every_owned_pop_group = { pop_group_transfer_ethic = {POP_GROUP = this ETHOS = ethic_xenophile PERCENTAGE = 1} | K8: 繁荣派 | L8: prosperity | M8: 和平 | N8: 亲外
A9: 威权主义 | B9: effect shift_ethic = ethic_authoritarian | C9: effect = {change_background_ethic = ethic_authoritarian} | D9: effect every_owned_pop_group = { pop_group_transfer_ethic = {POP_GROUP = this ETHOS = ethic_authoritarian PERCENTAGE = 1} | K9: 进步派 | L9: progressive
A10: 平等主义 | B10: effect shift_ethic = ethic_egalitarian | C10: effect = {change_background_ethic = ethic_egalitarian} | D10: effect every_owned_pop_group = { pop_group_transfer_ethic = {POP_GROUP = this ETHOS = ethic_egalitarian PERCENTAGE = 1} | K10: 宣泄派 | L10: manifesti
A11: 格式塔 | B11: effect shift_ethic = ethic_gestalt_consciousness | C11: effect = {change_background_ethic = ethic_gestalt_consciousness} | D11: effect every_owned_pop_group = { pop_group_transfer_ethic = {POP_GROUP = this ETHOS = ethic_gestalt_consciousness PERCENTAGE = 1} | K11: 劳力之结社（起始） | L11: cyber_creed_labor | M11: 平等
K12: 钢铁之圣卫（起始） | L12: cyber_creed_war
K13: 巨锤之使团（起始） | L13: cyber_creed_construction
K14: 思想之诗颂（起始） | L14: cyber_creed_research
K15: 统合信条 | L15: cyber_creed_general
K16: 劳力之结社（结束） | L16: cyber_creed_labor_2
K17: 钢铁之圣卫（结束） | L17: cyber_creed_war_2
B18: 派系名称 | C18: 技术派 | K18: 巨锤之使团（结束） | L18: cyber_creed_construction_2
A19: 压榨派系 | B19: =_xlfn.CONCAT("effect every_pop_faction = { limit = { is_pop_faction_type = ",_xlfn.XLOOKUP(C18,K1:K19,L1:L19)," } set_faction_extorted = yes }") -> effect every_pop_faction = { limit = { is_pop_faction_type = technologist } set_faction_extorted = yes } | K19: 思想之诗颂（结束） | L19: cyber_creed_research_2
A20: 注：同时只能压榨一个派系

Sheet 物种特质
A1: 4.0.22物种特质收录（2025.08.25）
A2: 添加/删除代码 | C2: add_trait | E2: 人口ID | F2: 1 | G2: 添加（add_trait_species）和移除（remove_trait_species）代码，可以使用下拉菜单进行选择 使用“debugtooltip”代码查看游戏内种族的ID，写进浅红色区域内的数字会自动填充进代码 | I2: 跳转创建物种
A3: 类别 | B3: 序号 | C3: 特质名称 | D3: 筛选 | E3: 自适应代码 | G3: 效果 | H3: 特质代码
A4: 有机宜居偏好 | B4: 1 | C4: 沙漠星球偏好 | D4: √ | E4: =_xlfn.CONCAT($C$2,"_species ",$F$2," ",H4) -> add_trait_species 1 trait_pc_desert_preference | G4: 沙漠星球宜居+80%，干燥气候宜居+60%，潮湿/寒冷气候宜居+20% | H4: trait_pc_desert_preference | I4: {=_xlfn._xlws.FILTER(H4:H47,D4:D47="√","未选择特质")} -> trait_pc_desert_preference
B5: 2 | C5: 干旱星球偏好 | D5: × | E5: =_xlfn.CONCAT($C$2,"_species ",$F$2," ",H5) -> add_trait_species 1 trait_pc_arid_preference | G5: 干旱星球宜居+80%，干燥气候宜居+60%，潮湿/寒冷气候宜居+20% | H5: trait_pc_arid_preference
B6: 3 | C6: 草原星球偏好 | D6: × | E6: =_xlfn.CONCAT($C$2,"_species ",$F$2," ",H6) -> add_trait_species 1 trait_pc_savannah_preference | G6: 草原星球宜居+80%，干燥气候宜居+60%，潮湿/寒冷气候宜居+20% | H6: trait_pc_savannah_preference
B7: 4 | C7: 热带星球偏好 | D7: × | E7: =_xlfn.CONCAT($C$2,"_species ",$F$2," ",H7) -> add_trait_species 1 trait_pc_tropical_preference | G7: 热带星球宜居+80%，潮湿气候宜居+60%，干燥/寒冷气候宜居+20% | H7: trait_pc_tropical_preference
B8: 5 | C8: 陆地星球偏好 | D8: × | E8: =_xlfn.CONCAT($C$2,"_species ",$F$2," ",H8) -> add_trait_species 1 trait_pc_continental_preference | G8: 陆地星球宜居+80%，潮湿气候宜居+60%，干燥/寒冷气候宜居+20% | H8: trait_pc_continental_preference | P8: 111 | R8: 111111 | S8: 1 | W8: 111
B9: 6 | C9: 海洋星球偏好 | D9: × | E9: =_xlfn.CONCAT($C$2,"_species ",$F$2," ",H9) -> add_trait_species 1 trait_pc_ocean_preference | G9: 海洋星球宜居+80%，潮湿气候宜居+60%，干燥/寒冷气候宜居+20% | H9: trait_pc_ocean_preference
B10: 7 | C10: 极地星球偏好 | D10: × | E10: =_xlfn.CONCAT($C$2,"_species ",$F$2," ",H10) -> add_trait_species 1 trait_pc_arctic_preference | G10: 极地星球宜居+80%，寒冷气候宜居+60%，干燥/潮湿气候宜居+20% | H10: trait_pc_arctic_preference
B11: 8 | C11: 苔原星球偏好 | D11: × | E11: =_xlfn.CONCAT($C$2,"_species ",$F$2," ",H11) -> add_trait_species 1 trait_pc_tundra_preference | G11: 苔原星球宜居+80%，寒冷气候宜居+60%，干燥/潮湿气候宜居+20% | H11: trait_pc_tundra_preference
B12: 9 | C12: 高山星球偏好 | D12: × | E12: =_xlfn.CONCAT($C$2,"_species ",$F$2," ",H12) -> add_trait_species 1 trait_pc_alpine_preference | G12: 高山星球宜居+80%，寒冷气候宜居+60%，干燥/潮湿气候宜居+20% | H12: trait_pc_alpine_preference
B13: 10 | C13: 人工智能星球偏好 | D13: × | E13: =_xlfn.CONCAT($C$2,"_species ",$F$2," ",H13) -> add_trait_species 1 trait_pc_ai_preference | G13: 机械星球宜居+100%，干燥/潮湿/寒冷气候宜居+1% | H13: trait_pc_ai_preference
B14: 11 | C14: 死寂星球偏好 | D14: × | E14: =_xlfn.CONCAT($C$2,"_species ",$F$2," ",H14) -> add_trait_species 1 trait_pc_nuked_preference | G14: 死寂星球宜居+80%，干燥/潮湿/寒冷气候宜居+60% | H14: trait_pc_nuked_preference
B15: 12 | C15: 盖亚星球偏好 | D15: × | E15: =_xlfn.CONCAT($C$2,"_species ",$F$2," ",H15) -> add_trait_species 1 trait_pc_gaia_preference | G15: 盖亚星球宜居+100% | H15: trait_pc_gaia_preference
B16: 13 | C16: 环形世界偏好 | D16: × | E16: =_xlfn.CONCAT($C$2,"_species ",$F$2," ",H16) -> add_trait_species 1 trait_pc_ringworld_habitable_preference | G16: 环形世界宜居+100% | H16: trait_pc_ringworld_habitable_preference
B17: 14 | C17: 居住站偏好 | D17: × | E17: =_xlfn.CONCAT($C$2,"_species ",$F$2," ",H17) -> add_trait_species 1 trait_pc_habitat_preference | G17: 轨道居住站宜居+80% | H17: trait_pc_habitat_preference
B18: 15 | C18: 机械星球偏好 | D18: × | E18: =_xlfn.CONCAT($C$2,"_species ",$F$2," ",H18) -> add_trait_species 1 trait_pc_machine_preference | G18: 机械星球宜居+100% | H18: trait_pc_machine_preference
B19: 16 | C19: 蜂巢星球偏好 | D19: × | E19: =_xlfn.CONCAT($C$2,"_species ",$F$2," ",H19) -> add_trait_species 1 trait_pc_hive_preference | G19: 蜂巢星球宜居+100% | H19: trait_pc_hive_preference
B20: 17 | C20: 遗落星球偏好 | D20: × | E20: =_xlfn.CONCAT($C$2,"_species ",$F$2," ",H20) -> add_trait_species 1 trait_pc_relic_preference | G20: 遗落星球宜居+80% | H20: trait_pc_relic_preference
... B24: 21 | C24: 突触凝炼机偏好 | D24: × | E24: =_xlfn.CONCAT($C$2,"_species ",$F$2," ",H24) -> add_trait_species 1 trait_pc_cosmogenesis_world_preference | G24: 突触凝炼机宜居+100% | H24: trait_pc_cosmogenesis_world_preference
A25: 机械偏好 | B25: 1 | C25: 干燥星球偏好 | D25: × | E25: =_xlfn.CONCAT($C$2,"_species ",$F$2," ",H25) -> add_trait_species 1 trait_dry_planet_preference | G25: 干燥星球宜居+75%，潮湿/寒冷气候宜居+50% | H25: trait_dry_planet_preference
B26: 2 | C26: 潮湿星球偏好 | D26: × | E26: =_xlfn.CONCAT($C$2,"_species ",$F$2," ",H26) -> add_trait_species 1 trait_wet_planet_preference | G26: 潮湿星球宜居+75%，干燥/寒冷气候宜居+50% | H26: trait_wet_planet_preference
B27: 3 | C27: 冰封星球偏好 | D27: × | E27: =_xlfn.CONCAT($C$2,"_species ",$F$2," ",H27) -> add_trait_species 1 trait_frozen_planet_preference | G27: 寒冷星球宜居+75%，干燥/潮湿气候宜居+50% | H27: trait_frozen_planet_preference
B28: 4 | C28: 居住站偏好 | D28: × | E28: =_xlfn.CONCAT($C$2,"_species ",$F$2," ",H28) -> add_trait_species 1 trait_machine_habitat_planet_preference | G28: 轨道居住站宜居+80% | H28: trait_machine_habitat_planet_preference
B29: 5 | C29: 盖亚星球偏好 | D29: × | E29: =_xlfn.CONCAT($C$2,"_species ",$F$2," ",H29) -> add_trait_species 1 trait_machine_pc_gaia_preference | G29: 盖亚星球宜居+100% | H29: trait_machine_pc_gaia_preference
B30: 6 | C30: 机械星球偏好 | D30: × | E30: =_xlfn.CONCAT($C$2,"_species ",$F$2," ",H30) -> add_trait_species 1 trait_machine_pc_machine_preference | G30: 机械星球宜居+100% | H30: trait_machine_pc_machine_preference
B31: 7 | C31: 环形世界偏好 | D31: × | E31: =_xlfn.CONCAT($C$2,"_species ",$F$2," ",H31) -> add_trait_species 1 trait_machine_pc_shattered_ring_habitable_preference | G31: 环形世界宜居+100% | H31: trait_machine_pc_shattered_ring_habitable_preference
B32: 8 | C32: 环形世界偏好 | D32: × | E32: =_xlfn.CONCAT($C$2,"_species ",$F$2," ",H32) -> add_trait_species 1 trait_machine_pc_ringworld_habitable_preference | G32: 环形世界宜居+100% | H32: trait_machine_pc_ringworld_habitable_preference
B33: 9 | C33: 遗落世界偏好 | D33: × | E33: =_xlfn.CONCAT($C$2,"_species ",$F$2," ",H33) -> add_trait_species 1 trait_machine_pc_relic_preference | G33: 遗落星球宜居+80% | H33: trait_machine_pc_relic_preference
B34: 10 | C34: 死寂星球偏好 | D34: × | E34: =_xlfn.CONCAT($C$2,"_species ",$F$2," ",H34) -> add_trait_species 1 trait_machine_pc_nuked_preference | G34: 死寂星球宜居+80%，干旱/潮湿/寒冷气候宜居+60% | H34: trait_machine_pc_nuked_preference
B35: 11 | C35: 纳米星球偏好 | D35: × | E35: =_xlfn.CONCAT($C$2,"_species ",$F$2," ",H35) -> add_trait_species 1 trait_machine_pc_nanotech_preference | G35: 纳米星球宜居+80%，干旱/潮湿/寒冷气候宜居+60% | H35: trait_machine_pc_nanotech_preference
A36: 诱变宜居偏好 | B36: 1 | C36: 诱变宜居性 | D36: × | E36: =_xlfn.CONCAT($C$2,"_species ",$F$2," ",H36) -> add_trait_species 1 trait_auto_hab_preference | G36: 自动改造宜居性偏好特质自动调整。干燥/潮湿/寒冷气候宜居+50%，死寂宜居+50% | H36: trait_auto_hab_preference
B37: 2 | C37: 潮湿气候变异 | D37: × | E37: =_xlfn.CONCAT($C$2,"_species ",$F$2," ",H37) -> add_trait_species 1 trait_auto_wet_preference | G37: 潮湿星球宜居+30%，干燥/寒冷气候宜居-20%，死寂宜居-20% | H37: trait_auto_wet_preference
B38: 3 | C38: 寒冷气候变异 | D38: × | E38: =_xlfn.CONCAT($C$2,"_species ",$F$2," ",H38) -> add_trait_species 1 trait_auto_cold_preference | G38: 寒冷星球宜居+30%，干燥/潮湿气候宜居-20%，死寂宜居-20% | H38: trait_auto_cold_preference
B39: 4 | C39: 干燥星球变异 | D39: × | E39: =_xlfn.CONCAT($C$2,"_species ",$F$2," ",H39) -> add_trait_species 1 trait_auto_dry_preference | G39: 干燥星球宜居+30%，潮湿/寒冷气候宜居-20%，死寂宜居-20% | H39: trait_auto_dry_preference
B40: 5 | C40: 死寂星球变异 | D40: × | E40: =_xlfn.CONCAT($C$2,"_species ",$F$2," ",H40) -> add_trait_species 1 trait_auto_pc_nuked_preference | G40: 干燥/潮湿/寒冷气候宜居-20%，死寂宜居+30% | H40: trait_auto_pc_nuked_preference
B41: 6 | C41: 盖亚星球变异 | D41: × | E41: =_xlfn.CONCAT($C$2,"_species ",$F$2," ",H41) -> add_trait_species 1 trait_auto_pc_gaia_preference | G41: 盖亚宜居+20%，干燥/潮湿/寒冷气候宜居-20%，死寂/轨道居住站宜居-20% | H41: trait_auto_pc_gaia_preference
B42: 7 | C42: 轨道居住站变异 | D42: × | E42: =_xlfn.CONCAT($C$2,"_species ",$F$2," ",H42) -> add_trait_species 1 trait_auto_pc_habitat_preference | G42: 轨道居住站宜居+50%，干燥/潮湿/寒冷气候宜居-20%，死寂宜居-20% | H42: trait_auto_pc_habitat_preference
B43: 8 | C43: 都市星球变异 | D43: × | E43: =_xlfn.CONCAT($C$2,"_species ",$F$2," ",H43) -> add_trait_species 1 trait_auto_pc_city_preference | G43: 都市星球宜居+20%，干燥/潮湿/寒冷气候宜居-20%，死寂宜居-20% | H43: trait_auto_pc_city_preference
B44: 9 | C44: 遗落星球变异 | D44: × | E44: =_xlfn.CONCAT($C$2,"_species ",$F$2," ",H44) -> add_trait_species 1 trait_auto_pc_relic_preference | G44: 遗落星球宜居+20%，干燥/潮湿/寒冷气候宜居-20%，死寂宜居-20% | H44: trait_auto_pc_relic_preference
B45: 10 | C45: 蜂巢星球变异 | D45: × | E45: =_xlfn.CONCAT($C$2,"_species ",$F$2," ",H45) -> add_trait_species 1 trait_auto_pc_hive_preference | G45: 蜂巢星球宜居+20%，干燥/潮湿/寒冷气候宜居-20%，死寂宜居-20% | H45: trait_auto_pc_hive_preference
B46: 11 | C46: 环形世界变异 | D46: × | E46: =_xlfn.CONCAT($C$2,"_species ",$F$2," ",H46) -> add_trait_species 1 trait_auto_pc_ringworld_habitable_preference | G46: 环形世界/破碎之环宜居+20%，干燥/潮湿/寒冷气候宜居-20%，死寂宜居-20% | H46: trait_auto_pc_ringworld_habitable_preference
B47: 12 | C47: 突触凝炼机变异 | D47: × | E47: =_xlfn.CONCAT($C$2,"_species ",$F$2," ",H47) -> add_trait_species 1 trait_auto_pc_cosmogenesis_world_preference | G47: 突触凝炼机宜居+20%，干燥/潮湿/寒冷气候宜居-20%，死寂宜居-20% | H47: trait_auto_pc_cosmogenesis_world_preference
A48: 有机基础特质 | B48: 1 | C48: 农民 | D48: × | E48: =_xlfn.CONCAT($C$2,"_species ",$F$2," ",H48) -> add_trait_species 1 trait_agrarian | G48: 农夫岗位的岗位效率+15% | H48: trait_agrarian | I48: {=_xlfn._xlws.FILTER(H48:H331,D48:D331="√","未选择特质")} -> 未选择特质
B49: 2 | C49: 足智多谋 | D49: × | E49: =_xlfn.CONCAT($C$2,"_species ",$F$2," ",H49) -> add_trait_species 1 trait_ingenious | G49: 技工岗位的岗位效率+15% | H49: trait_ingenious
B50: 3 | C50: 勤勉 | D50: × | E50: =_xlfn.CONCAT($C$2,"_species ",$F$2," ",H50) -> add_trait_species 1 trait_industrious | G50: 矿工岗位的岗位效率+15% | H50: trait_industrious
B51: 4 | C51: 聪慧 | D51: × | E51: =_xlfn.CONCAT($C$2,"_species ",$F$2," ",H51) -> add_trait_species 1 trait_intelligent | G51: 研究岗位的岗位效率+10% | H51: trait_intelligent
B52: 5 | C52: 节俭 | D52: × | E52: =_xlfn.CONCAT($C$2,"_species ",$F$2," ",H52) -> add_trait_species 1 trait_thrifty | G52: 商贩岗位的岗位效率+25% | H52: trait_thrifty
B53: 6 | C53: 天生工程师 | D53: × | E53: =_xlfn.CONCAT($C$2,"_species ",$F$2," ",H53) -> add_trait_species 1 trait_natural_engineers | G53: 工程学家岗位的岗位效率+15% | H53: trait_natural_engineers
B54: 7 | C54: 天生物理学家 | D54: × | E54: =_xlfn.CONCAT($C$2,"_species ",$F$2," ",H54) -> add_trait_species 1 trait_natural_physicists | G54: 物理学家岗位的岗位效率+15% | H54: trait_natural_physicists
B55: 8 | C55: 天生社会学家 | D55: × | E55: =_xlfn.CONCAT($C$2,"_species ",$F$2," ",H55) -> add_trait_species 1 trait_natural_sociologists | G55: 社会学家岗位的岗位效率+15% | H55: trait_natural_sociologists
B56: 9 | C56: 极易适应 | D56: × | E56: =_xlfn.CONCAT($C$2,"_species ",$F$2," ",H56) -> add_trait_species 1 trait_extremely_adaptive | G56: 宜居性+20% | H56: trait_extremely_adaptive
B57: 10 | C57: 善于适应 | D57: × | E57: =_xlfn.CONCAT($C$2,"_species ",$F$2," ",H57) -> add_trait_species 1 trait_adaptive | G57: 宜居性+10% | H57: trait_adaptive
B58: 11 | C58: 水土不服 | D58: × | E58: =_xlfn.CONCAT($C$2,"_species ",$F$2," ",H58) -> add_trait_species 1 trait_nonadaptive | G58: 宜居性-10% | H58: trait_nonadaptive
B59: 12 | C59: 快速繁殖 | D59: × | E59: =_xlfn.CONCAT($C$2,"_species ",$F$2," ",H59) -> add_trait_species 1 trait_rapid_breeders | G59: 人口增长速度+10% | H59: trait_rapid_breeders
B60: 13 | C60: 缓慢繁殖 | D60: × | E60: =_xlfn.CONCAT($C$2,"_species ",$F$2," ",H60) -> add_trait_species 1 trait_slow_breeders | G60: 人口增长速度-10% | H60: trait_slow_breeders
... B76: 29 | C76: 令人厌恶 | D76: × | E76: =_xlfn.CONCAT($C$2,"_species ",$F$2," ",H76) -> add_trait_species 1 trait_repugnant | G76: 演艺人员岗位的岗位效率-20% | H76: trait_repugnant
B77: 30 | C77: 受提升 | D77: × | E77: =_xlfn.CONCAT($C$2,"_species ",$F$2," ",H77) -> add_trait_species 1 trait_uplifted | H77: trait_uplifted
B78: 31 | C78: 从众 | D78: × | E78: =_xlfn.CONCAT($C$2,"_species ",$F$2," ",H78) -> add_trait_species 1 trait_conformists | G78: 主流思潮吸引力+30% | H78: trait_conformists
B79: 32 | C79: 天性反常 | D79: × | E79: =_xlfn.CONCAT($C$2,"_species ",$F$2," ",H79) -> add_trait_species 1 trait_deviants | G79: 主流思潮吸引力-15% | H79: trait_deviants
B80: 33 | C80: 尊者 | D80: × | E80: =_xlfn.CONCAT($C$2,"_species ",$F$2," ",H80) -> add_trait_species 1 trait_venerable | G80: 领袖寿命+80年 | H80: trait_venerable
B81: 34 | C81: 延年益寿 | D81: × | E81: =_xlfn.CONCAT($C$2,"_species ",$F$2," ",H81) -> add_trait_species 1 trait_enduring | G81: 领袖寿命+20年 | H81: trait_enduring
B82: 35 | C82: 快节奏 | D82: × | E82: =_xlfn.CONCAT($C$2,"_species ",$F$2," ",H82) -> add_trait_species 1 trait_fleeting | G82: 领袖寿命-10年 | H82: trait_fleeting
B83: 36 | C83: 颓废 | D83: × | E83: =_xlfn.CONCAT($C$2,"_species ",$F$2," ",H83) -> add_trait_species 1 trait_decadent | G83: 劳工幸福度-10%，奴隶幸福度-10% | H83: trait_decadent
B84: 37 | C84: 快速复原 | D84: × | E84: =_xlfn.CONCAT($C$2,"_species ",$F$2," ",H84) -> add_trait_species 1 trait_resilient | G84: 防御部队伤害+50% | H84: trait_resilient
B85: 38 | C85: 节约 | D85: × | E85: =_xlfn.CONCAT($C$2,"_species ",$F$2," ",H85) -> add_trait_species 1 trait_conservational | G85: 人口消费品维护费-10% | H85: trait_conservational
B86: 39 | C86: 挥霍 | D86: × | E86: =_xlfn.CONCAT($C$2,"_species ",$F$2," ",H86) -> add_trait_species 1 trait_wasteful | G86: 人口消费品维护费+10% | H86: trait_wasteful
B87: 40 | C87: 闪烁表皮 | D87: × | E87: =_xlfn.CONCAT($C$2,"_species ",$F$2," ",H87) -> add_trait_species 1 trait_lithoid_scintillating | G87: 每个具有奴役或更高生活标准的100人口每月产生0.01稀有水晶 | H87: trait_lithoid_scintillating
B88: 41 | C88: 气态副产物 | D88: × | E88: =_xlfn.CONCAT($C$2,"_species ",$F$2," ",H88) -> add_trait_species 1 trait_lithoid_gaseous_byproducts | G88: 每个具有奴役或更高生活标准的100人口每月产生0.01异星天然气 | H88: trait_lithoid_gaseous_byproducts
B89: 42 | C89: 易爆排泄物 | D89: × | E89: =_xlfn.CONCAT($C$2,"_species ",$F$2," ",H89) -> add_trait_species 1 trait_lithoid_volatile_excretions | G89: 每个具有奴役或更高生活标准的100人口每月产生0.01易爆微粒 | H89: trait_lithoid_volatile_excretions
... B103: 56 | C103: 异星新陈代谢 | D103: × | E103: =_xlfn.CONCAT($C$2,"_species ",$F$2," ",H103) -> add_trait_species 1 trait_exotic_metabolism | G103: 领袖寿命+50年，异星天然气维护费+0.125 | H103: trait_exotic_metabolism
A104: 有机表型特质 | B104: 1 | C104: 卵生 | D104: × | E104: =_xlfn.CONCAT($C$2,"_species ",$F$2," ",H104) -> add_trait_species 1 trait_egg_laying | G104: 人口生长速度：当生活在当地食物（或矿物）产出盈余的行星上时+15% | H104: trait_egg_laying
B105: 2 | C105: 季节性休眠 | D105: × | E105: =_xlfn.CONCAT($C$2,"_species ",$F$2," ",H105) -> add_trait_species 1 trait_seasonal_dormancy | G105: 受雇人口维护费-15%，居民人口维护费-75% | H105: trait_seasonal_dormancy
B106: 3 | C106: 空心骨骼 | D106: × | E106: =_xlfn.CONCAT($C$2,"_species ",$F$2," ",H106) -> add_trait_species 1 trait_hollow_bones | G106: 每行星规模导致的劳工和低级子个体的岗位效率-0.67% | H106: trait_hollow_bones
B107: 4 | C107: 根植 | D107: × | E107: =_xlfn.CONCAT($C$2,"_species ",$F$2," ",H107) -> add_trait_species 1 trait_rooted | G107: 人口不会自动迁移，强制迁移花费+200% | H107: trait_rooted
B108: 5 | C108: 酸性血液 | D108: × | E108: =_xlfn.CONCAT($C$2,"_species ",$F$2," ",H108) -> add_trait_species 1 trait_acidic_vascularity | G108: 陆军会爆炸性死亡对敌方陆军造成250伤害，净化人口资源产出-75% | H108: trait_acidic_vascularity
B109: 6 | C109: 有壳 | D109: × | E109: =_xlfn.CONCAT($C$2,"_species ",$F$2," ",H109) -> add_trait_species 1 trait_shelled | G109: 人口住房使用-10%，宜居性+10% | H109: trait_shelled
B110: 7 | C110: 保护色 | D110: × | E110: =_xlfn.CONCAT($C$2,"_species ",$F$2," ",H110) -> add_trait_species 1 trait_camouflage | G110: 物理学家岗位的岗位效率+10%，陆军生命值+20% | H110: trait_camouflage
B111: 8 | C111: 色语 | D111: × | E111: =_xlfn.CONCAT($C$2,"_species ",$F$2," ",H111) -> add_trait_species 1 trait_chromalogs | G111: 物理学家岗位的岗位效率+20%，官僚岗位的岗位效率+20%，陆军生命值+40%，主流思潮吸引力+15% | H111: trait_chromalogs
B112: 9 | C112: 易碎 | D112: × | E112: =_xlfn.CONCAT($C$2,"_species ",$F$2," ",H112) -> add_trait_species 1 trait_brittle | G112: 人口舒适度使用+0.5 | H112: trait_brittle
B113: 10 | C113: 群居 | D113: × | E113: =_xlfn.CONCAT($C$2,"_species ",$F$2," ",H113) -> add_trait_species 1 trait_familial | G113: 同一行星上拥有该特质的每100人口产生的幸福度+0.1（最大+20%） | H113: trait_familial
B114: 11 | C114: 透水皮肤 | D114: × | E114: =_xlfn.CONCAT($C$2,"_species ",$F$2," ",H114) -> add_trait_species 1 trait_permeable_skin | G114: 与偏好处于不同气候类别的星球上的宜居性-20% | H114: trait_permeable_skin
B115: 12 | C115: 遗传记忆 | D115: × | E115: =_xlfn.CONCAT($C$2,"_species ",$F$2," ",H115) -> add_trait_species 1 trait_genetic_memory | G115: 殖民地建立年限提升的宜居性每年+0.5%（最大50%） | H115: trait_genetic_memory
B116: 13 | C116: 早产 | D116: × | E116: =_xlfn.CONCAT($C$2,"_species ",$F$2," ",H116) -> add_trait_species 1 trait_nascent_stage | G116: 带有该特质的人口在新生的前5为未开智状态 | H116: trait_nascent_stage
... B119: 16 | C119: 备用器官 | D119: × | E119: =_xlfn.CONCAT($C$2,"_species ",$F$2," ",H119) -> add_trait_species 1 trait_spare_organs | G119: 牲口岗位效率+50%，进攻部队死亡时20%概率生成替换陆军，领袖第一次死亡时可以幸存 | H119: trait_spare_organs
A120: 强夺天工特质 | B120: 1 | C120: 一现昙花 | D120: × | E120: =_xlfn.CONCAT($C$2,"_species ",$F$2," ",H120) -> add_trait_species 1 trait_auto_mod_overtuned | G120: 领袖寿命-20年，自动改造特质以适应人口当前从事的工作 | H120: trait_auto_mod_overtuned
B121: 2 | C121: 移接适应力 | D121: × | E121: =_xlfn.CONCAT($C$2,"_species ",$F$2," ",H121) -> add_trait_species 1 trait_spliced_adaptability | G121: 领袖寿命-10年，宜居性+20% | H121: trait_spliced_adaptability
B122: 3 | C122: 激素强健 | D122: × | E122: =_xlfn.CONCAT($C$2,"_species ",$F$2," ",H122) -> add_trait_species 1 trait_juiced_power | G122: 陆军伤害+40%，领袖寿命-10年，劳工和低级子个体的岗位效率+5% | H122: trait_juiced_power
B123: 4 | C123: 农业附肢 | D123: × | E123: =_xlfn.CONCAT($C$2,"_species ",$F$2," ",H123) -> add_trait_species 1 trait_farm_hands | G123: 领袖寿命-10年，农夫岗位的岗位效率+15% | H123: trait_farm_hands
B124: 5 | C124: 职业矿工 | D124: × | E124: =_xlfn.CONCAT($C$2,"_species ",$F$2," ",H124) -> add_trait_species 1 trait_crack_miner | G124: 领袖寿命-10年，矿工岗位的岗位效率+15% | H124: trait_crack_miner
B125: 6 | C125: 技工天赋 | D125: × | E125: =_xlfn.CONCAT($C$2,"_species ",$F$2," ",H125) -> add_trait_species 1 trait_technical_skill | G125: 领袖寿命-10年，技工岗位的岗位效率+15% | H125: trait_technical_skill
B126: 7 | C126: 商业天才 | D126: × | E126: =_xlfn.CONCAT($C$2,"_species ",$F$2," ",H126) -> add_trait_species 1 trait_commercial_genius | G126: 领袖寿命-10年，商贩岗位的岗位效率+25% | H126: trait_commercial_genius
B127: 8 | C127: 匠心微笑 | D127: × | E127: =_xlfn.CONCAT($C$2,"_species ",$F$2," ",H127) -> add_trait_species 1 trait_crafted_smiles | G127: 领袖寿命-10年，演艺人员岗位的岗位效率+15% | H127: trait_crafted_smiles
B128: 9 | C128: 低廉维护 | D128: × | E128: =_xlfn.CONCAT($C$2,"_species ",$F$2," ",H128) -> add_trait_species 1 trait_low_maintenance | G128: 领袖寿命-10年，人口消费品维护费-10% | H128: trait_low_maintenance
B129: 10 | C129: 增强智能 | D129: × | E129: =_xlfn.CONCAT($C$2,"_species ",$F$2," ",H129) -> add_trait_species 1 trait_artificial_intelligence | G129: 领袖寿命-10年，研究人员岗位的岗位效率+10% | H129: trait_artificial_intelligence
B130: 11 | C130: 基因辅导 | D130: × | E130: =_xlfn.CONCAT($C$2,"_species ",$F$2," ",H130) -> add_trait_species 1 trait_gene_mentorship | G130: 领袖寿命-10年，领袖获得经验+30% | H130: trait_gene_mentorship
B131: 12 | C131: 宣泄传统 | D131: × | E131: =_xlfn.CONCAT($C$2,"_species ",$F$2," ",H131) -> add_trait_species 1 trait_expressed_tradition | G131: 领袖寿命-10年，官僚岗位的岗位效率+10% | H131: trait_expressed_tradition
B132: 13 | C132: 升格突触 | D132: × | E132: =_xlfn.CONCAT($C$2,"_species ",$F$2," ",H132) -> add_trait_species 1 trait_elevated_synapses | G132: 领袖寿命-30年，领袖维护费-25%，领袖负面特质上限-1，研究人员岗位的岗位效率+20% | H132: trait_elevated_synapses
... B134: 15 | C134: 过度忍耐 | D134: × | E134: =_xlfn.CONCAT($C$2,"_species ",$F$2," ",H134) -> add_trait_species 1 trait_excessive_endurance | G134: 领袖寿命-30年，宜居性+30%，岗位效率+5% | H134: trait_excessive_endurance
...

Sheet 领袖特质
A1: 4.0.22领袖特质收录（2025.08.25）
A2: 选中/全部领袖移除全部负面特质 | F2: 选中/全部领袖移除全部正面特质 | J2: 选中/全部领袖移除全部特质 | K2: 添加（add_trait）和移除（remove_trait）代码，可以使用下拉菜单进行选择，ctrl+shift+L开启关闭筛选 移除全部特质：选中领袖移除选择第一行，全部领袖移除（无需选中）选择第二行。 选择领袖类型：选择非格式塔节点时，需要在领袖界面选中领袖；选择格式塔节点时，不要选中任何东西。 批量添加选中特质：在筛选栏里打“√”后，会一次性添加勾选特质，但选中过多特质时，控制台输入有上限会导致后面的特质无法添加，建议直接输入时勾选不超过15个，如果超过可转变为run代码形式添加。
A3: effect remove_all_negative_traits = yes | F3: effect remove_all_positive_traits = yes | J3: effect remove_all_traits = yes
A4: effect every_owned_leader = {remove_all_negative_traits = yes} | F4: effect every_owned_leader = {remove_all_positive_traits = yes} | J4: effect every_owned_leader = {remove_all_traits = yes}
A5: 添加/删除代码 | C5: add_trait | F5: 选择领袖类型 | J5: 非格式塔节点
A6: 批量添加/移除选中特质 | C6: =_xlfn.CONCAT("effect ",_xlfn.XLOOKUP(J5,$W$9:$W$13,$X$9:$X$13),_xlfn.XLOOKUP(J5,$W$9:$W$13,$Y$9:$Y$13)," ",_xlfn.XLOOKUP(J5,$W$9:$W$13,$Z$9:$Z$13),$C$5," = { trait = ",_xlfn.TEXTJOIN(_xlfn.CONCAT(" } ",$C$5," = { trait = "),TRUE,S8:S728)," }}}") -> effect leader = { add_trait = { trait = 未选择特质 }}} | J6: 跳转创建领袖
A7: 序号 | B7: 名称 | C7: 筛选 | D7: 行政官 | E7: 指挥官 | F7: 科学家 | G7: 职业需求 | H7: 其他需求 | I7: 互斥特质 | J7: 自适应代码 | K7: 属性 | L7: 内阁 | M7: 总督 | N7: 特殊 | O7: 等级 | P7: 效果 | Q7: 代码 | R7: 来源
A8: 1 | B8: 护卫舰建造专精 | C8: × | E8: √ | H8: 无至臻完人DLC，需要科技驱逐舰 | I8: 驱逐舰建造专精，巡洋舰建造专精，战列舰建造专精 | J8: =_xlfn.CONCAT("effect ",_xlfn.XLOOKUP($J$5,$W$9:$W$13,$X$9:$X$13),_xlfn.XLOOKUP($J$5,$W$9:$W$13,$Y$9:$Y$13)," ",_xlfn.XLOOKUP($J$5,$W$9:$W$13,$Z$9:$Z$13),$C$5," = { trait = ",Q8," }}}") -> effect leader = { add_trait = { trait = trait_ruler_corvette_focus }}} | K8: 普通 | L8: √ | N8: √ | O8: Ⅰ | P8: 作为内阁官员的帝国效应：护卫舰建造花费-30% | Q8: trait_ruler_corvette_focus | R8: 00_admiral_traits.txt | S8: {=_xlfn._xlws.FILTER(Q8:Q728,C8:C728="√","未选择特质")} -> 未选择特质 | W8: 控制板
A9: 2 | B9: 驱逐舰建造专精 | C9: × | E9: √ | H9: 无至臻完人DLC，需要科技驱逐舰 | I9: 护卫舰建造专精，巡洋舰建造专精，战列舰建造专精 | J9: =_xlfn.CONCAT("effect ",_xlfn.XLOOKUP($J$5,$W$9:$W$13,$X$9:$X$13),_xlfn.XLOOKUP($J$5,$W$9:$W$13,$Y$9:$Y$13)," ",_xlfn.XLOOKUP($J$5,$W$9:$W$13,$Z$9:$Z$13),$C$5," = { trait = ",Q9," }}}") -> effect leader = { add_trait = { trait = trait_ruler_destroyer_focus }}} | K9: 普通 | L9: √ | N9: √ | O9: Ⅰ | P9: 作为内阁官员的帝国效应：驱逐舰建造花费-30% | Q9: trait_ruler_destroyer_focus | R9: 00_admiral_traits.txt | W9: 非格式塔节点 | X9: leader = {
A10: 3 | B10: 巡洋舰建造专精 | C10: × | E10: √ | H10: 无至臻完人DLC，需要科技巡洋舰 | I10: 护卫舰建造专精，驱逐舰建造专精，战列舰建造专精 | J10: =_xlfn.CONCAT("effect ",_xlfn.XLOOKUP($J$5,$W$9:$W$13,$X$9:$X$13),_xlfn.XLOOKUP($J$5,$W$9:$W$13,$Y$9:$Y$13)," ",_xlfn.XLOOKUP($J$5,$W$9:$W$13,$Z$9:$Z$13),$C$5," = { trait = ",Q10," }}}") -> effect leader = { add_trait = { trait = trait_ruler_cruiser_focus }}} | K10: 普通 | L10: √ | N10: √ | O10: Ⅰ | P10: 作为内阁官员的帝国效应：巡洋舰建造花费-30% | Q10: trait_ruler_cruiser_focus | R10: 00_admiral_traits.txt | W10: 意识节点 | X10: every_owned_leader = { limit = { | Y10: is_councilor_type = councilor_gestalt_cognitive | Z10: }
A11: 4 | B11: 战列舰建造专精 | C11: × | E11: √ | H11: 无至臻完人DLC，需要科技战列舰 | I11: 护卫舰建造专精，驱逐舰建造专精，巡洋舰建造专精 | J11: =_xlfn.CONCAT("effect ",_xlfn.XLOOKUP($J$5,$W$9:$W$13,$X$9:$X$13),_xlfn.XLOOKUP($J$5,$W$9:$W$13,$Y$9:$Y$13)," ",_xlfn.XLOOKUP($J$5,$W$9:$W$13,$Z$9:$Z$13),$C$5," = { trait = ",Q11," }}}") -> effect leader = { add_trait = { trait = trait_ruler_battleship_focus }}} | K11: 普通 | L11: √ | N11: √ | O11: Ⅰ | P11: 作为内阁官员的帝国效应：战列舰建造花费-30% | Q11: trait_ruler_battleship_focus | R11: 00_admiral_traits.txt | W11: 生长节点 | X11: every_owned_leader = { limit = { | Y11: is_councilor_type = councilor_gestalt_growth | Z11: }
A12: 5 | B12: 舰队后勤专家 | C12: × | E12: √ | H12: 无至臻完人DLC | J12: =_xlfn.CONCAT("effect ",_xlfn.XLOOKUP($J$5,$W$9:$W$13,$X$9:$X$13),_xlfn.XLOOKUP($J$5,$W$9:$W$13,$Y$9:$Y$13)," ",_xlfn.XLOOKUP($J$5,$W$9:$W$13,$Z$9:$Z$13),$C$5," = { trait = ",Q12," }}}") -> effect leader = { add_trait = { trait = leader_trait_fleet_logistician }}} | K12: 普通 | N12: √ | O12: Ⅰ | P12: 军用舰队效果：驻港舰船维护费-15% | Q12: leader_trait_fleet_logistician | R12: 00_admiral_traits.txt | W12: 管控节点 | X12: every_owned_leader = { limit = { | Y12: is_councilor_type = councilor_gestalt_regulatory | Z12: }
A13: 6 | B13: 出其不意 （游击者） | C13: × | E13: √ | J13: =_xlfn.CONCAT("effect ",_xlfn.XLOOKUP($J$5,$W$9:$W$13,$X$9:$X$13),_xlfn.XLOOKUP($J$5,$W$9:$W$13,$Y$9:$Y$13)," ",_xlfn.XLOOKUP($J$5,$W$9:$W$13,$Z$9:$Z$13),$C$5," = { trait = ",Q13," }}}") -> effect leader = { add_trait = { trait = leader_trait_skirmisher }}} | K13: 普通 | L13: √ | O13: Ⅰ | P13: 作为内阁官员的帝国效应：舰船武器伤害+5%，亚光速航速+15% | Q13: leader_trait_skirmisher | R13: 00_admiral_traits.txt | W13: 军团节点 | X13: every_owned_leader = { limit = { | Y13: is_councilor_type = councilor_gestalt_legion | Z13: }
A14: 7 | B14: 火力全开 （侵略性攻击思维；侵略性攻击模式） | C14: × | E14: √ | I14: 谨慎 | J14: =_xlfn.CONCAT("effect ",_xlfn.XLOOKUP($J$5,$W$9:$W$13,$X$9:$X$13),_xlfn.XLOOKUP($J$5,$W$9:$W$13,$Y$9:$Y$13)," ",_xlfn.XLOOKUP($J$5,$W$9:$W$13,$Z$9:$Z$13),$C$5," = { trait = ",Q14," }}}") -> effect leader = { add_trait = { trait = leader_trait_aggressive }}} | K14: 普通 | O14: Ⅰ | P14: 军用舰队效果：舰船武器射速+5%，舰船武器伤害+5% | Q14: leader_trait_aggressive | R14: 00_admiral_traits.txt
A15: 8 | B15: 谨慎 （小心谨慎） | C15: × | E15: √ | I15: 火力全开 | J15: =_xlfn.CONCAT("effect ",_xlfn.XLOOKUP($J$5,$W$9:$W$13,$X$9:$X$13),_xlfn.XLOOKUP($J$5,$W$9:$W$13,$Y$9:$Y$13)," ",_xlfn.XLOOKUP($J$5,$W$9:$W$13,$Z$9:$Z$13),$C$5," = { trait = ",Q15," }}}") -> effect leader = { add_trait = { trait = leader_trait_cautious }}} | K15: 普通 | O15: Ⅰ | P15: 军用舰队效果：射程+15%，战斗撤离几率+5% | Q15: leader_trait_cautious | R15: 00_admiral_traits.txt
A16: 9 | B16: 坚强不屈 | C16: × | E16: √ | I16: 神经质，吊儿郎当，诡术师 | J16: =_xlfn.CONCAT("effect ",_xlfn.XLOOKUP($J$5,$W$9:$W$13,$X$9:$X$13),_xlfn.XLOOKUP($J$5,$W$9:$W$13,$Y$9:$Y$13)," ",_xlfn.XLOOKUP($J$5,$W$9:$W$13,$Z$9:$Z$13),$C$5," = { trait = ",Q16," }}}") -> effect leader = { add_trait = { trait = leader_trait_unyielding }}} | K16: 普通 | O16: Ⅰ | P16: 军用舰队效果：船体值+20%，战斗撤离几率-20% | Q16: leader_trait_unyielding | R16: 00_admiral_traits.txt
A17: 10 | B17: 工程师 （自动维修系统） | C17: × | E17: √ | J17: =_xlfn.CONCAT("effect ",_xlfn.XLOOKUP($J$5,$W$9:$W$13,$X$9:$X$13),_xlfn.XLOOKUP($J$5,$W$9:$W$13,$Y$9:$Y$13)," ",_xlfn.XLOOKUP($J$5,$W$9:$W$13,$Z$9:$Z$13),$C$5," = { trait = ",Q17," }}}") -> effect leader = { add_trait = { trait = leader_trait_engineer }}} | K17: 普通 | O17: Ⅰ | P17: 军用舰队效果：每日船体再生+0.5%，每日装甲再生+1% | Q17: leader_trait_engineer | R17: 00_admiral_traits.txt
A18: 11 | B18: 诡术师 | C18: × | E18: √ | I18: 坚强不屈，不计后果 | J18: =_xlfn.CONCAT("effect ",_xlfn.XLOOKUP($J$5,$W$9:$W$13,$X$9:$X$13),_xlfn.XLOOKUP($J$5,$W$9:$W$13,$Y$9:$Y$13)," ",_xlfn.XLOOKUP($J$5,$W$9:$W$13,$Z$9:$Z$13),$C$5," = { trait = ",Q18," }}}") -> effect leader = { add_trait = { trait = leader_trait_trickster }}} | K18: 普通 | O18: Ⅰ | P18: 军用舰队效果：紧急超光速脱离承受风险-20%，战斗撤离几率+40% | Q18: leader_trait_trickster | R18: 00_admiral_traits.txt
A19: 12 | B19: 片甲不留 | C19: × | E19: √ | G19: 舰队司令 | I19: 应急维修 | J19: =_xlfn.CONCAT("effect ",_xlfn.XLOOKUP($J$5,$W$9:$W$13,$X$9:$X$13),_xlfn.XLOOKUP($J$5,$W$9:$W$13,$Y$9:$Y$13)," ",_xlfn.XLOOKUP($J$5,$W$9:$W$13,$Z$9:$Z$13),$C$5," = { trait = ",Q19," }}}") -> effect leader = { add_trait = { trait = leader_trait_wrecker }}} | K19: 老练 | O19: Ⅰ | P19: 军用舰队效果：舰船武器伤害+15%，产生残骸概率-35% | Q19: leader_trait_wrecker | R19: 00_admiral_traits.txt
A20: 13 | C20: × | E20: √ | G20: 舰队司令 | J20: =_xlfn.CONCAT("effect ",_xlfn.XLOOKUP($J$5,$W$9:$W$13,$X$9:$X$13),_xlfn.XLOOKUP($J$5,$W$9:$W$13,$Y$9:$Y$13)," ",_xlfn.XLOOKUP($J$5,$W$9:$W$13,$Z$9:$Z$13),$C$5," = { trait = ",Q20," }}}") -> effect leader = { add_trait = { trait = leader_trait_wrecker_2 }}} | K20: 老练 | O20: Ⅱ | P20: 军用舰队效果：舰船武器伤害+25%，产生残骸概率-50% | Q20: leader_trait_wrecker_2 | R20: 00_admiral_traits.txt
A21: 14 | B21: 赶尽杀绝 | C21: × | E21: √ | G21: 陆军司令 | J21: =_xlfn.CONCAT("effect ",_xlfn.XLOOKUP($J$5,$W$9:$W$13,$X$9:$X$13),_xlfn.XLOOKUP($J$5,$W$9:$W$13,$Y$9:$Y$13)," ",_xlfn.XLOOKUP($J$5,$W$9:$W$13,$Z$9:$Z$13),$C$5," = { trait = ",Q21," }}}") -> effect leader = { add_trait = { trait = leader_trait_annihilator }}} | K21: 老练 | O21: Ⅰ | P21: 军用舰队效果：轨道轰炸伤害+100%，舰船武器伤害+5% | Q21: leader_trait_annihilator | R21: 00_admiral_traits.txt
A22: 15 | C22: × | E22: √ | G22: 陆军司令 | J22: =_xlfn.CONCAT("effect ",_xlfn.XLOOKUP($J$5,$W$9:$W$13,$X$9:$X$13),_xlfn.XLOOKUP($J$5,$W$9:$W$13,$Y$9:$Y$13)," ",_xlfn.XLOOKUP($J$5,$W$9:$W$13,$Z$9:$Z$13),$C$5," = { trait = ",Q22," }}}") -> effect leader = { add_trait = { trait = leader_trait_annihilator_2 }}} | K22: 老练 | O22: Ⅱ | P22: 军用舰队效果：轨道轰炸伤害+200%，舰船武器伤害+10% | Q22: leader_trait_annihilator_2 | R22: 00_admiral_traits.txt
A23: 16 | B23: 大炮兵主义 （炮术专家；炮术模块） | C23: × | E23: √ | G23: 舰队司令 | J23: =_xlfn.CONCAT("effect ",_xlfn.XLOOKUP($J$5,$W$9:$W$13,$X$9:$X$13),_xlfn.XLOOKUP($J$5,$W$9:$W$13,$Y$9:$Y$13)," ",_xlfn.XLOOKUP($J$5,$W$9:$W$13,$Z$9:$Z$13),$C$5," = { trait = ",Q23," }}}") -> effect leader = { add_trait = { trait = leader_trait_artillerist }}} | K23: 老练 | O23: Ⅰ | P23: 军用舰队效果：舰船武器伤害+10%，追踪+7.5% | Q23: leader_trait_artillerist | R23: 00_admiral_traits.txt
A24: 17 | C24: × | E24: √ | G24: 舰队司令 | J24: =_xlfn.CONCAT("effect ",_xlfn.XLOOKUP($J$5,$W$9:$W$13,$X$9:$X$13),_xlfn.XLOOKUP($J$5,$W$9:$W$13,$Y$9:$Y$13)," ",_xlfn.XLOOKUP($J$5,$W$9:$W$13,$Z$9:$Z$13),$C$5," = { trait = ",Q24," }}}") -> effect leader = { add_trait = { trait = leader_trait_artillerist_2 }}} | K24: 老练 | O24: Ⅱ | P24: 军用舰队效果：舰船武器伤害+15%，追踪+10%，命中+7.5% | Q24: leader_trait_artillerist_2 | R24: 00_admiral_traits.txt
A25: 18 | B25: 威风堂堂 （指挥中枢；控制主机） | C25: × | E25: √ | G25: 舰队司令 | J25: =_xlfn.CONCAT("effect ",_xlfn.XLOOKUP($J$5,$W$9:$W$13,$X$9:$X$13),_xlfn.XLOOKUP($J$5,$W$9:$W$13,$Y$9:$Y$13)," ",_xlfn.XLOOKUP($J$5,$W$9:$W$13,$Z$9:$Z$13),$C$5," = { trait = ",Q25," }}}") -> effect leader = { add_trait = { trait = leader_trait_commanding_presence }}} | K25: 老练 | O25: Ⅰ | P25: 军用舰队效果：舰队指挥上限+50 | Q25: leader_trait_commanding_presence | R25: 00_admiral_traits.txt
A26: 19 | C26: × | E26: √ | G26: 舰队司令 | J26: =_xlfn.CONCAT("effect ",_xlfn.XLOOKUP($J$5,$W$9:$W$13,$X$9:$X$13),_xlfn.XLOOKUP($J$5,$W$9:$W$13,$Y$9:$Y$13)," ",_xlfn.XLOOKUP($J$5,$W$9:$W$13,$Z$9:$Z$13),$C$5," = { trait = ",Q26," }}}") -> effect leader = { add_trait = { trait = leader_trait_commanding_presence_2 }}} | K26: 老练 | O26: Ⅱ | P26: 军用舰队效果：舰队指挥上限+80 | Q26: leader_trait_commanding_presence_2 | R26: 00_admiral_traits.txt
A27: 20 | B27: 物资掠夺 （拆卸能手；拆卸器） | C27: × | E27: √ | G27: 舰队司令 | J27: =_xlfn.CONCAT("effect ",_xlfn.XLOOKUP($J$5,$W$9:$W$13,$X$9:$X$13),_xlfn.XLOOKUP($J$5,$W$9:$W$13,$Y$9:$Y$13)," ",_xlfn.XLOOKUP($J$5,$W$9:$W$13,$Z$9:$Z$13),$C$5," = { trait = ",Q27," }}}") -> effect leader = { add_trait = { trait = leader_trait_corsair }}} | K27: 老练 | N27: √ | O27: Ⅰ | P27: 军用舰队效果：每摧毁一艘敌舰能量币+6 | Q27: leader_trait_corsair | R27: 00_admiral_traits.txt
A28: 21 | C28: × | E28: √ | G28: 舰队司令 | J28: =_xlfn.CONCAT("effect ",_xlfn.XLOOKUP($J$5,$W$9:$W$13,$X$9:$X$13),_xlfn.XLOOKUP($J$5,$W$9:$W$13,$Y$9:$Y$13)," ",_xlfn.XLOOKUP($J$5,$W$9:$W$13,$Z$9:$Z$13),$C$5," = { trait = ",Q28," }}}") -> effect leader = { add_trait = { trait = leader_trait_corsair_2 }}} | K28: 老练 | N28: √ | O28: Ⅱ | P28: 军用舰队效果：每摧毁一艘敌舰能量币+15，隐形强度+1 | Q28: leader_trait_corsair_2 | R28: 00_admiral_traits.txt
A29: 22 | B29: 定点爆破 | C29: × | E29: √ | G29: 陆军司令 | J29: =_xlfn.CONCAT("effect ",_xlfn.XLOOKUP($J$5,$W$9:$W$13,$X$9:$X$13),_xlfn.XLOOKUP($J$5,$W$9:$W$13,$Y$9:$Y$13)," ",_xlfn.XLOOKUP($J$5,$W$9:$W$13,$Z$9:$Z$13),$C$5," = { trait = ",Q29," }}}") -> effect leader = { add_trait = { trait = leader_trait_demolisher }}} | K29: 老练 | O29: Ⅰ | P29: 军用舰队效果：对恒星基地伤害+30% | Q29: leader_trait_demolisher | R29: 00_admiral_traits.txt
A30: 23 | C30: × | E30: √ | G30: 陆军司令 | J30: =_xlfn.CONCAT("effect ",_xlfn.XLOOKUP($J$5,$W$9:$W$13,$X$9:$X$13),_xlfn.XLOOKUP($J$5,$W$9:$W$13,$Y$9:$Y$13)," ",_xlfn.XLOOKUP($J$5,$W$9:$W$13,$Z$9:$Z$13),$C$5," = { trait = ",Q30," }}}") -> effect leader = { add_trait = { trait = leader_trait_demolisher_2 }}} | K30: 老练 | O30: Ⅱ | P30: 军用舰队效果：对恒星基地伤害+50% | Q30: leader_trait_demolisher_2 | R30: 00_admiral_traits.txt
A31: 24 | B31: 残舰拆解 （破船手；破船机） | C31: × | E31: √ | G31: 舰队司令；陆军司令 | J31: =_xlfn.CONCAT("effect ",_xlfn.XLOOKUP($J$5,$W$9:$W$13,$X$9:$X$13),_xlfn.XLOOKUP($J$5,$W$9:$W$13,$Y$9:$Y$13)," ",_xlfn.XLOOKUP($J$5,$W$9:$W$13,$Z$9:$Z$13),$C$5," = { trait = ",Q31," }}}") -> effect leader = { add_trait = { trait = leader_trait_shipbreaker }}} | K31: 老练 | O31: Ⅰ | P31: 军用舰队效果：每摧毁一艘敌舰合金+3 | Q31: leader_trait_shipbreaker | R31: 00_admiral_traits.txt
A32: 25 | C32: × | E32: √ | G32: 舰队司令；陆军司令 | J32: =_xlfn.CONCAT("effect ",_xlfn.XLOOKUP($J$5,$W$9:$W$13,$X$9:$X$13),_xlfn.XLOOKUP($J$5,$W$9:$W$13,$Y$9:$Y$13)," ",_xlfn.XLOOKUP($J$5,$W$9:$W$13,$Z$9:$Z$13),$C$5," = { trait = ",Q32," }}}") -> effect leader = { add_trait = { trait = leader_trait_shipbreaker_2 }}} | K32: 老练 | O32: Ⅱ | P32: 军用舰队效果：装甲硬化+15%，每摧毁一艘敌舰合金+8 | Q32: leader_trait_shipbreaker_2 | R32: 00_admiral_traits.txt
A33: 26 | B33: 远古科技专精 | C33: × | E33: √ | G33: 舰队司令 | I33: 与其他舰队专精互斥 | J33: =_xlfn.CONCAT("effect ",_xlfn.XLOOKUP($J$5,$W$9:$W$13,$X$9:$X$13),_xlfn.XLOOKUP($J$5,$W$9:$W$13,$Y$9:$Y$13)," ",_xlfn.XLOOKUP($J$5,$W$9:$W$13,$Z$9:$Z$13),$C$5," = { trait = ",Q33," }}}") -> effect leader = { add_trait = { trait = leader_trait_archaeo_specialization }}} | K33: 老练 | O33: Ⅰ | P33: 军用舰队效果：远古科技武器伤害+20%，远古科技武器射速+15% | Q33: leader_trait_archaeo_specialization | R33: 00_admiral_traits.txt
A34: 27 | C34: × | E34: √ | G34: 舰队司令 | I34: 与其他舰队专精互斥 | J34: =_xlfn.CONCAT("effect ",_xlfn.XLOOKUP($J$5,$W$9:$W$13,$X$9:$X$13),_xlfn.XLOOKUP($J$5,$W$9:$W$13,$Y$9:$Y$13)," ",_xlfn.XLOOKUP($J$5,$W$9:$W$13,$Z$9:$Z$13),$C$5," = { trait = ",Q34," }}}") -> effect leader = { add_trait = { trait = leader_trait_archaeo_specialization_2 }}} | K34: 老练 | O34: Ⅱ | P34: 军用舰队效果：远古科技武器伤害+35%，远古科技武器射速+35% | Q34: leader_trait_archaeo_specialization_2 | R34: 00_admiral_traits.txt
A35: 28 | B35: 炮击专精 | C35: × | E35: √ | G35: 舰队司令 | H35: 需要科技驱逐舰或刺蜂 | I35: 与其他舰队专精互斥 | J35: =_xlfn.CONCAT("effect ",_xlfn.XLOOKUP($J$5,$W$9:$W$13,$X$9:$X$13),_xlfn.XLOOKUP($J$5,$W$9:$W$13,$Y$9:$Y$13)," ",_xlfn.XLOOKUP($J$5,$W$9:$W$13,$Z$9:$Z$13),$C$5," = { trait = ",Q35," }}}") -> effect leader = { add_trait = { trait = leader_trait_artillery_specialization }}} | K35: 老练 | O35: Ⅰ | P35: 军用舰队效果：炮击武器伤害+20%，舰船武器射程+15% | Q35: leader_trait_artillery_specialization | R35: 00_admiral_traits.txt
A36: 29 | C36: × | E36: √ | G36: 舰队司令 | H36: 需要科技驱逐舰或刺蜂 | I36: 与其他舰队专精互斥 | J36: =_xlfn.CONCAT("effect ",_xlfn.XLOOKUP($J$5,$W$9:$W$13,$X$9:$X$13),_xlfn.XLOOKUP($J$5,$W$9:$W$13,$Y$9:$Y$13)," ",_xlfn.XLOOKUP($J$5,$W$9:$W$13,$Z$9:$Z$13),$C$5," = { trait = ",Q36," }}}") -> effect leader = { add_trait = { trait = leader_trait_artillery_specialization_2 }}} | K36: 老练 | O36: Ⅱ | P36: 军用舰队效果：炮击武器伤害+35%，舰船武器射程+35% | Q36: leader_trait_artillery_specialization_2 | R36: 00_admiral_traits.txt
A37: 30 | B37: 航母专精 | C37: × | E37: √ | G37: 舰队司令 | H37: 需要科技巡洋舰或孵后 | I37: 与其他舰队专精互斥 | J37: =_xlfn.CONCAT("effect ",_xlfn.XLOOKUP($J$5,$W$9:$W$13,$X$9:$X$13),_xlfn.XLOOKUP($J$5,$W$9:$W$13,$Y$9:$Y$13)," ",_xlfn.XLOOKUP($J$5,$W$9:$W$13,$Z$9:$Z$13),$C$5," = { trait = ",Q37," }}}") -> effect leader = { add_trait = { trait = leader_trait_carrier_specialization }}} | K37: 老练 | O37: Ⅰ | P37: 军用舰队效果：舰载机伤害+15%，舰载机射速+15%，舰船交战范围+15% | Q37: leader_trait_carrier_specialization | R37: 00_admiral_traits.txt
A38: 31 | C38: × | E38: √ | G38: 舰队司令 | H38: 需要科技巡洋舰或孵后 | I38: 与其他舰队专精互斥 | J38: =_xlfn.CONCAT("effect ",_xlfn.XLOOKUP($J$5,$W$9:$W$13,$X$9:$X$13),_xlfn.XLOOKUP($J$5,$W$9:$W$13,$Y$9:$Y$13)," ",_xlfn.XLOOKUP($J$5,$W$9:$W$13,$Z$9:$Z$13),$C$5," = { trait = ",Q38," }}}") -> effect leader = { add_trait = { trait = leader_trait_carrier_specialization_2 }}} | K38: 老练 | O38: Ⅱ | P38: 军用舰队效果：舰载机伤害+25%，舰载机射速+25%，舰船交战范围+25% | Q38: leader_trait_carrier_specialization_2 | R38: 00_admiral_traits.txt
A39: 32 | B39: 制导专精 | C39: × | E39: √ | G39: 舰队司令 | H39: 需要科技核导弹 | I39: 与其他舰队专精互斥 | J39: =_xlfn.CONCAT("effect ",_xlfn.XLOOKUP($J$5,$W$9:$W$13,$X$9:$X$13),_xlfn.XLOOKUP($J$5,$W$9:$W$13,$Y$9:$Y$13)," ",_xlfn.XLOOKUP($J$5,$W$9:$W$13,$Z$9:$Z$13),$C$5," = { trait = ",Q39," }}}") -> effect leader = { add_trait = { trait = leader_trait_rocketry_specialization }}} | K39: 老练 | O39: Ⅰ | P39: 军用舰队效果：爆炸武器射速+15%，爆炸武器伤害+15% | Q39: leader_trait_rocketry_specialization | R39: 00_admiral_traits.txt
A40: 33 | C40: × | E40: √ | G40: 舰队司令 | H40: 需要科技核导弹 | I40: 与其他舰队专精互斥 | J40: =_xlfn.CONCAT("effect ",_xlfn.XLOOKUP($J$5,$W$9:$W$13,$X$9:$X$13),_xlfn.XLOOKUP($J$5,$W$9:$W$13,$Y$9:$Y$13)," ",_xlfn.XLOOKUP($J$5,$W$9:$W$13,$Z$9:$Z$13),$C$5," = { trait = ",Q40," }}}") -> effect leader = { add_trait = { trait = leader_trait_rocketry_specialization_2 }}} | K40: 老练 | O40: Ⅱ | P40: 军用舰队效果：爆炸武器射速+25%，爆炸武器伤害+25% | Q40: leader_trait_rocketry_specialization_2 | R40: 00_admiral_traits.txt
A41: 34 | B41: 炮艇专精 | C41: × | E41: √ | G41: 舰队司令 | I41: 与其他舰队专精互斥 | J41: =_xlfn.CONCAT("effect ",_xlfn.XLOOKUP($J$5,$W$9:$W$13,$X$9:$X$13),_xlfn.XLOOKUP($J$5,$W$9:$W$13,$Y$9:$Y$13)," ",_xlfn.XLOOKUP($J$5,$W$9:$W$13,$Z$9:$Z$13),$C$5," = { trait = ",Q41," }}}") -> effect leader = { add_trait = { trait = leader_trait_gunship_specialization }}} | K41: 老练 | O41: Ⅰ | P41: 军用舰队效果：小型槽位武器射速+15%，小型槽位武器伤害+15%，中型槽位武器射速+10%，中型槽位武器伤害+10% | Q41: leader_trait_gunship_specialization | R41: 00_admiral_traits.txt
A42: 35 | C42: × | E42: √ | G42: 舰队司令 | I42: 与其他舰队专精互斥 | J42: =_xlfn.CONCAT("effect ",_xlfn.XLOOKUP($J$5,$W$9:$W$13,$X$9:$X$13),_xlfn.XLOOKUP($J$5,$W$9:$W$13,$Y$9:$Y$13)," ",_xlfn.XLOOKUP($J$5,$W$9:$W$13,$Z$9:$Z$13),$C$5," = { trait = ",Q42," }}}") -> effect leader = { add_trait = { trait = leader_trait_gunship_specialization_2 }}} | K42: 老练 | O42: Ⅱ | P42: 军用舰队效果：小型槽位武器射速+25%，小型槽位武器伤害+25%，中型槽位武器射速+15%，中型槽位武器伤害+15% | Q42: leader_trait_gunship_specialization_2 | R42: 00_admiral_traits.txt
A43: 36 | B43: 应急维修 | C43: × | E43: √ | G43: 舰队司令 | I43: 片甲不留 | J43: =_xlfn.CONCAT("effect ",_xlfn.XLOOKUP($J$5,$W$9:$W$13,$X$9:$X$13),_xlfn.XLOOKUP($J$5,$W$9:$W$13,$Y$9:$Y$13)," ",_xlfn.XLOOKUP($J$5,$W$9:$W$13,$Z$9:$Z$13),$C$5," = { trait = ",Q43," }}}") -> effect leader = { add_trait = { trait = leader_trait_juryrigger }}} | K43: 老练 | O43: Ⅰ | P43: 军用舰队效果：产生残骸概率-100%，每摧毁一艘敌舰本舰队中随机舰船恢复10%船体值 | Q43: leader_trait_juryrigger | R43: 00_admiral_traits.txt
A44: 37 | C44: × | E44: √ | G44: 舰队司令 | I44: 片甲不留 | J44: =_xlfn.CONCAT("effect ",_xlfn.XLOOKUP($J$5,$W$9:$W$13,$X$9:$X$13),_xlfn.XLOOKUP($J$5,$W$9:$W$13,$Y$9:$Y$13)," ",_xlfn.XLOOKUP($J$5,$W$9:$W$13,$Z$9:$Z$13),$C$5," = { trait = ",Q44," }}}") -> effect leader = { add_trait = { trait = leader_trait_juryrigger_2 }}} | K44: 老练 | O44: Ⅱ | P44: 军用舰队效果：产生残骸概率-100%，每摧毁一艘敌舰本舰队中随机舰船恢复25%船体值 | Q44: leader_trait_juryrigger_2 | R44: 00_admiral_traits.txt
A45: 38 | B45: 精准轰炸 | C45: × | E45: √ | G45: 陆军司令 | J45: =_xlfn.CONCAT("effect ",_xlfn.XLOOKUP($J$5,$W$9:$W$13,$X$9:$X$13),_xlfn.XLOOKUP($J$5,$W$9:$W$13,$Y$9:$Y$13)," ",_xlfn.XLOOKUP($J$5,$W$9:$W$13,$Z$9:$Z$13),$C$5," = { trait = ",Q45," }}}") -> effect leader = { add_trait = { trait = leader_trait_surgical_bombardment }}} | K45: 老练 | O45: Ⅰ | P45: 军用舰队效果：轨道轰炸对陆军伤害+33%，轨道轰炸对人口伤害-67% | Q45: leader_trait_surgical_bombardment | R45: 00_admiral_traits.txt
A46: 39 | C46: × | E46: √ | G46: 陆军司令 | J46: =_xlfn.CONCAT("effect ",_xlfn.XLOOKUP($J$5,$W$9:$W$13,$X$9:$X$13),_xlfn.XLOOKUP($J$5,$W$9:$W$13,$Y$9:$Y$13)," ",_xlfn.XLOOKUP($J$5,$W$9:$W$13,$Z$9:$Z$13),$C$5," = { trait = ",Q46," }}}") -> effect leader = { add_trait = { trait = leader_trait_surgical_bombardment_2 }}} | K46: 老练 | O46: Ⅱ | P46: 军用舰队效果：轨道轰炸对陆军伤害+75%，轨道轰炸对人口伤害-80% | Q46: leader_trait_surgical_bombardment_2 | R46: 00_admiral_traits.txt
A47: 40 | B47: 侦查专家 | C47: × | E47: √ | F47: √ | G47: 舰队司令；探索者 | J47: =_xlfn.CONCAT("effect ",_xlfn.XLOOKUP($J$5,$W$9:$W$13,$X$9:$X$13),_xlfn.XLOOKUP($J$5,$W$9:$W$13,$Y$9:$Y$13)," ",_xlfn.XLOOKUP($J$5,$W$9:$W$13,$Z$9:$Z$13),$C$5," = { trait = ",Q47," }}}") -> effect leader = { add_trait = { trait = leader_trait_scout }}} | K47: 老练 | O47: Ⅰ | P47: 军用舰队效果：亚光速航行+15%，舰船超空间探测距离+3，任务失踪耗时-15% | Q47: leader_trait_scout | R47: 00_admiral_traits.txt
A48: 41 | C48: × | E48: √ | F48: √ | G48: 舰队司令；探索者 | J48: =_xlfn.CONCAT("effect ",_xlfn.XLOOKUP($J$5,$W$9:$W$13,$X$9:$X$13),_xlfn.XLOOKUP($J$5,$W$9:$W$13,$Y$9:$Y$13)," ",_xlfn.XLOOKUP($J$5,$W$9:$W$13,$Z$9:$Z$13),$C$5," = { trait = ",Q48," }}}") -> effect leader = { add_trait = { trait = leader_trait_scout_2 }}} | K48: 老练 | O48: Ⅱ | P48: 军用舰队效果：亚光速航行+25%，舰船超空间探测距离+4，任务失踪耗时-25% | Q48: leader_trait_scout_2 | R48: 00_admiral_traits.txt
A49: 42 | B49: 其疾如风 | C49: × | E49: √ | G49: 战略家 | I49: 懒散怠惰 | J49: =_xlfn.CONCAT("effect ",_xlfn.XLOOKUP($J$5,$W$9:$W$13,$X$9:$X$13),_xlfn.XLOOKUP($J$5,$W$9:$W$13,$Y$9:$Y$13)," ",_xlfn.XLOOKUP($J$5,$W$9:$W$13,$Z$9:$Z$13),$C$5," = { trait = ",Q49," }}}") -> effect leader = { add_trait = { trait = leader_trait_gale_speed }}} | K49: 老练 | L49: √ | O49: Ⅰ | P49: 作为内阁官员的帝国效应：亚光速航速+10% | Q49: leader_trait_gale_speed | R49: 00_admiral_traits.txt
A50: 43 | C50: × | E50: √ | G50: 战略家 | I50: 懒散怠惰 | J50: =_xlfn.CONCAT("effect ",_xlfn.XLOOKUP($J$5,$W$9:$W$13,$X$9:$X$13),_xlfn.XLOOKUP($J$5,$W$9:$W$13,$Y$9:$Y$13)," ",_xlfn.XLOOKUP($J$5,$W$9:$W$13,$Z$9:$Z$13),$C$5," = { trait = ",Q50," }}}") -> effect leader = { add_trait = { trait = leader_trait_gale_speed_2 }}} | K50: 老练 | L50: √ | O50: Ⅱ | P50: 作为内阁官员的帝国效应：亚光速航速+15% | Q50: leader_trait_gale_speed_2 | R50: 00_admiral_traits.txt
A51: 44 | B51: 筑防者 | C51: × | E51: √ | G51: 战略家 | J51: =_xlfn.CONCAT("effect ",_xlfn.XLOOKUP($J$5,$W$9:$W$13,$X$9:$X$13),_xlfn.XLOOKUP($J$5,$W$9:$W$13,$Y$9:$Y$13)," ",_xlfn.XLOOKUP($J$5,$W$9:$W$13,$Z$9:$Z$13),$C$5," = { trait = ",Q51," }}}") -> effect leader = { add_trait = { trait = trait_ruler_fortifier }}} | K51: 老练 | L51: √ | O51: Ⅰ | P51: 作为内阁官员的帝国效应：恒星基地升级费用-7.5%，防御平台建造花费-7.5%，恒星基地和防御平台船体值+5% | Q51: trait_ruler_fortifier | R51: 00_admiral_traits.txt
A52: 45 | C52: × | E52: √ | G52: 战略家 | J52: =_xlfn.CONCAT("effect ",_xlfn.XLOOKUP($J$5,$W$9:$W$13,$X$9:$X$13),_xlfn.XLOOKUP($J$5,$W$9:$W$13,$Y$9:$Y$13)," ",_xlfn.XLOOKUP($J$5,$W$9:$W$13,$Z$9:$Z$13),$C$5," = { trait = ",Q52," }}}") -> effect leader = { add_trait = { trait = trait_ruler_fortifier_2 }}} | K52: 老练 | L52: √ | O52: Ⅱ | P52: 作为内阁官员的帝国效应：恒星基地升级费用-10%，防御平台建造花费-10%，恒星基地和防御平台船体值+10% | Q52: trait_ruler_fortifier_2 | R52: 00_admiral_traits.txt
A53: 46 | B53: 舰队后勤专家 | C53: × | E53: √ | G53: 战略家 | J53: =_xlfn.CONCAT("effect ",_xlfn.XLOOKUP($J$5,$W$9:$W$13,$X$9:$X$13),_xlfn.XLOOKUP($J$5,$W$9:$W$13,$Y$9:$Y$13)," ",_xlfn.XLOOKUP($J$5,$W$9:$W$13,$Z$9:$Z$13),$C$5," = { trait = ",Q53," }}}") -> effect leader = { add_trait = { trait = leader_trait_armada_logistician }}} | K53: 老练 | L53: √ | O53: Ⅰ | P53: 作为内阁官员的帝国效应：舰船维护费-7.5%，海军容量+2.5% | Q53: leader_trait_armada_logistician | R53: 00_admiral_traits.txt
A54: 47 | C54: × | E54: √ | G54: 战略家 | J54: =_xlfn.CONCAT("effect ",_xlfn.XLOOKUP($J$5,$W$9:$W$13,$X$9:$X$13),_xlfn.XLOOKUP($J$5,$W$9:$W$13,$Y$9:$Y$13)," ",_xlfn.XLOOKUP($J$5,$W$9:$W$13,$Z$9:$Z$13),$C$5," = { trait = ",Q54," }}}") -> effect leader = { add_trait = { trait = leader_trait_armada_logistician_2 }}} | K54: 老练 | L54: √ | O54: Ⅱ | P54: 作为内阁官员的帝国效应：舰船维护费-10%，海军容量+7.5% | Q54: leader_trait_armada_logistician_2 | R54: 00_admiral_traits.txt
A55: 48 | B55: 军事先驱 （模块化舰船设计） | C55: × | E55: √ | G55: 战略家 | J55: =_xlfn.CONCAT("effect ",_xlfn.XLOOKUP($J$5,$W$9:$W$13,$X$9:$X$13),_xlfn.XLOOKUP($J$5,$W$9:$W$13,$Y$9:$Y$13)," ",_xlfn.XLOOKUP($J$5,$W$9:$W$13,$Z$9:$Z$13),$C$5," = { trait = ",Q55," }}}") -> effect leader = { add_trait = { trait = trait_ruler_military_pioneer }}} | K55: 老练 | L55: √ | O55: Ⅰ | P55: 作为内阁官员的帝国效应：舰船建造速度+10%，恒星基地升级费用-7.5% | Q55: trait_ruler_military_pioneer | R55: 00_admiral_traits.txt
A56: 49 | C56: × | E56: √ | G56: 战略家 | J56: =_xlfn.CONCAT("effect ",_xlfn.XLOOKUP($J$5,$W$9:$W$13,$X$9:$X$13),_xlfn.XLOOKUP($J$5,$W$9:$W$13,$Y$9:$Y$13)," ",_xlfn.XLOOKUP($J$5,$W$9:$W$13,$Z$9:$Z$13),$C$5," = { trait = ",Q56," }}}") -> effect leader = { add_trait = { trait = trait_ruler_military_pioneer_2 }}} | K56: 老练 | L56: √ | O56: Ⅱ | P56: 作为内阁官员的帝国效应：舰船建造速度+20%，恒星基地升级费用-10% | Q56: trait_ruler_military_pioneer_2 | R56: 00_admiral_traits.txt
A57: 50 | B57: 武力恫吓 （好战表现；威胁指示器） | C57: × | E57: √ | G57: 战略家 | J57: =_xlfn.CONCAT("effect ",_xlfn.XLOOKUP($J$5,$W$9:$W$13,$X$9:$X$13),_xlfn.XLOOKUP($J$5,$W$9:$W$13,$Y$9:$Y$13)," ",_xlfn.XLOOKUP($J$5,$W$9:$W$13,$Z$9:$Z$13),$C$5," = { trait = ",Q57," }}}") -> effect leader = { add_trait = { trait = leader_trait_intimidator }}} | K57: 老练 | L57: √ | O57: Ⅰ | P57: 作为内阁官员的帝国效应：力量投射产出的最大影响力+0.50 | Q57: leader_trait_intimidator | R57: 00_admiral_traits.txt
A58: 51 | C58: × | E58: √ | G58: 战略家 | J58: =_xlfn.CONCAT("effect ",_xlfn.XLOOKUP($J$5,$W$9:$W$13,$X$9:$X$13),_xlfn.XLOOKUP($J$5,$W$9:$W$13,$Y$9:$Y$13)," ",_xlfn.XLOOKUP($J$5,$W$9:$W$13,$Z$9:$Z$13),$C$5," = { trait = ",Q58," }}}") -> effect leader = { add_trait = { trait = leader_trait_intimidator_2 }}} | K58: 老练 | L58: √ | O58: Ⅱ | P58: 作为内阁官员的帝国效应：力量投射产出的最大影响力+0.75 | Q58: leader_trait_intimidator_2 | R58: 00_admiral_traits.txt
A59: 52 | B59: 边防卫士 （庇护；防御计算） | C59: × | E59: √ | G59: 战略家 | J59: =_xlfn.CONCAT("effect ",_xlfn.XLOOKUP($J$5,$W$9:$W$13,$X$9:$X$13),_xlfn.XLOOKUP($J$5,$W$9:$W$13,$Y$9:$Y$13)," ",_xlfn.XLOOKUP($J$5,$W$9:$W$13,$Z$9:$Z$13),$C$5," = { trait = ",Q59," }}}") -> effect leader = { add_trait = { trait = leader_trait_border_guard }}} | K59: 老练 | L59: √ | O59: Ⅰ | P59: 作为内阁官员的帝国效应：防御平台建造速度+15%，恒星基地伤害+20%，恒星基地船体值+25% | Q59: leader_trait_border_guard | R59: 00_admiral_traits.txt
A60: 53 | C60: × | E60: √ | G60: 战略家 | J60: =_xlfn.CONCAT("effect ",_xlfn.XLOOKUP($J$5,$W$9:$W$13,$X$9:$X$13),_xlfn.XLOOKUP($J$5,$W$9:$W$13,$Y$9:$Y$13)," ",_xlfn.XLOOKUP($J$5,$W$9:$W$13,$Z$9:$Z$13),$C$5," = { trait = ",Q60," }}}") -> effect leader = { add_trait = { trait = leader_trait_border_guard_2 }}} | K60: 老练 | L60: √ | O60: Ⅱ | P60: 作为内阁官员的帝国效应：防御平台建造速度+30%，恒星基地伤害+30%，恒星基地船体值+35% | Q60: leader_trait_border_guard_2 | R60: 00_admiral_traits.txt
A61: 54 | B61: 海军教官 （战斗大脑；交战数据库） | C61: × | E61: √ | G61: 战略家 | J61: =_xlfn.CONCAT("effect ",_xlfn.XLOOKUP($J$5,$W$9:$W$13,$X$9:$X$13),_xlfn.XLOOKUP($J$5,$W$9:$W$13,$Y$9:$Y$13)," ",_xlfn.XLOOKUP($J$5,$W$9:$W$13,$Z$9:$Z$13),$C$5," = { trait = ",Q61," }}}") -> effect leader = { add_trait = { trait = leader_trait_crew_trainer }}} | K61: 老练 | L61: √ | O61: Ⅰ | P61: 作为内阁官员的帝国效应：海军容量+30，舰船初始经验+120 | Q61: leader_trait_crew_trainer | R61: 00_admiral_traits.txt
A62: 55 | C62: × | E62: √ | G62: 战略家 | J62: =_xlfn.CONCAT("effect ",_xlfn.XLOOKUP($J$5,$W$9:$W$13,$X$9:$X$13),_xlfn.XLOOKUP($J$5,$W$9:$W$13,$Y$9:$Y$13)," ",_xlfn.XLOOKUP($J$5,$W$9:$W$13,$Z$9:$Z$13),$C$5," = { trait = ",Q62," }}}") -> effect leader = { add_trait = { trait = leader_trait_crew_trainer_2 }}} | K62: 老练 | L62: √ | O62: Ⅱ | P62: 作为内阁官员的帝国效应：海军容量+60，舰船初始经验+200 | Q62: leader_trait_crew_trainer_2 | R62: 00_admiral_traits.txt
A63: 56 | B63: 枪炮大师 | C63: × | E63: √ | G63: 舰队司令 | J63: =_xlfn.CONCAT("effect ",_xlfn.XLOOKUP($J$5,$W$9:$W$13,$X$9:$X$13),_xlfn.XLOOKUP($J$5,$W$9:$W$13,$Y$9:$Y$13)," ",_xlfn.XLOOKUP($J$5,$W$9:$W$13,$Z$9:$Z$13),$C$5," = { trait = ",Q63," }}}") -> effect leader = { add_trait = { trait = leader_trait_master_gunner }}} | K63: 命定 | O63: Ⅰ | P63: 军用舰队效果：舰船武器射程+30%，追踪+30%，命中+30% | Q63: leader_trait_master_gunner | R63: 00_admiral_traits.txt
A64: 57 | B64: 军事监督者 | C64: × | E64: √ | G64: 战略家 | J64: =_xlfn.CONCAT("effect ",_xlfn.XLOOKUP($J$5,$W$9:$W$13,$X$9:$X$13),_xlfn.XLOOKUP($J$5,$W$9:$W$13,$Y$9:$Y$13)," ",_xlfn.XLOOKUP($J$5,$W$9:$W$13,$Z$9:$Z$13),$C$5," = { trait = ",Q64," }}}") -> effect leader = { add_trait = { trait = leader_trait_military_overseer }}} | K64: 命定 | L64: √ | O64: Ⅰ | P64: 作为内阁官员的帝国效应：力量投射产出的最大影响力+2，军用舰船建造速度+25%，舰船初始经验+500 | Q64: leader_trait_military_overseer | R64: 00_admiral_traits.txt
A65: 58 | B65: 天才军械师 | C65: × | E65: √ | G65: 战略家 | J65: =_xlfn.CONCAT("effect ",_xlfn.XLOOKUP($J$5,$W$9:$W$13,$X$9:$X$13),_xlfn.XLOOKUP($J$5,$W$9:$W$13,$Y$9:$Y$13)," ",_xlfn.XLOOKUP($J$5,$W$9:$W$13,$Z$9:$Z$13),$C$5," = { trait = ",Q65," }}}") -> effect leader = { add_trait = { trait = leader_trait_armorer }}} | K65: 命定 | L65: √ | O65: Ⅰ | P65: 作为内阁官员的帝国效应：护盾承受值+100，装甲值+100，装甲硬化+20%，护盾硬化+20%； | Q65: leader_trait_armorer | R65: 00_admiral_traits.txt
A66: 59 | B66: 维护指挥官 | C66: × | E66: √ | G66: 舰队司令 | J66: =_xlfn.CONCAT("effect ",_xlfn.XLOOKUP($J$5,$W$9:$W$13,$X$9:$X$13),_xlfn.XLOOKUP($J$5,$W$9:$W$13,$Y$9:$Y$13)," ",_xlfn.XLOOKUP($J$5,$W$9:$W$13,$Z$9:$Z$13),$C$5," = { trait = ",Q66," }}}") -> effect leader = { add_trait = { trait = leader_trait_destiny_engineer }}} | K66: 命定 | O66: Ⅰ | P66: 军用舰队效果：船体值+25%，每日船体再生+2% | Q66: leader_trait_destiny_engineer | R66: 00_admiral_traits.txt
A67: 60 | B67: 游击大师 | C67: × | E67: √ | G67: 舰队司令 | J67: =_xlfn.CONCAT("effect ",_xlfn.XLOOKUP($J$5,$W$9:$W$13,$X$9:$X$13),_xlfn.XLOOKUP($J$5,$W$9:$W$13,$Y$9:$Y$13)," ",_xlfn.XLOOKUP($J$5,$W$9:$W$13,$Z$9:$Z$13),$C$5," = { trait = ",Q67," }}}") -> effect leader = { add_trait = { trait = leader_trait_guerilla_tactics }}} | K67: 命定 | O67: Ⅰ | P67: 军用舰队效果：撤离机会+2，闪避率+10，任务中失踪耗时-50%，舰队指挥上限-25%，隐形强度+2 | Q67: leader_trait_guerilla_tactics | R67: 00_admiral_traits.txt
A68: 61 | B68: 帝国之盾 | C68: × | E68: √ | G68: 舰队司令 | J68: =_xlfn.CONCAT("effect ",_xlfn.XLOOKUP($J$5,$W$9:$W$13,$X$9:$X$13),_xlfn.XLOOKUP($J$5,$W$9:$W$13,$Y$9:$Y$13)," ",_xlfn.XLOOKUP($J$5,$W$9:$W$13,$Z$9:$Z$13),$C$5," = { trait = ",Q68," }}}") -> effect leader = { add_trait = { trait = leader_trait_survivalist }}} | K68: 命定 | O68: Ⅰ | P68: 军用舰队效果：位于友方恒星系闪避+45%，位于友方恒星系舰船武器射速+45%，位于友方恒星系护盾承受值+300 | Q68: leader_trait_survivalist | R68: 00_admiral_traits.txt
A69: 62 | B69: 战争构筑师 | C69: × | E69: √ | G69: 战略家 | J69: =_xlfn.CONCAT("effect ",_xlfn.XLOOKUP($J$5,$W$9:$W$13,$X$9:$X$13),_xlfn.XLOOKUP($J$5,$W$9:$W$13,$Y$9:$Y$13)," ",_xlfn.XLOOKUP($J$5,$W$9:$W$13,$Z$9:$Z$13),$C$5," = { trait = ",Q69," }}}") -> effect leader = { add_trait = { trait = leader_trait_maven_of_war }}} | K69: 命定 | L69: √ | O69: Ⅰ | P69: 作为内阁官员的帝国效应：亚光速航速+15%，军用舰船建造速度+30%，合金船效果：研究速度 (宇航技术)+5%，宇航技术研究选项的概率+25%；生物舰船组国家效果：研究速度 (生物学)+5%，生物学研究选项的概率+25% | Q69: leader_trait_maven_of_war | R69: 00_admiral_traits.txt
A70: 63 | B70: 和平守护者 | C70: × | D70: √ | E70: √ | G70: 国务顾问；战略家 | J70: =_xlfn.CONCAT("effect ",_xlfn.XLOOKUP($J$5,$W$9:$W$13,$X$9:$X$13),_xlfn.XLOOKUP($J$5,$W$9:$W$13,$Y$9:$Y$13)," ",_xlfn.XLOOKUP($J$5,$W$9:$W$13,$Z$9:$Z$13),$C$5," = { trait = ",Q70," }}}") -> effect leader = { add_trait = { trait = leader_trait_peacekeeper }}} | K70: 命定 | L70: √ | O70: Ⅰ | P70: 作为内阁官员的帝国效应：稳定度+5，犯罪度-20，和平主义思潮吸引力+40% | Q70: leader_trait_peacekeeper | R70: 00_admiral_traits.txt
A71: 64 | B71: 神经质 | C71: × | E71: √ | I71: 坚强不屈 | J71: =_xlfn.CONCAT("effect ",_xlfn.XLOOKUP($J$5,$W$9:$W$13,$X$9:$X$13),_xlfn.XLOOKUP($J$5,$W$9:$W$13,$Y$9:$Y$13)," ",_xlfn.XLOOKUP($J$5,$W$9:$W$13,$Z$9:$Z$13),$C$5," = { trait = ",Q71," }}}") -> effect leader = { add_trait = { trait = leader_trait_nervous }}} | K71: 负面 | O71: Ⅰ | P71: 军用舰队效果：舰船武器射速-5%，战斗撤离几率+5% | Q71: leader_trait_nervous | R71: 00_admiral_traits.txt
A72: 65 | C72: × | E72: √ | I72: 坚强不屈 | J72: =_xlfn.CONCAT("effect ",_xlfn.XLOOKUP($J$5,$W$9:$W$13,$X$9:$X$13),_xlfn.XLOOKUP($J$5,$W$9:$W$13,$Y$9:$Y$13)," ",_xlfn.XLOOKUP($J$5,$W$9:$W$13,$Z$9:$Z$13),$C$5," = { trait = ",Q72," }}}") -> effect leader = { add_trait = { trait = leader_trait_nervous_2 }}} | K72: 负面 | O72: Ⅱ | P72: 军用舰队效果：舰船武器射速-15%，战斗撤离几率+15% | Q72: leader_trait_nervous_2 | R72: 00_admiral_traits.txt
A73: 66 | B73: 懒散怠惰 | C73: × | E73: √ | I73: 其疾如风 | J73: =_xlfn.CONCAT("effect ",_xlfn.XLOOKUP($J$5,$W$9:$W$13,$X$9:$X$13),_xlfn.XLOOKUP($J$5,$W$9:$W$13,$Y$9:$Y$13)," ",_xlfn.XLOOKUP($J$5,$W$9:$W$13,$Z$9:$Z$13),$C$5," = { trait = ",Q73," }}}") -> effect leader = { add_trait = { trait = leader_trait_lethargic }}} | K73: 负面 | O73: Ⅰ | P73: 军用舰队效果：闪避-5%，亚光速航行-5%，舰船维护费-2.5% | Q73: leader_trait_lethargic | R73: 00_admiral_traits.txt
A74: 67 | C74: × | E74: √ | I74: 其疾如风 | J74: =_xlfn.CONCAT("effect ",_xlfn.XLOOKUP($J$5,$W$9:$W$13,$X$9:$X$13),_xlfn.XLOOKUP($J$5,$W$9:$W$13,$Y$9:$Y$13)," ",_xlfn.XLOOKUP($J$5,$W$9:$W$13,$Z$9:$Z$13),$C$5," = { trait = ",Q74," }}}") -> effect leader = { add_trait = { trait = leader_trait_lethargic_2 }}} | K74: 负面 | O74: Ⅱ | P74: 军用舰队效果：闪避-15%，亚光速航行-15%，舰船维护费-5% | Q74: leader_trait_lethargic_2 | R74: 00_admiral_traits.txt
A75: 68 | B75: 微操大师 （不善协调；低效协调模块） | C75: × | E75: √ | J75: =_xlfn.CONCAT("effect ",_xlfn.XLOOKUP($J$5,$W$9:$W$13,$X$9:$X$13),_xlfn.XLOOKUP($J$5,$W$9:$W$13,$Y$9:$Y$13)," ",_xlfn.XLOOKUP($J$5,$W$9:$W$13,$Z$9:$Z$13),$C$5," = { trait = ",Q75," }}}") -> effect leader = { add_trait = { trait = leader_trait_micromanager }}} | K75: 负面 | O75: Ⅰ | P75: 军用舰队效果：舰船维护费+10% | Q75: leader_trait_micromanager | R75: 00_admiral_traits.txt
A76: 69 | C76: × | E76: √ | J76: =_xlfn.CONCAT("effect ",_xlfn.XLOOKUP($J$5,$W$9:$W$13,$X$9:$X$13),_xlfn.XLOOKUP($J$5,$W$9:$W$13,$Y$9:$Y$13)," ",_xlfn.XLOOKUP($J$5,$W$9:$W$13,$Z$9:$Z$13),$C$5," = { trait = ",Q76," }}}") -> effect leader = { add_trait = { trait = leader_trait_micromanager_2 }}} | K76: 负面 | O76: Ⅱ | P76: 军用舰队效果：舰船维护费+30% | Q76: leader_trait_micromanager_2 | R76: 00_admiral_traits.txt
A77: 70 | B77: 不计后果 （错误计算；风险估算失灵） | C77: × | E77: √ | I77: 诡术师 | J77: =_xlfn.CONCAT("effect ",_xlfn.XLOOKUP($J$5,$W$9:$W$13,$X$9:$X$13),_xlfn.XLOOKUP($J$5,$W$9:$W$13,$Y$9:$Y$13)," ",_xlfn.XLOOKUP($J$5,$W$9:$W$13,$Z$9:$Z$13),$C$5," = { trait = ",Q77," }}}") -> effect leader = { add_trait = { trait = leader_trait_reckless }}} | K77: 负面 | O77: Ⅰ | P77: 军用舰队效果：战斗撤离几率-20% | Q77: leader_trait_reckless | R77: 00_admiral_traits.txt
A78: 71 | C78: × | E78: √ | I78: 诡术师 | J78: =_xlfn.CONCAT("effect ",_xlfn.XLOOKUP($J$5,$W$9:$W$13,$X$9:$X$13),_xlfn.XLOOKUP($J$5,$W$9:$W$13,$Y$9:$Y$13)," ",_xlfn.XLOOKUP($J$5,$W$9:$W$13,$Z$9:$Z$13),$C$5," = { trait = ",Q78," }}}") -> effect leader = { add_trait = { trait = leader_trait_reckless_2 }}} | K78: 负面 | O78: Ⅱ | P78: 军用舰队效果：战斗撤离几率-60% | Q78: leader_trait_reckless_2 | R78: 00_admiral_traits.txt
A79: 72 | B79: 吊儿郎当 （低效防御） | C79: × | E79: √ | I79: 坚强不屈 | J79: =_xlfn.CONCAT("effect ",_xlfn.XLOOKUP($J$5,$W$9:$W$13,$X$9:$X$13),_xlfn.XLOOKUP($J$5,$W$9:$W$13,$Y$9:$Y$13)," ",_xlfn.XLOOKUP($J$5,$W$9:$W$13,$Z$9:$Z$13),$C$5," = { trait = ",Q79," }}}") -> effect leader = { add_trait = { trait = leader_trait_slipshod }}} | K79: 负面 | O79: Ⅰ | P79: 军用舰队效果：装甲值-10%，护盾承受值-10% | Q79: leader_trait_slipshod | R79: 00_admiral_traits.txt
A80: 73 | C80: × | E80: √ | I80: 坚强不屈 | J80: =_xlfn.CONCAT("effect ",_xlfn.XLOOKUP($J$5,$W$9:$W$13,$X$9:$X$13),_xlfn.XLOOKUP($J$5,$W$9:$W$13,$Y$9:$Y$13)," ",_xlfn.XLOOKUP($J$5,$W$9:$W$13,$Z$9:$Z$13),$C$5," = { trait = ",Q80," }}}") -> effect leader = { add_trait = { trait = leader_trait_slipshod_2 }}} | K80: 负面 | O80: Ⅱ | P80: 军用舰队效果：装甲值-20%，护盾承受值-20% | Q80: leader_trait_slipshod_2 | R80: 00_admiral_traits.txt
A81: 74 | B81: 屠龙者 | C81: × | E81: √ | H81: 击杀以太巨龙或天龙 | J81: =_xlfn.CONCAT("effect ",_xlfn.XLOOKUP($J$5,$W$9:$W$13,$X$9:$X$13),_xlfn.XLOOKUP($J$5,$W$9:$W$13,$Y$9:$Y$13)," ",_xlfn.XLOOKUP($J$5,$W$9:$W$13,$Z$9:$Z$13),$C$5," = { trait = ",Q81," }}}") -> effect leader = { add_trait = { trait = leader_trait_dragonslayer }}} | K81: 普通 | N81: √ | O81: Ⅰ | P81: 军用舰队效果：亚光速航速+10%，舰船武器射速+10%；陆军效果：陆军伤害+10%，陆军撤退几率+10% | Q81: leader_trait_dragonslayer | R81: 00_admiral_traits.txt
A82: 75 | B82: 克隆大军指挥官 | C82: × | E82: √ | H82: 起源克隆大军 | J82: =_xlfn.CONCAT("effect ",_xlfn.XLOOKUP($J$5,$W$9:$W$13,$X$9:$X$13),_xlfn.XLOOKUP($J$5,$W$9:$W$13,$Y$9:$Y$13)," ",_xlfn.XLOOKUP($J$5,$W$9:$W$13,$Z$9:$Z$13),$C$5," = { trait = ",Q82," }}}") -> effect leader = { add_trait = { trait = leader_trait_clone_army_commander }}} | K82: 普通 | N82: √ | O82: Ⅰ | P82: 军用舰队效果：舰船武器射速+25%，舰船武器射程+10% | Q82: leader_trait_clone_army_commander | R82: 00_admiral_traits.txt
A83: 76 | B83: 末裔克隆大军指挥官 | C83: × | E83: √ | H83: 起源克隆大军 | J83: =_xlfn.CONCAT("effect ",_xlfn.XLOOKUP($J$5,$W$9:$W$13,$X$9:$X$13),_xlfn.XLOOKUP($J$5,$W$9:$W$13,$Y$9:$Y$13)," ",_xlfn.XLOOKUP($J$5,$W$9:$W$13,$Z$9:$Z$13),$C$5," = { trait = ",Q83," }}}") -> effect leader = { add_trait = { trait = leader_trait_clone_army_fertile_commander }}} | K83: 普通 | N83: √ | O83: Ⅰ | P83: 军用舰队效果：舰船武器射速+15%，舰船武器射程+5% | Q83: leader_trait_clone_army_fertile_commander | R83: 00_admiral_traits.txt
A84: 77 | B84: 先裔克隆大军指挥官 | C84: × | E84: √ | H84: 起源克隆大军 | J84: =_xlfn.CONCAT("effect ",_xlfn.XLOOKUP($J$5,$W$9:$W$13,$X$9:$X$13),_xlfn.XLOOKUP($J$5,$W$9:$W$13,$Y$9:$Y$13)," ",_xlfn.XLOOKUP($J$5,$W$9:$W$13,$Z$9:$Z$13),$C$5," = { trait = ",Q84," }}}") -> effect leader = { add_trait = { trait = leader_trait_clone_army_full_commander }}} | K84: 普通 | N84: √ | O84: Ⅰ | P84: 军用舰队效果：舰船武器射速+35%，舰船武器射程+20% | Q84: leader_trait_clone_army_full_commander | R84: 00_admiral_traits.txt
A85: 78 | B85: 战术算法 | C85: × | E85: √ | H85: 国策战术算法 | J85: =_xlfn.CONCAT("effect ",_xlfn.XLOOKUP($J$5,$W$9:$W$13,$X$9:$X$13),_xlfn.XLOOKUP($J$5,$W$9:$W$13,$Y$9:$Y$13)," ",_xlfn.XLOOKUP($J$5,$W$9:$W$13,$Z$9:$Z$13),$C$5," = { trait = ",Q85," }}}") -> effect leader = { add_trait = { trait = leader_trait_tactical_algorithms }}} | K85: 老练 | N85: √ | P85: 随领袖技能等级提升：军用舰船合金维护费-10%，军用舰船能量币维护费+20% | Q85: leader_trait_tactical_algorithms | R85: 00_admiral_traits.txt
A86: 79 | B86: 虚境行者导师 | C86: × | D86: √ | H86: 城邦特质 | J86: =_xlfn.CONCAT("effect ",_xlfn.XLOOKUP($J$5,$W$9:$W$13,$X$9:$X$13),_xlfn.XLOOKUP($J$5,$W$9:$W$13,$Y$9:$Y$13)," ",_xlfn.XLOOKUP($J$5,$W$9:$W$13,$Z$9:$Z$13),$C$5," = { trait = ",Q86," }}}") -> effect leader = { add_trait = { trait = leader_trait_shroudwalker }}} | K86: 老练 | M86: √ | N86: √ | O86: Ⅰ | P86: 这位领袖预期寿命+30年；行星效果：舒适度+5%，灵能使凝聚力产出+3（评估者凝聚力产出+2）；督管星域首府时星域效果：舒适度+2.5%、灵能使凝聚力产出+1（评估者凝聚力产出+1） | Q86: leader_trait_shroudwalker | R86: 00_enclave_leader_traits.txt
A87: 80 | B87: 打捞大师 | C87: × | F87: √ | H87: 城邦特质 | J87: =_xlfn.CONCAT("effect ",_xlfn.XLOOKUP($J$5,$W$9:$W$13,$X$9:$X$13),_xlfn.XLOOKUP($J$5,$W$9:$W$13,$Y$9:$Y$13)," ",_xlfn.XLOOKUP($J$5,$W$9:$W$13,$Z$9:$Z$13),$C$5," = { trait = ",Q87," }}}") -> effect leader = { add_trait = { trait = leader_trait_master_salvager }}} | K87: 老练 | N87: √ | O87: Ⅰ | P87: 星系中的友方舰船:每月船体值维修+2%，当星系中有残骸被打捞或研究完成时15%的概率打捞舰船；只会打捞其他帝国的军舰 | Q87: leader_trait_master_salvager | R87: 00_enclave_leader_traits.txt
A88: 81 | B88: 策展人 （策展人原理） | C88: × | F88: √ | H88: 城邦特质 | J88: =_xlfn.CONCAT("effect ",_xlfn.XLOOKUP($J$5,$W$9:$W$13,$X$9:$X$13),_xlfn.XLOOKUP($J$5,$W$9:$W$13,$Y$9:$Y$13)," ",_xlfn.XLOOKUP($J$5,$W$9:$W$13,$Z$9:$Z$13),$C$5," = { trait = ",Q88," }}}") -> effect leader = { add_trait = { trait = leader_trait_curator }}} | K88: 老练 | L88: √ | N88: √ | O88: Ⅰ | P88: 作为内阁官员的帝国效应：研究速度+10%，研究人员维护费+10%（生体荒野帝国：行星研究建筑维护费+10%），调查速度+25%，标本产出+5%，提高抽取稀有科技的概率 | Q88: leader_trait_curator | R88: 00_enclave_leader_traits.txt
A89: 82 | B89: 城邦商人 | C89: × | D89: √ | H89: 城邦特质 | J89: =_xlfn.CONCAT("effect ",_xlfn.XLOOKUP($J$5,$W$9:$W$13,$X$9:$X$13),_xlfn.XLOOKUP($J$5,$W$9:$W$13,$Y$9:$Y$13)," ",_xlfn.XLOOKUP($J$5,$W$9:$W$13,$Z$9:$Z$13),$C$5," = { trait = ",Q89," }}}") -> effect leader = { add_trait = { trait = leader_trait_enclave_trader }}} | K89: 老练 | N89: √ | O89: Ⅰ | P89: 行星效果：贸易额+10%；督管星域首府时星域效果：贸易额+5% | Q89: leader_trait_enclave_trader | R89: 00_enclave_leader_traits.txt
A90: 83 | B90: 雪拉企业联络人 | C90: × | D90: √ | H90: 城邦特质 | J90: =_xlfn.CONCAT("effect ",_xlfn.XLOOKUP($J$5,$W$9:$W$13,$X$9:$X$13),_xlfn.XLOOKUP($J$5,$W$9:$W$13,$Y$9:$Y$13)," ",_xlfn.XLOOKUP($J$5,$W$9:$W$13,$Z$9:$Z$13),$C$5," = { trait = ",Q90," }}}") -> effect leader = { add_trait = { trait = leader_trait_xuracorp_liaison }}} | K90: 老练 | M90: √ | N90: √ | O90: Ⅰ | P90: 这位领袖每月异星天然气+2；行星效果：岗位产生的异星天然气+25%、贸易额+10%； 督管星域首府时星域效果：岗位产生的异星天然气+10%、贸易额+5% | Q90: leader_trait_xuracorp_liaison | R90: 00_enclave_leader_traits.txt
A91: 84 | B91: 里甘联络人 | C91: × | D91: √ | H91: 城邦特质 | J91: =_xlfn.CONCAT("effect ",_xlfn.XLOOKUP($J$5,$W$9:$W$13,$X$9:$X$13),_xlfn.XLOOKUP($J$5,$W$9:$W$13,$Y$9:$Y$13)," ",_xlfn.XLOOKUP($J$5,$W$9:$W$13,$Z$9:$Z$13),$C$5," = { trait = ",Q91," }}}") -> effect leader = { add_trait = { trait = leader_trait_riggan_liaison }}} | K91: 老练 | M91: √ | N91: √ | O91: Ⅰ | P91: 这位领袖每月易爆微粒+2；行星效果：岗位产生的易爆微粒+25%、贸易额+10%； 督管星域首府时星域效果：岗位产生的易爆微粒+10%、贸易额+5% | Q91: leader_trait_riggan_liaison | R91: 00_enclave_leader_traits.txt
A92: 85 | B92: 穆塔根联络人 | C92: × | D92: √ | H92: 城邦特质 | J92: =_xlfn.CONCAT("effect ",_xlfn.XLOOKUP($J$5,$W$9:$W$13,$X$9:$X$13),_xlfn.XLOOKUP($J$5,$W$9:$W$13,$Y$9:$Y$13)," ",_xlfn.XLOOKUP($J$5,$W$9:$W$13,$Z$9:$Z$13),$C$5," = { trait = ",Q92," }}}") -> effect leader = { add_trait = { trait = leader_trait_muutagan_liaison }}} | K92: 老练 | M92: √ | N92: √ | O92: Ⅰ | P92: 这位领袖每月稀有水晶+2；行星效果：岗位产生的稀有水晶+25%、贸易额+10%； 督管星域首府时星域效果：岗位产生的稀有水晶+10%、贸易额+5% | Q92: leader_trait_muutagan_liaison | R92: 00_enclave_leader_traits.txt
A93: 86 | B93: 防御工程师 （防御平台工程师） | C93: × | E93: √ | J93: =_xlfn.CONCAT("effect ",_xlfn.XLOOKUP($J$5,$W$9:$W$13,$X$9:$X$13),_xlfn.XLOOKUP($J$5,$W$9:$W$13,$Y$9:$Y$13)," ",_xlfn.XLOOKUP($J$5,$W$9:$W$13,$Z$9:$Z$13),$C$5," = { trait = ",Q93," }}}") -> effect leader = { add_trait = { trait = leader_trait_defence_engineer }}} | K93: 普通 | L93: √ | O93: Ⅰ | P93: 作为内阁官员的帝国效应：防御平台伤害+15%，防御平台船体值+10% | Q93: leader_trait_defence_engineer | R93: 00_general_traits.txt
A94: 87 | B94: 屠夫 （杀戮狂蜂；杀戮机器） | C94: × | E94: √ | I94: 纸上谈兵，警惕 | J94: =_xlfn.CONCAT("effect ",_xlfn.XLOOKUP($J$5,$W$9:$W$13,$X$9:$X$13),_xlfn.XLOOKUP($J$5,$W$9:$W$13,$Y$9:$Y$13)," ",_xlfn.XLOOKUP($J$5,$W$9:$W$13,$Z$9:$Z$13),$C$5," = { trait = ",Q94," }}}") -> effect leader = { add_trait = { trait = leader_trait_butcher }}} | K94: 普通 | O94: Ⅰ | P94: 陆军效果：陆军伤害+15%，陆军连带伤害+50% | Q94: leader_trait_butcher | R94: 00_general_traits.txt
A95: 88 | B95: 警惕 （精准打击） | C95: × | E95: √ | I95: 草菅人命，屠夫 | J95: =_xlfn.CONCAT("effect ",_xlfn.XLOOKUP($J$5,$W$9:$W$13,$X$9:$X$13),_xlfn.XLOOKUP($J$5,$W$9:$W$13,$Y$9:$Y$13)," ",_xlfn.XLOOKUP($J$5,$W$9:$W$13,$Z$9:$Z$13),$C$5," = { trait = ",Q95," }}}") -> effect leader = { add_trait = { trait = leader_trait_restrained }}} | K95: 普通 | O95: Ⅰ | P95: 军用舰队效果：轨道轰炸对人口伤害-15%；陆军效果：撤退几率+15%，连带伤害-35% | Q95: leader_trait_restrained | R95: 00_general_traits.txt
A96: 89 | B96: 令人恐惧 （灌输恐惧） | C96: × | E96: √ | G96: 陆军司令 | J96: =_xlfn.CONCAT("effect ",_xlfn.XLOOKUP($J$5,$W$9:$W$13,$X$9:$X$13),_xlfn.XLOOKUP($J$5,$W$9:$W$13,$Y$9:$Y$13)," ",_xlfn.XLOOKUP($J$5,$W$9:$W$13,$Z$9:$Z$13),$C$5," = { trait = ",Q96," }}}") -> effect leader = { add_trait = { trait = leader_trait_dreaded }}} | K96: 老练 | O96: Ⅰ | P96: 陆军效果：陆军士气伤害+25% | Q96: leader_trait_dreaded | R96: 00_general_traits.txt
A97: 90 | C97: × | E97: √ | G97: 陆军司令 | J97: =_xlfn.CONCAT("effect ",_xlfn.XLOOKUP($J$5,$W$9:$W$13,$X$9:$X$13),_xlfn.XLOOKUP($J$5,$W$9:$W$13,$Y$9:$Y$13)," ",_xlfn.XLOOKUP($J$5,$W$9:$W$13,$Z$9:$Z$13),$C$5," = { trait = ",Q97," }}}") -> effect leader = { add_trait = { trait = leader_trait_dreaded_2 }}} | K97: 老练 | O97: Ⅱ | P97: 陆军效果：陆军士气伤害+50% | Q97: leader_trait_dreaded_2 | R97: 00_general_traits.txt
A98: 91 | B98: 重拳出击 （重击者） | C98: × | E98: √ | G98: 陆军司令 | J98: =_xlfn.CONCAT("effect ",_xlfn.XLOOKUP($J$5,$W$9:$W$13,$X$9:$X$13),_xlfn.XLOOKUP($J$5,$W$9:$W$13,$Y$9:$Y$13)," ",_xlfn.XLOOKUP($J$5,$W$9:$W$13,$Z$9:$Z$13),$C$5," = { trait = ",Q98," }}}") -> effect leader = { add_trait = { trait = leader_trait_heavy_hitter }}} | K98: 老练 | O98: Ⅰ | P98: 陆军效果：陆军伤害+15% | Q98: leader_trait_heavy_hitter | R98: 00_general_traits.txt
A99: 92 | C99: × | E99: √ | G99: 陆军司令 | J99: =_xlfn.CONCAT("effect ",_xlfn.XLOOKUP($J$5,$W$9:$W$13,$X$9:$X$13),_xlfn.XLOOKUP($J$5,$W$9:$W$13,$Y$9:$Y$13)," ",_xlfn.XLOOKUP($J$5,$W$9:$W$13,$Z$9:$Z$13),$C$5," = { trait = ",Q99," }}}") -> effect leader = { add_trait = { trait = leader_trait_heavy_hitter_2 }}} | K99: 老练 | O99: Ⅱ | P99: 陆军效果：陆军伤害+30% | Q99: leader_trait_heavy_hitter_2 | R99: 00_general_traits.txt
A100: 93 | B100: 审讯专家 （审查仪） | C100: × | E100: √ | G100: 陆军司令 | J100: =_xlfn.CONCAT("effect ",_xlfn.XLOOKUP($J$5,$W$9:$W$13,$X$9:$X$13),_xlfn.XLOOKUP($J$5,$W$9:$W$13,$Y$9:$Y$13)," ",_xlfn.XLOOKUP($J$5,$W$9:$W$13,$Z$9:$Z$13),$C$5," = { trait = ",Q100," }}}") -> effect leader = { add_trait = { trait = leader_trait_interrogator }}} | K100: 老练 | O100: Ⅰ | P100: 陆军效果：作为进攻方在地面作战中获胜时对应帝国情报+15 | Q100: leader_trait_interrogator | R100: 00_general_traits.txt
...

Sheet 星球区划
A1: 4.0.22星球区划特化建筑代码（2025.08.22）
A2: 注：本条目收录了恒星类型，行星类型，星球模型，区划，特化，建筑条目，并对每栏目进行了自适应化（条目太多，并且生成需要很多其他条目辅助，因此做成自适应型）。
A4: 改变恒星类型 | I4: 对选中行星进行 地爆天星
A5: 注：选中恒星输入，下拉菜单可选择其他恒星类型，实际上只改变了恒星BUFF与大地图的星系外观，例如黑洞如果输入下方的改变星球类型，仍然为黑洞星系。 | I5: event planet_destruction.100
A6: 改变恒星类型 | B6: B型恒星 | C6: =_xlfn.CONCAT("effect = { solar_system = { set_star_class = ",_xlfn.XLOOKUP(B6,A90:A116,B90:B116)," }}") -> effect = { solar_system = { set_star_class = sc_b }}
I7: 对选中行星进行 安乐天使
A8: 改变星球类型 | I8: event planet_destruction.200
A9: 注：选中星球输入，下拉菜单可选择其他恒星类型。
A10: 改变为宜居星球 | B10: 蜂巢星球 | C10: =_xlfn.CONCAT("planet_class ",_xlfn.XLOOKUP(B10,D90:D112,E90:E112)) -> planet_class pc_hive | I10: 对选中行星执行 中子灭杀
A11: 改变为其他星球 | B11: 气态巨行星 | C11: =_xlfn.CONCAT("planet_class ",_xlfn.XLOOKUP(B11,D113:D141,E113:E141)) -> planet_class pc_gas_giant | I11: event planet_destruction.300
A12: 改变为恒星类型星球 | B12: M型红巨星 | C12: =_xlfn.CONCAT("planet_class ",_xlfn.XLOOKUP(B12,D142:D154,E142:E154)) -> planet_class pc_m_giant_star
I13: 对选中行星执行 神圣激素
A14: 改变星球模型 | I14: event planet_destruction.400
A15: 注：选中星球输入，该条目仅改变星球外观；不同物种类型的环世界，理想城，居住站有差异，可以通过更改图形文化换成对应模型；人工星球类模型建议只输入给人工星球。
A16: 设定栏 | B16: 模型类别 | C16: 人工星球模型 | D16: 图形文化 | E16: 哺乳类 | F16: 模型名称 | G16: 环世界框架（单段） | I16: 对选中行星执行 纳米灾疫
A17: 生成栏 | B17: =_xlfn.CONCAT("effect set_planet_entity = { entity = ",_xlfn.XLOOKUP(G16,A381:A563,B381:B563)," graphical_culture = ",_xlfn.XLOOKUP(E16,扩展代码!B670:B686,扩展代码!C670:C686)," }") -> effect set_planet_entity = { entity = ringworld_construction_entity graphical_culture = mammalian_01 } | I17: event planet_destruction.500
A19: 生成星球 | I19: 对选中行星执行 天洪浩荡
A20: 注：选中恒星输入，设定后即可生成。 | I20: event planet_destruction.700
A21: 设定栏 | B21: 星球类型 | C21: 熔融星球 | D21: 星球名称 | E21: "测试" | F21: 星球大小 | G21: 10
B22: 生成距离 | C22: 100 | D22: 生成角度 | E22: 100 | F22: 偏移角度 | G22: 0 | I22: 对选中行星执行 毒流天降
B23: 是否生成行星环 | C23: yes | D23: 是否清除障碍 | E23: yes | F23: 是否清除行星修正 | G23: yes | I23: event planet_destruction.800
A24: 生成栏 | B24: =_xlfn.CONCAT("effect = { solar_system = { spawn_planet = { class = ",_xlfn.XLOOKUP(C21,D90:D154,E90:E154)," location = this orbit_distance_offset = ",C22," orbit_angle_offset = ",E22," plane_offset = ",G22," has_ring = ",C23," size = ",G21," init_effect = { set_name = ",E21," clear_blockers = ",E23," clear_planet_modifiers = ",G23," }}}}") -> effect = { solar_system = { spawn_planet = { class = pc_molten location = this orbit_distance_offset = 100 orbit_angle_offset = 100 plane_offset = 0 has_ring = yes size = 10 init_effect = { set_name = "测试" clear_blockers = yes clear_planet_modifiers = yes }}}}
I25: 对选中行星执行 降智光束
A26: 添加星球区划 | I26: event planet_destruction.900
A27: 注：选中星球输入，对于设定请查看右侧图片，可以通过筛选来快速找到对应区划，也可直接在“区划名称”中直接输入对应名称，不满足条件的区划过月会被合并。一些次要区划在特化以后会更换名称，但代码上仍然按照无特化时添加，因此筛选中不加入此类别的区划。 | F27: 区划设定规则（对下方生成特化与建筑也适用）
A28: 设定栏 | B28: 区划位置筛选 | C28: 主区划 | D28: 区划星球筛选 | E28: 忽略筛选 | F28: =_xlfn.DISPIMG("ID_D1C7E8AF35CA488A998247BFFC839F0B",1) -> =DISPIMG("ID_D1C7E8AF35CA488A998247BFFC839F0B",1) | I28: 对选中恒星执行 焚天神兵
B29: 区划名称 | C29: 智链都会 | D29: 生成数量 | E29: 10 | I29: effect solar_system = { destroy_star_system = yes }
A30: 生成栏 | B30: =_xlfn.CONCAT("planet = { while = { count = ",E29," add_district = {district_type = ",_xlfn.XLOOKUP(C29,G90:G136,H90:H136)," }}") -> planet = { while = { count = 10 add_district = {district_type = district_mindlink }}
I31: 直接 移除 选中 星球
A32: 添加区划特化 | I32: effect remove_planet = yes
A33: 注：选中星球输入，对于设定请查看上方图片，可以通过筛选来快速找到对应特化，也可直接在“特化名称”中直接输入对应名称，不满足条件的特化过月不会消失，如果忽略主次区划添加会导致UI显示异常，例如将理想城次区划的特化加入主区划后会显示异常，但不影响正常游戏，区划筛选是为了将特化生成进指定区划，槽位选择请看图片显示位置。
A34: 设定栏 | B34: 特化位置定位筛选 | C34: 忽略筛选 | D34: 区划星球筛选 | E34: 忽略筛选 | F34: 特化星球类别筛选 | G34: 环形世界 | I34: 移除 除了恒星外 的 所有星球 （范围：当前恒星系统）
B35: 添加到该槽位 | C35: 0 | D35: 添加到该区划 | E35: 未特化理想城3 | F35: 特化名称 | G35: 能源发电（环形世界） | I35: effect = { solar_system = { every_system_planet = { limit = { is_star = no } remove_planet = yes }}}
A36: 生成栏 | B36: =_xlfn.CONCAT("Effect planet = { add_zone = { district = ",_xlfn.XLOOKUP(E35,G90:G136,H90:H136)," zone = ",_xlfn.XLOOKUP(G35,A162:A275,B162:B275)," zone_slot = ",C35," replace = yes }}") -> Effect planet = { add_zone = { district = district_arcology_urban_3 zone = zone_energy_ring_world zone_slot = 0 replace = yes }}
I37: 直接 移除 选中 星球中的所有建筑与人口
A38: 添加建筑 | I38: effect destroy_colony = yes
A39: 注：选中星球输入，对于设定请查看上方图片，可以通过筛选来快速找到对应建筑，也可直接在“建筑名称”中直接输入对应名称，不满足条件的建筑过月会消失，筛选区划和特化是为了精确定位生成位置，但无法更精确定位到哪个建筑槽，只能通过连续添加三个建筑来调整摆放顺序（使用前需删除已存在的建筑）。
A40: 设定栏 | B40: 建筑填入区划位置筛选 | C40: 主区划 | D40: 建筑填入区划星球筛选 | E40: 基础区划 | F40: 建筑填入区划名称 | G40: 城市区划 | I40: 增加或减少 选中星球破坏度（输入负值则减）
B41: 建筑填入特化位置筛选 | C41: 主区划 | D41: 建筑填入特化星球筛选 | E41: 常规星球 | F41: 建筑填入特化名称 | G41: 政府特区 | I41: effect add_planet_devastation = 100
B42: 建筑来源筛选 | C42: 基础建筑 | D42: 建筑类别筛选 | E42: 军事建筑 | F42: 建筑名称（单） | G42: 军事学院
B43: 建筑名称1 | C43: 军事学院 | D43: 建筑名称2 | E43: 军事学院 | F43: 建筑名称3 | G43: 军事学院 | I43: 打开或关闭 选中星球的土星环模型
A44: 添加单个建筑 | B44: =_xlfn.CONCAT("Effect planet = { add_building = {district = ",_xlfn.XLOOKUP(G40,G90:G136,H90:H136)," zone = ",_xlfn.XLOOKUP(G41,A162:A275,B162:B275)," building = ",_xlfn.XLOOKUP(G42,G162:G557,H162:H557)," }}") -> Effect planet = { add_building = {district = district_city zone = zone_default building = building_military_academy }} | I44: effect set_ring = yes
A45: 连续添加三个建筑 | B45: =_xlfn.CONCAT("Effect planet = { add_building = {district = ",_xlfn.XLOOKUP(G40,G90:G136,H90:H136)," zone = ",_xlfn.XLOOKUP(G41,A162:A275,B162:B275)," building = ",_xlfn.XLOOKUP(C43,G162:G557,H162:H557)," }","add_building = {district = ",_xlfn.XLOOKUP(G40,G90:G136,H90:H136)," zone = ",_xlfn.XLOOKUP(G41,A162:A275,B162:B275)," building = ",_xlfn.XLOOKUP(E43,G162:G557,H162:H557)," }","add_building = {district = ",_xlfn.XLOOKUP(G40,G90:G136,H90:H136)," zone = ",_xlfn.XLOOKUP(G41,A162:A275,B162:B275)," building = ",_xlfn.XLOOKUP(G43,G162:G557,H162:H557)," }}") -> Effect planet = { add_building = {district = district_city zone = zone_default building = building_military_academy }add_building = {district = district_city zone = zone_default building = building_military_academy }add_building = {district = district_city zone = zone_default building = building_military_academy }}
I46: 设置选中星球的飞升等级
I47: planet_ascension_tier 10
A48: 添加企业与宗主建筑
A49: 注：企业和宗主国如未创建分部/协议，先输入前三行代码，已建立则忽视；之后选中星球输入即可。 | I49: 设置选中星球的规模大小
A50: 设定分部/条款来源国家 | B50: effect = { save_global_event_target_as = playercountry} | I50: planet_size 30
A51: 选中星球创建分部（企业） | B51: effect establish_branch_office = event_target:playercountry
A52: 选中星球创建协议（宗主国） | B52: effect = { root.owner = { set_subject_of = { who = event_target:playercountry allow_instant_negotiation = yes preset = preset_vassal }
A53: 设定栏 | B53: 建筑类别筛选 | C53: 企业分部建筑 | D53: 建筑名称 | E53: 私人矿业财团
A54: 生成栏 | B54: =_xlfn.CONCAT("effect add_building = ",_xlfn.XLOOKUP(E53,A291:A355,B291:B355)) -> effect add_building = building_private_mining_consortium
A89: 恒星类型 | B89: 恒星代码 | D89: 星球类型 | E89: 星球代码 | G89: 区划名称 | H89: 区划代码 | I89: 区划位置1 | J89: 区划位置2 | K89: 区划控制 | L89: 特化控制 | M89: 建筑控制
A90: B型恒星 | B90: sc_b | D90: 沙漠星球 | E90: pc_desert | G90: 突触凝炼机区划 | H90: district_cosmogenesis_goverment | I90: 无区划 | J90: 天灾区划 | K90: {=_xlfn._xlws.FILTER(G90:G136,(IF(C28="忽略筛选",ROW(I90:I136)>=1,I90:I136=C28))*(IF(E28="忽略筛选",ROW(J90:J136)>=1,J90:J136=E28)),"请选择条件")} -> 智链都会 | L90: {=_xlfn._xlws.FILTER(G90:G136,(IF(C34="忽略筛选",ROW(I90:I136)>=1,I90:I136=C34))*(IF(E34="忽略筛选",ROW(J90:J136)>=1,J90:J136=E34)),"请选择条件")} -> 突触凝炼机区划 | M90: {=_xlfn._xlws.FILTER(G90:G136,(IF(C40="忽略筛选",ROW(I90:I136)>=1,I90:I136=C40))*(IF(E40="忽略筛选",ROW(J90:J136)>=1,J90:J136=E40)),"请选择条件")} -> 城市区划
A91: A型恒星 | B91: sc_a | D91: 干旱星球 | E91: pc_arid | G91: 神经之门 | H91: district_cosmogenesis_world_science | I91: 无区划 | J91: 天灾区划 | K91: 城市区划 | L91: 神经之门 | M91: 拾荒站
A92: F型恒星 | B92: sc_f | D92: 草原星球 | E92: pc_savannah | G92: 扩充思维区 | H92: district_cosmogenesis_world_logic | I92: 无区划 | J92: 天灾区划 | K92: 拾荒站 | L92: 扩充思维区
A93: G型恒星 | B93: sc_g | D93: 热带星球 | E93: pc_tropical | G93: 智链都会 | H93: district_mindlink | I93: 主区划 | J93: 天灾区划 | K93: 起居区划 | L93: 智链都会
A94: K型恒星 | B94: sc_k | D94: 陆地星球 | E94: pc_continental | G94: 城市区划 | H94: district_city | I94: 主区划 | J94: 基础区划 | K94: 监狱区划 | L94: 城市区划
A95: M型恒星 | B95: sc_m | D95: 海洋星球 | E95: pc_ocean | G95: 拾荒站 | H95: district_crashed_slaver_ship | I95: 主区划 | J95: 基础区划 | K95: 奴隶居住区划 | L95: 拾荒站
A96: M型红巨星 | B96: sc_m_giant | D96: 苔原星球 | E96: pc_tundra | G96: 起居区划 | H96: district_resort | I96: 主区划 | J96: 特殊星球区划 | K96: 蜂巢集群 | L96: 起居区划
A97: T型褐矮星 | B97: sc_t | D97: 极地星球 | E97: pc_arctic | G97: 景点区划1 | H97: district_resort_1 | I97: 次区划1 | J97: 特殊星球区划 | K97: 中央枢纽 | L97: 景点区划1
A98: 黑洞 | B98: sc_black_hole | D98: 高山星球 | E98: pc_alpine | G98: 景点区划2 | H98: district_resort_2 | I98: 次区划2 | J98: 特殊星球区划 | K98: 居住理想城 | L98: 景点区划2
A99: 中子星 | B99: sc_neutron_star | D99: 死寂星球 | E99: pc_nuked | G99: 景点区划3 | H99: district_resort_3 | I99: 次区划3 | J99: 特殊星球区划 | K99: 居住站区划 | L99: 景点区划3
A100: 脉冲星 | B100: sc_pulsar | D100: 蜂巢星球 | E100: pc_hive | G100: 监狱区划 | H100: district_prison | I100: 主区划 | J100: 特殊星球区划 | K100: 城市区段 | L100: 监狱区划
A101: 双星1（A型恒星+脉冲星） | B101: sc_binary_1 | D101: 机械星球 | E101: pc_machine | G101: 奴隶居住区划 | H101: district_slave | I101: 主区划 | J101: 特殊星球区划 | K101: 蜂巢区段 | L101: 奴隶居住区划
A102: 双星2（B型恒星+中子星） | B102: sc_binary_2 | D102: 盖亚星球 | E102: pc_gaia | G102: 蜂巢集群 | H102: district_hive | I102: 主区划 | J102: 蜂巢星球区划 | K102: 中枢区段 | L102: 蜂巢集群
A103: 双星3（M型红巨星+脉冲星） | B103: sc_binary_3 | D103: 环形区段（赛博勒克斯） | E103: pc_cybrex | G103: 未特化集群1 | H103: district_hive_1 | I103: 次区划1 | J103: 蜂巢星球区划 | K103: 共栖群落 | L103: 未特化集群1
A104: 双星4（M型红巨星+F型恒星） | B104: sc_binary_4 | D104: 纳米星球 | E104: pc_nanotech | G104: 未特化集群2 | H104: district_hive_2 | I104: 次区划2 | J104: 蜂巢星球区划 | L104: 未特化集群2
A105: 双星5（B型恒星+B型恒星） | B105: sc_binary_5 | D105: 环形区段（居住段） | E105: pc_ringworld_habitable | G105: 未特化集群3 | H105: district_hive_3 | I105: 次区划3 | J105: 蜂巢星球区划 | L105: 未特化集群3
A106: 双星6（M型恒星+G型恒星） | B106: sc_binary_6 | D106: 破碎之环区段 | E106: pc_shattered_ring_habitable | G106: 中央枢纽 | H106: district_nexus | I106: 主区划 | J106: 机械与纳米星球区划 | L106: 中央枢纽
A107: 双星7（K型恒星+F型恒星） | B107: sc_binary_7 | D107: 轨道居住站 | E107: pc_habitat | G107: 未特化枢纽1 | H107: district_nexus_1 | I107: 次区划1 | J107: 机械与纳米星球区划 | L107: 未特化枢纽1
A108: 双星8（G型恒星+F型恒星） | B108: sc_binary_8 | D108: 突触凝炼机 | E108: pc_cosmogenesis_world | G108: 未特化枢纽2 | H108: district_nexus_2 | I108: 次区划2 | J108: 机械与纳米星球区划 | L108: 未特化枢纽2
A109: 双星9（A型恒星+F型恒星） | B109: sc_binary_9 | D109: （无名居住站1） | E109: pc_crystal_habitat | G109: 未特化枢纽3 | H109: district_nexus_3 | I109: 次区划3 | J109: 机械与纳米星球区划 | L109: 未特化枢纽3
A110: 双星10（A型恒星+T型褐矮星） | B110: sc_binary_10 | D110: （无名居住站2） | E110: pc_warden_guardian | G110: 居住理想城 | H110: district_arcology_housing | I110: 主区划 | J110: 理想城区划 | L110: 居住理想城
A111: 三合星1（G型恒星+M型恒星+K型恒星） | B111: sc_trinary_1 | D111: 都市星球 | E111: pc_city | G111: 未特化理想城1 | H111: district_arcology_urban_1 | I111: 次区划1 | J111: 理想城区划 | L111: 未特化理想城1
A112: 三合星2（B型恒星+A型恒星+F型恒星） | B112: sc_trinary_2 | D112: 遗落星球 | E112: pc_relic | G112: 未特化理想城2 | H112: district_arcology_urban_2 | I112: 次区划2 | J112: 理想城区划 | L112: 未特化理想城2
A113: 三合星3（K型恒星+F型恒星+G型恒星） | B113: sc_trinary_3 | D113: 气态巨行星 | E113: pc_gas_giant | G113: 未特化理想城3 | H113: district_arcology_urban_3 | I113: 次区划3 | J113: 理想城区划 | L113: 未特化理想城3
A114: 三合星4（B型恒星+K型恒星+T型褐矮星） | B114: sc_trinary_4 | D114: 小行星1 | E114: pc_asteroid | G114: 发电区划 | H114: district_generator | I114: 次区划1 | J114: 基础区划 | L114: 发电区划
A115: 翠光使 | B115: sc_toxoid_star | D115: 冰晶小行星 | E115: pc_ice_asteroid | G115: 发电区划（无上限） | H115: district_generator_uncapped | I115: 次区划1 | J115: 基础区划 | L115: 发电区划（无上限）
A116: 星界细缝 | B116: sc_rift_star | D116: 晶态小行星 | E116: pc_rare_crystal_asteroid | G116: 采矿区划 | H116: district_mining | I116: 次区划2 | J116: 基础区划 | L116: 采矿区划
D117: 熔融星球 | E117: pc_molten | G117: 采矿区划（无上限） | H117: district_mining_uncapped | I117: 次区划2 | J117: 基础区划 | L117: 采矿区划（无上限）
D118: 荒芜星球 | E118: pc_barren | G118: 农业区划 | H118: district_farming | I118: 次区划3 | J118: 基础区划 | L118: 农业区划
D119: 荒芜星球（冷冻） | E119: pc_barren_cold | G119: 农业区划（无上限） | H119: district_farming_uncapped | I119: 次区划3 | J119: 基础区划 | L119: 农业区划（无上限）
D120: 剧毒星球 | E120: pc_toxic | G120: 居住站区划 | H120: district_hab_housing | I120: 主区划 | J120: 居住站区划 | L120: 居住站区划
A121: 随机双星星系 | B121: rl_binary_stars | D121: 冰封星球 | E121: pc_frozen | G121: 反应堆区划 | H121: district_hab_energy | I121: 次区划1 | J121: 居住站区划 | L121: 反应堆区划
A122: 随机三星星系 | B122: rl_trinary_stars | D122: 崩坏的人工智能星球 | E122: pc_machine_broken | G122: 航天采矿湾 | H122: district_hab_mining | I122: 次区划2 | J122: 居住站区划 | L122: 航天采矿湾
A123: 随机标准星系 | B123: rl_standard_stars | D123: 屏障星球 | E123: pc_shielded | G123: 研究区划 | H123: district_hab_science | I123: 次区划3 | J123: 居住站区划 | L123: 研究区划
A124: 随机恒星星系 | B124: rl_starting_stars | D124: 人工智能星球 | E124: pc_ai | G124: 城市区段 | H124: district_rw_city | I124: 主区划 | J124: 环世界区划 | L124: 城市区段
A125: 随机恒星双星星系 | B125: rl_binary_starting_stars | D125: 孵化星球 | E125: pc_infested | G125: 蜂巢区段 | H125: district_rw_hive | I125: 主区划 | J125: 环世界区划 | L125: 蜂巢区段
A126: 随机特殊星系 | B126: rl_special_stars | D126: 破损的环形区段（居住段） | E126: pc_ringworld_habitable_damaged | G126: 中枢区段 | H126: district_rw_nexus | I126: 主区划 | J126: 环世界区划 | L126: 中枢区段
A127: 随机矮星系 | B127: rl_dwarf_stars | D127: 环形区段（辅助1） | E127: pc_ringworld_tech | G127: 未特化区段1 | H127: district_rw_urban_1 | I127: 次区划1 | J127: 环世界区划 | L127: 未特化区段1
A128: 随心全部单星星系 | B128: rl_all_stars | D128: 破损的环形区段（辅助1） | E128: pc_ringworld_tech_damaged | G128: 未特化区段2 | H128: district_rw_urban_2 | I128: 次区划2 | J128: 环世界区划 | L128: 未特化区段2
D129: 环形区段（辅助2） | E129: pc_ringworld_seam | G129: 未特化区段3 | H129: district_rw_urban_3 | I129: 次区划3 | J129: 环世界区划 | L129: 未特化区段3
D130: 破损的环形区段（辅助2） | E130: pc_ringworld_seam_damaged | G130: 共栖群落 | H130: district_craglands | I130: 主区划 | J130: 荒野区划 | L130: 共栖群落
D131: 虚境星球 | E131: pc_shrouded | G131: 光合原野 | H131: district_photosynthesis_fields | I131: 次区划1 | J131: 荒野区划 | L131: 光合原野
D132: 崩坏星球 | E132: pc_broken | G132: 光合原野（完成纯净） | H132: district_photosynthesis_fields_uncapped | I132: 次区划1 | J132: 荒野区划 | L132: 光合原野（完成纯净）
D133: 粉碎星球1 | E133: pc_shattered | G133: 中空山岭 | H133: district_hollow_mountains | I133: 次区划2 | J133: 荒野区划 | L133: 中空山岭
D134: 纳米星球（灰蛊） | E134: pc_gray_goo | G134: 中空山岭（完成纯净） | H134: district_hollow_mountains_uncapped | I134: 次区划2 | J134: 荒野区划 | L134: 中空山岭（完成纯净）
D135: 破碎星球 | E135: pc_egg_cracked | G135: 硕果森林 | H135: district_orchard_forests | I135: 次区划3 | J135: 荒野区划 | L135: 硕果森林
D136: 晶态小行星（利维坦） | E136: pc_crystal_asteroid | G136: 硕果森林（完成纯净） | H136: district_orchard_forests_uncapped | I136: 次区划3 | J136: 荒野区划 | L136: 硕果森林（完成纯净）
...

Sheet 科技
A1: 4.0.21科技代码（2025.07.09）
A2: 添加可学科技代码： | E2: research_all_technologies
A3: 添加全部科技代码： | E3: research_all_technologies 1
A4: 添加x层循环科技： | E4: research_all_technologies 0 x
A5: 类别 | B5: 序号 | C5: 名称 | D5: 备注名称 | E5: 代码 | F5: 等级 | G5: key | H5: 属性
A6: 物理学
A7: 力场操控 | B7: 1 | C7: 安乐天使 | E7: =_xlfn.CONCAT("research_technology"," ",G7) -> research_technology tech_pk_shielder | F7: t5 | G7: tech_pk_shielder | H7: 特殊
B8: 2 | C8: 裂隙探球 | E8: =_xlfn.CONCAT("research_technology"," ",G8) -> research_technology tech_rift_sphere | F8: t2 | G8: tech_rift_sphere | H8: 稀有
B9: 3 | C9: 风暴操控 | E9: =_xlfn.CONCAT("research_technology"," ",G9) -> research_technology tech_storm_manipulation | F9: t2 | G9: tech_storm_manipulation | H9: 特殊
B10: 4 | C10: 先进风暴操控 | E10: =_xlfn.CONCAT("research_technology"," ",G10) -> research_technology tech_advanced_storm_manipulation | F10: t3 | G10: tech_advanced_storm_manipulation | H10: 特殊
B11: 5 | C11: 试验性超空间导航 | E11: =_xlfn.CONCAT("research_technology"," ",G11) -> research_technology tech_experimental_subspace_navigation | F11: t2 | G11: tech_experimental_subspace_navigation | H11: 稀有
B12: 6 | C12: 暗物质偏导护盾 | E12: =_xlfn.CONCAT("research_technology"," ",G12) -> research_technology tech_dark_matter_deflector | F12: t5 | G12: tech_dark_matter_deflector | H12: 特殊
B13: 7 | C13: 皱缩空间仓库 | E13: =_xlfn.CONCAT("research_technology"," ",G13) -> research_technology tech_fe_silo_1 | F13: t5 | G13: tech_fe_silo_1 | H13: 特殊
B14: 8 | C14: 高维度仓库 | E14: =_xlfn.CONCAT("research_technology"," ",G14) -> research_technology tech_fe_silo_2 | F14: t5 | G14: tech_fe_silo_2 | H14: 特殊
B15: 9 | C15: 基础隐形场 | E15: =_xlfn.CONCAT("research_technology"," ",G15) -> research_technology tech_cloaking_1 | F15: t2 | G15: tech_cloaking_1 | H15: 稀有
B16: 10 | C16: 高级隐形场 | E16: =_xlfn.CONCAT("research_technology"," ",G16) -> research_technology tech_cloaking_2 | F16: t3 | G16: tech_cloaking_2 | H16: 稀有
B17: 11 | C17: 精英隐形场 | E17: =_xlfn.CONCAT("research_technology"," ",G17) -> research_technology tech_cloaking_3 | F17: t4 | G17: tech_cloaking_3 | H17: 稀有
B18: 12 | C18: 暗物质隐形场 | E18: =_xlfn.CONCAT("research_technology"," ",G18) -> research_technology tech_cloaking_dark_matter | F18: t5 | G18: tech_cloaking_dark_matter | H18: 危险
B19: 13 | C19: 重力陷阱 | E19: =_xlfn.CONCAT("research_technology"," ",G19) -> research_technology tech_gravity_wells | F19: t2 | G19: tech_gravity_wells | H19: 普通
... B47: 41 | C47: 暗物质收集 | E47: =_xlfn.CONCAT("research_technology"," ",G47) -> research_technology tech_mine_dark_matter | F47: t3 | G47: tech_mine_dark_matter | H47: 普通
A48: 计算技术 | B48: 1 | C48: 宇宙天气模型 | E48: =_xlfn.CONCAT("research_technology"," ",G48) -> research_technology tech_storm_prediction_1 | F48: t1 | G48: tech_storm_prediction_1 | H48: 特殊
B49: 2 | C49: 概率流 | E49: =_xlfn.CONCAT("research_technology"," ",G49) -> research_technology tech_storm_prediction_2 | F49: t3 | G49: tech_storm_prediction_2 | H49: 特殊
B50: 3 | C50: 量子创新中心 | E50: =_xlfn.CONCAT("research_technology"," ",G50) -> research_technology tech_fe_lab_1 | F50: t5 | G50: tech_fe_lab_1 | H50: 特殊
B51: 4 | C51: 超然创新部 | E51: =_xlfn.CONCAT("research_technology"," ",G51) -> research_technology tech_fe_lab_2 | F51: t5 | G51: tech_fe_lab_2 | H51: 特殊
B52: 5 | C52: 探测阵列 | E52: =_xlfn.CONCAT("research_technology"," ",G52) -> research_technology tech_detection_array | F52: t2 | G52: tech_detection_array | H52: 稀有
B53: 6 | C53: 先进探测算法 | E53: =_xlfn.CONCAT("research_technology"," ",G53) -> research_technology tech_assisted_detection | F53: t2 | G53: tech_assisted_detection | H53: 稀有
B54: 7 | C54: 新数字 | E54: =_xlfn.CONCAT("research_technology"," ",G54) -> research_technology tech_new_numbers | F54: t2 | G54: tech_new_numbers | H54: 土著
B55: 8 | C55: 三元计算技术 | E55: =_xlfn.CONCAT("research_technology"," ",G55) -> research_technology tech_trinary_computing | F55: t2 | G55: tech_trinary_computing | H55: 土著
B56: 9 | C56: 大气轨道力学 | E56: =_xlfn.CONCAT("research_technology"," ",G56) -> research_technology tech_atmospheric_orbital_mechanics | F56: t2 | G56: tech_atmospheric_orbital_mechanics | H56: 土著
B57: 10 | C57: 传感器生物整合 | E57: =_xlfn.CONCAT("research_technology"," ",G57) -> research_technology tech_sensors_bio_integration | F57: t2 | G57: tech_sensors_bio_integration | H57: 特殊
B58: 11 | C58: 战斗计算机生物整合 | E58: =_xlfn.CONCAT("research_technology"," ",G58) -> research_technology tech_combat_computers_bio_integration | F58: t2 | G58: tech_combat_computers_bio_integration | H58: 特殊
B59: 12 | C59: 神秘编码器 | E59: =_xlfn.CONCAT("research_technology"," ",G59) -> research_technology tech_enigmatic_encoder | F59: t5 | G59: tech_enigmatic_encoder | H59: 特殊
B60: 13 | C60: 神秘解码器 | E60: =_xlfn.CONCAT("research_technology"," ",G60) -> research_technology tech_enigmatic_decoder | F60: t5 | G60: tech_enigmatic_decoder | H60: 特殊
... B85: 38 | C85: 管理型人工智能 | E85: =_xlfn.CONCAT("research_technology"," ",G85) -> research_technology tech_administrative_ai | F85: t1 | G85: tech_administrative_ai | H85: 普通
B86: 39 | C86: 自动化殖民船 | D86: 幼苗孵化（荒野） | E86: =_xlfn.CONCAT("research_technology"," ",G86) -> research_technology tech_cryostasis_1 | F86: t1 | G86: tech_cryostasis_1 | H86: 普通
B87: 40 | C87: 自我意识殖民船 | D87: 永久孵化（荒野） | E87: =_xlfn.CONCAT("research_technology"," ",G87) -> research_technology tech_cryostasis_2 | F87: t3 | G87: tech_cryostasis_2 | H87: 普通
B88: 41 | C88: 自我演化逻辑 | E88: =_xlfn.CONCAT("research_technology"," ",G88) -> research_technology tech_self_aware_logic | F88: t2 | G88: tech_self_aware_logic | H88: 普通
B89: 42 | C89: 自动探索协议 | E89: =_xlfn.CONCAT("research_technology"," ",G89) -> research_technology tech_automated_exploration | F89: t1 | G89: tech_automated_exploration | H89: 普通
B90: 43 | C90: 正电子人工智能 | E90: =_xlfn.CONCAT("research_technology"," ",G90) -> research_technology tech_sapient_ai | F90: t4 | G90: tech_sapient_ai | H90: 普通
B91: 44 | C91: 正电子脑植入体 | E91: =_xlfn.CONCAT("research_technology"," ",G91) -> research_technology tech_positronic_implants | F91: t4 | G91: tech_positronic_implants | H91: 普通
B92: 45 | C92: 特种作战计算机 | E92: =_xlfn.CONCAT("research_technology"," ",G92) -> research_technology tech_combat_computers_1 | F92: t1 | G92: tech_combat_computers_1 | H92: 普通
B93: 46 | C93: 拓展战斗算法 | E93: =_xlfn.CONCAT("research_technology"," ",G93) -> research_technology tech_combat_computers_2 | F93: t3 | G93: tech_combat_computers_2 | H93: 普通
B94: 47 | C94: 智慧战斗模拟 | E94: =_xlfn.CONCAT("research_technology"," ",G94) -> research_technology tech_combat_computers_3 | F94: t4 | G94: tech_combat_computers_3 | H94: 危险
B95: 48 | C95: 自律舰船智能 | E95: =_xlfn.CONCAT("research_technology"," ",G95) -> research_technology tech_combat_computers_autonomous | F95: t4 | G95: tech_combat_computers_autonomous | H95: 危险
B96: 49 | C96: 辅助火控 | E96: =_xlfn.CONCAT("research_technology"," ",G96) -> research_technology tech_auxiliary_fire_control | F96: t1 | G96: tech_auxiliary_fire_control | H96: 普通
B97: 50 | C97: 同步防御 | E97: =_xlfn.CONCAT("research_technology"," ",G97) -> research_technology tech_synchronized_defences | F97: t4 | G97: tech_synchronized_defences | H97: 稀有
B98: 51 | C98: 市场分析算法 | E98: =_xlfn.CONCAT("research_technology"," ",G98) -> research_technology tech_consumer_good_refinement_1 | F98: t2 | G98: tech_consumer_good_refinement_1 | H98: 普通
B99: 52 | C99: 预测消费 | E99: =_xlfn.CONCAT("research_technology"," ",G99) -> research_technology tech_consumer_good_refinement_2 | F99: t4 | G99: tech_consumer_good_refinement_2 | H99: 普通
... B110: 63 | C110: 引力分析 | E110: =_xlfn.CONCAT("research_technology"," ",G110) -> research_technology tech_repeatable_reduced_building_cost | F110: t5 | G110: tech_repeatable_reduced_building_cost | H110: 循环
B111: 64 | C111: 主动反制 | D111: 哨卫拍炮（生物） | E111: =_xlfn.CONCAT("research_technology"," ",G111) -> research_technology tech_pd_tracking_1 | F111: t0 | G111: tech_pd_tracking_1 | H111: 普通
B112: 65 | C112: 互联支援系统 | D112: 屏障拍炮（生物） | E112: =_xlfn.CONCAT("research_technology"," ",G112) -> research_technology tech_pd_tracking_2 | F112: t2 | G112: tech_pd_tracking_2 | H112: 普通
B113: 66 | C113: 预测算法 | D113: 守护者拍炮（生物） | E113: =_xlfn.CONCAT("research_technology"," ",G113) -> research_technology tech_pd_tracking_3 | F113: t4 | G113: tech_pd_tracking_3 | H113: 普通
A114: 粒子物理 | B114: 1 | C114: 中子灭杀 | E114: =_xlfn.CONCAT("research_technology"," ",G114) -> research_technology tech_pk_neutron | F114: t5 | G114: tech_pk_neutron | H114: 特殊
B115: 2 | C115: 星界采收 | E115: =_xlfn.CONCAT("research_technology"," ",G115) -> research_technology tech_astral_harvesting | F115: t2 | G115: tech_astral_harvesting | H115: 普通
B116: 3 | C116: L-星门启动 | E116: =_xlfn.CONCAT("research_technology"," ",G116) -> research_technology tech_lgate_activation | F116: t3 | G116: tech_lgate_activation | H116: 特殊
B117: 4 | C117: 暗物质能源 | D117: 暗物质代谢（生物） | E117: =_xlfn.CONCAT("research_technology"," ",G117) -> research_technology tech_dark_matter_power_core | F117: t5 | G117: tech_dark_matter_power_core | H117: 特殊
B118: 5 | C118: 三级奇点 | E118: =_xlfn.CONCAT("research_technology"," ",G118) -> research_technology tech_fe_singularity_1 | F118: t5 | G118: tech_fe_singularity_1 | H118: 特殊
B119: 6 | C119: 四级奇点 | E119: =_xlfn.CONCAT("research_technology"," ",G119) -> research_technology tech_fe_singularity_2 | F119: t5 | G119: tech_fe_singularity_2 | H119: 特殊
B120: 7 | C120: 暗物质探测 | E120: =_xlfn.CONCAT("research_technology"," ",G120) -> research_technology tech_dark_matter_detection | F120: t5 | G120: tech_dark_matter_detection | H120: 稀有
B121: 8 | C121: 亚空间引擎 | E121: =_xlfn.CONCAT("research_technology"," ",G121) -> research_technology tech_subspace_drive | F121: t0 | G121: tech_subspace_drive | H121: 稀有
B122: 9 | C122: 异常传感 | E122: =_xlfn.CONCAT("research_technology"," ",G122) -> research_technology tech_unusual_senses | F122: t2 | G122: tech_unusual_senses | H122: 土著
B123: 10 | C123: 超光速生物整合 | E123: =_xlfn.CONCAT("research_technology"," ",G123) -> research_technology tech_hyper_drive_bio_integration | F123: t2 | G123: tech_hyper_drive_bio_integration | H123: 特殊
B124: 11 | C124: 欧米伽理论 | E124: =_xlfn.CONCAT("research_technology"," ",G124) -> research_technology tech_akx_worm_3 | F124: t3 | G124: tech_akx_worm_3 | H124: 特殊
B125: 12 | C125: 星门激活 | E125: =_xlfn.CONCAT("research_technology"," ",G125) -> research_technology tech_gateway_activation | F125: t4 | G125: tech_gateway_activation | H125: 稀有
B126: 13 | C126: 星门建造 | E126: =_xlfn.CONCAT("research_technology"," ",G126) -> research_technology tech_gateway_construction | F126: t5 | G126: tech_gateway_construction | H126: 稀有
B127: 14 | C127: 量子弹弓 | E127: =_xlfn.CONCAT("research_technology"," ",G127) -> research_technology tech_quantum_catapult | F127: t3 | G127: tech_quantum_catapult | H127: 稀有
B128: 15 | C128: 超空间中继器 | E128: =_xlfn.CONCAT("research_technology"," ",G128) -> research_technology tech_hyper_relays | F128: t2 | G128: tech_hyper_relays | H128: 稀有
B129: 16 | C129: 裂变能源 | D129: 裂变代谢（生物） | E129: =_xlfn.CONCAT("research_technology"," ",G129) -> research_technology tech_fission_power | F129: t0 | G129: tech_fission_power | H129: 普通
B130: 17 | C130: 聚变能源 | D130: 聚变代谢（生物） | E130: =_xlfn.CONCAT("research_technology"," ",G130) -> research_technology tech_fusion_power | F130: t1 | G130: tech_fusion_power | H130: 普通
B131: 18 | C131: 冷核聚变能源 | D131: 冷核裂变代谢（生物） | E131: =_xlfn.CONCAT("research_technology"," ",G131) -> research_technology tech_cold_fusion_power | F131: t2 | G131: tech_cold_fusion_power | H131: 普通
B132: 19 | C132: 反物质能源 | D132: 反物质代谢（生物） | E132: =_xlfn.CONCAT("research_technology"," ",G132) -> research_technology tech_antimatter_power | F132: t3 | G132: tech_antimatter_power | H132: 普通
B133: 20 | C133: 零点能源 | D133: 零点能代谢（生物） | E133: =_xlfn.CONCAT("research_technology"," ",G133) -> research_technology tech_zero_point_power | F133: t4 | G133: tech_zero_point_power | H133: 普通
B134: 21 | C134: 反应堆增压器 | E134: =_xlfn.CONCAT("research_technology"," ",G134) -> research_technology tech_reactor_boosters_1 | F134: t0 | G134: tech_reactor_boosters_1 | H134: 普通
B135: 22 | C135: 改良反应堆增压器 | E135: =_xlfn.CONCAT("research_technology"," ",G135) -> research_technology tech_reactor_boosters_2 | F135: t1 | G135: tech_reactor_boosters_2 | H135: 普通
B136: 23 | C136: 先进反应堆增压器 | E136: =_xlfn.CONCAT("research_technology"," ",G136) -> research_technology tech_reactor_boosters_3 | F136: t1 | G136: tech_reactor_boosters_3 | H136: 普通
B137: 24 | C137: 超空间移动 | E137: =_xlfn.CONCAT("research_technology"," ",G137) -> research_technology tech_hyper_drive_1 | F137: t0 | G137: tech_hyper_drive_1 | H137: 普通
B138: 25 | C138: 超空间航道突破点 | E138: =_xlfn.CONCAT("research_technology"," ",G138) -> research_technology tech_hyper_drive_2 | F138: t2 | G138: tech_hyper_drive_2 | H138: 普通
B139: 26 | C139: 超空间滑流 | E139: =_xlfn.CONCAT("research_technology"," ",G139) -> research_technology tech_hyper_drive_3 | F139: t3 | G139: tech_hyper_drive_3 | H139: 普通
B140: 27 | C140: 虫洞稳定 | E140: =_xlfn.CONCAT("research_technology"," ",G140) -> research_technology tech_wormhole_stabilization | F140: t3 | G140: tech_wormhole_stabilization | H140: 稀有
B141: 28 | C141: 跃迁引擎 | D141: 跃迁器官（生物） | E141: =_xlfn.CONCAT("research_technology"," ",G141) -> research_technology tech_jump_drive_1 | F141: t5 | G141: tech_jump_drive_1 | H141: 危险
B142: 29 | C142: 超光速抑制 | E142: =_xlfn.CONCAT("research_technology"," ",G142) -> research_technology tech_ftl_inhibitor | F142: t2 | G142: tech_ftl_inhibitor | H142: 普通
B143: 30 | C143: 聚焦阵列 | E143: =_xlfn.CONCAT("research_technology"," ",G143) -> research_technology tech_repeatable_weapon_type_energy_damage | F143: t5 | G143: tech_repeatable_weapon_type_energy_damage | H143: 循环
B144: 31 | C144: 快速冷却剂 | E144: =_xlfn.CONCAT("research_technology"," ",G144) -> research_technology tech_repeatable_weapon_type_energy_fire_rate | F144: t5 | G144: tech_repeatable_weapon_type_energy_fire_rate | H144: 循环
B145: 32 | C145: 红激光发射器 | D145: 红光投射器（生物） | E145: =_xlfn.CONCAT("research_technology"," ",G145) -> research_technology tech_lasers_1 | F145: t0 | G145: tech_lasers_1 | H145: 普通
B146: 33 | C146: 蓝激光发射器 | D146: 蓝光投射器（生物） | E146: =_xlfn.CONCAT("research_technology"," ",G146) -> research_technology tech_lasers_2 | F146: t1 | G146: tech_lasers_2 | H146: 普通
B147: 34 | C147: 紫外激光发射器 | D147: 紫外光投射器（生物） | E147: =_xlfn.CONCAT("research_technology"," ",G147) -> research_technology tech_lasers_3 | F147: t2 | G147: tech_lasers_3 | H147: 普通
B148: 35 | C148: X射线发射器 | D148: X光投射器（生物） | E148: =_xlfn.CONCAT("research_technology"," ",G148) -> research_technology tech_lasers_4 | F148: t3 | G148: tech_lasers_4 | H148: 普通
B149: 36 | C149: 伽马激光 | D149: 伽马光投射器（生物） | E149: =_xlfn.CONCAT("research_technology"," ",G149) -> research_technology tech_lasers_5 | F149: t4 | G149: tech_lasers_5 | H149: 普通
B150: 37 | C150: 粒子光矛 | D150: 粒子光束（生物） | E150: =_xlfn.CONCAT("research_technology"," ",G150) -> research_technology tech_energy_lance_1 | F150: t4 | G150: tech_energy_lance_1 | H150: 普通
B151: 38 | C151: 快子光矛 | D151: 快子光束（生物） | E151: =_xlfn.CONCAT("research_technology"," ",G151) -> research_technology tech_energy_lance_2 | F151: t4 | G151: tech_energy_lance_2 | H151: 普通
B152: 39 | C152: 等离子发射器 | D152: 生物等离子喷射炮（生物） | E152: =_xlfn.CONCAT("research_technology"," ",G152) -> research_technology tech_plasma_1 | F152: t2 | G152: tech_plasma_1 | H152: 普通
B153: 40 | C153: 等离子加速器 | D153: 生物等离子加速炮（生物） | E153: =_xlfn.CONCAT("research_technology"," ",G153) -> research_technology tech_plasma_2 | F153: t3 | G153: tech_plasma_2 | H153: 普通
B154: 41 | C154: 等离子加农炮 | D154: 生物等离子加农炮（生物） | E154: =_xlfn.CONCAT("research_technology"," ",G154) -> research_technology tech_plasma_3 | F154: t4 | G154: tech_plasma_3 | H154: 普通
B155: 42 | C155: 电弧发射器 | D155: 雷霆喷涌（生物） | E155: =_xlfn.CONCAT("research_technology"," ",G155) -> research_technology tech_arc_emitter_1 | F155: t4 | G155: tech_arc_emitter_1 | H155: 普通
B156: 43 | C156: 聚能电弧发射器 | D156: 雷霆射流（生物） | E156: =_xlfn.CONCAT("research_technology"," ",G156) -> research_technology tech_arc_emitter_2 | F156: t4 | G156: tech_arc_emitter_2 | H156: 普通
... B161: 48 | C161: 中子发射器 | D161: 中子喷射炮（生物） | E161: =_xlfn.CONCAT("research_technology"," ",G161) -> research_technology tech_energy_torpedoes_2 | F161: t4 | G161: tech_energy_torpedoes_2 | H161: 普通
B162: 49 | C162: 高维武器 | E162: =_xlfn.CONCAT("research_technology"," ",G162) -> research_technology tech_extradimensional_weapon_1 | F162: t5 | G162: tech_extradimensional_weapon_1 | H162: 特殊
B163: 50 | C163: 采矿无人机激光 | D163: 采矿光投射器（生物） | E163: =_xlfn.CONCAT("research_technology"," ",G163) -> research_technology tech_mining_drone_weapon_1 | F163: t2 | G163: tech_mining_drone_weapon_1 | H163: 特殊
B164: 51 | C164: 雷云导线 | E164: =_xlfn.CONCAT("research_technology"," ",G164) -> research_technology tech_space_cloud_weapon_1 | F164: t2 | G164: tech_space_cloud_weapon_1 | H164: 特殊
B165: 52 | C165: 太虚光束 | E165: =_xlfn.CONCAT("research_technology"," ",G165) -> research_technology null_void_beam | F165: t2 | G165: null_void_beam | H165: 特殊
...

Sheet 异常
A1: 4.0.21异常点收录（2025.08.16更新）
A2: 序号 | C2: 等级 | D2: 出现地点 | E2: 添加代码 | F2: 备注
A3: 1 | B3: 坠毁的飞船 | C3: 3 | D3: 小行星 | E3: add_anomaly crashed_ship_asteroid_category
A4: 2 | B4: 未知起源 | C4: 1 | D4: 小行星 | E4: add_anomaly origin_asteroid_category | F4: 标本小行星化石，粪粒石
A5: 3 | B5: 覆盖着残骸 | C5: 3 | D5: 小行星 | E5: add_anomaly debris_asteroid_category | F5: 加力燃烧室科技
A6: 4 | B6: 能量辐射 | C6: 1 | D6: 小行星 | E6: add_anomaly emissions_asteroid_category
A7: 5 | B7: 对接舱 | C7: 3 | D7: 小行星 | E7: add_anomaly hatch_asteroid_category
A8: 6 | B8: 小行星碰撞 | C8: 1 | D8: 小行星 | E8: add_anomaly collision_asteroid_category | F8: 国家修正，标本远古热传感器
A9: 7 | B9: 废弃空间站 | C9: 3 | D9: 小行星 | E9: add_anomaly station_asteroid_category | F9: 科技超空间移动，标本[星系名称]策展人调查
A10: 8 | B10: 生命迹象 | C10: 2 | D10: 小行星 | E10: add_anomaly life_asteroid_category | F10: 标本晶糖
A11: 9 | B11: 大气层中的物体 | C11: 4 | D11: 气态巨行星 | E11: add_anomaly object_gasgiant_category
A12: 10 | B12: 潜力巨大的卫星 | C12: 1 | D12: 气态巨行星 | E12: add_anomaly moon_gasgiant_category
A13: 11 | B13: 生命迹象 | C13: 2 | D13: 气态巨行星 | E13: add_anomaly life_gasgiant_category
A14: 12 | B14: 大气风暴 | C14: 1 | D14: 气态巨行星 | E14: add_anomaly storms_gasgiant_category | F14: 坑，拯救科学家
A15: 13 | B15: 飞行器结构 | C15: 1 | D15: 气态巨行星 | E15: add_anomaly aerostat_gasgiant_category
A16: 14 | B16: 货仓 | C16: 1 | D16: 气态巨行星 | E16: add_anomaly cargo_gasgiant_category | F16: 样本外星珠宝，循环邮件
A17: 15 | B17: 太空碎片 | C17: 1 | D17: 气态巨行星 | E17: add_anomaly debris_gasgiant_category | F17: 获得开明特质
A18: 16 | B18: 巨大撞击 | C18: 2 | D18: 非宜居星球 | E18: add_anomaly impact_uninhabitable_category
A19: 17 | B19: 异常能源示数 | C19: 2 | D19: 非宜居星球 | E19: add_anomaly energy_uninhabitable_category | F19: 标本跨星系炮弹
A20: 18 | B20: 微弱的信号 | C20: 2 | D20: 非宜居星球 | E20: add_anomaly signal_uninhabitable_category
A21: 19 | B21: 轨道小行星 | C21: 1 | D21: 非宜居星球，非卫星 | E21: add_anomaly asteroid_uninhabitable_category | F21: 被困的小行星
A22: 20 | B22: 太阳帆 | C22: 2 | D22: 非宜居星球 | E22: add_anomaly solar_uninhabitable_category | F22: 标本破损恒星帆
A23: 21 | B23: 生命迹象 | C23: 2 | D23: 剧毒星球 | E23: add_anomaly life_toxic_category | F23: 样本剧毒生物引擎
A24: 22 | B24: 生命迹象 | C24: 2 | D24: 冰封星球 | E24: add_anomaly life_frozen_category | F24: 活体金属科技
A25: 23 | B25: 生命迹象 | C25: 2 | D25: 荒芜星球 | E25: add_anomaly life_barren_category | F25: 行星修正
A26: 24 | B26: 战争迹象 | C26: 4 | D26: 非宜居星球 | E26: add_anomaly battle_uninhabitable_category
A27: 25 | B27: 远古船坞 | C27: 4 | D27: 非宜居星球 | E27: add_anomaly shipyard_uninhabitable_category
A28: 26 | B28: 前人殖民的迹象 | C28: 1 | D28: 剧毒星球 | E28: add_anomaly inhabited_toxic_category
A29: 27 | B29: 地表文字 | C29: 2 | D29: 非宜居星球 | E29: add_anomaly writing_uninhabitable_category | F29: 标本佣兵传说
A30: 28 | B30: 地表信标 | C30: 1 | D30: 非宜居星球 | E30: add_anomaly beacon_uninhabitable_category | F30: 标本远古采矿发射器
A31: 29 | B31: 成因奇怪的山脉 | C31: 3 | D31: 非宜居星球 | E31: add_anomaly mountain_uninhabitable_category | F31: 行星修正，骸骨巨兽，标本超巨型炒蛋，巨大跖骨
A32: 30 | B32: 未知物体 | C32: 2 | D32: 非宜居星球 | E32: add_anomaly object_uninhabitable_category | F32: 外星壁画，标本知识目录
A33: 31 | B33: 气态巨行星信号 | C33: 5 | D33: 气态巨行星 | E33: add_anomaly signal_gasgiant_category | F33: 伯达拉克事件链
A34: 32 | B34: 气态巨行星飞船 | C34: 5 | D34: 气态巨行星 | E34: add_anomaly ship_gasgiant_category
A35: 33 | B35: 终结轨道 | C35: 5 | D35: 气态巨行星 | E35: add_anomaly terminal_gasgiant_category
A36: 34 | B36: 核废墟 | C36: 1 | D36: 死寂星球 | E36: add_anomaly sol_wasteland_category
A37: 35 | B37: 奇特的撞击坑 | C37: 7 | D37: 荒芜星球或小行星 | E37: add_anomaly living_metal_category | F37: 活体金属科技
A38: 36 | B38: 古生命迹象 | C38: 3 | D38: 遗落星球，宜居星球，非格式塔 | E38: add_anomaly the_lonely_bot_category | F38: 行星特征，标本[prev.GetName]机器人残骸
A39: 37 | B39: 怪异辐射 | C39: 4 | D39: 距脱水1-12跳的荒芜星球 | E39: add_anomaly fungal_emitters_category | F39: 改良真菌网络修正，标本变异“巨大蘑菇”
A40: 38 | B40: 迷路灵魂 | C40: 2 | D40: 小行星 | E40: add_anomaly lost_soul_cat | F40: 标本遗弃机器人
A41: 39 | B41: 在恒星帆上 | C41: 2 | D41: 恒星 | E41: add_anomaly on_solar_sails_cat | F41: 考古遗址：瓶中信
A42: 40 | B42: 失事地点 | C42: 2 | D42: 小行星 | E42: add_anomaly on_crashed_ship_cat | F42: 考古遗址：毁灭的种子
A43: 41 | B43: 小行星电波 | C43: 1 | D43: 小行星 | E43: add_anomaly AST_WAVELENGTHS_1_CAT | F43: 获得特质治国术或生物学，标本DNA档案，矿化大脑
A44: 42 | B44: 残骸场 | C44: 3 | D44: 小行星，有太阳系或地联 | E44: add_anomaly AST_DEBRIS_FIELD_1_CAT | F44: 恒星系坐标事件链，标本金色唱片
A45: 43 | B45: 丰饶的星球 | C45: 4 | D45: 陆地，热带星球，有太阳系或地联 | E45: add_anomaly HBL_LUSH_PLANET_1_CAT | F45: 标本共生体，铝制雕版
A46: 44 | B46: 碑塔 | C46: 3 | D46: 小行星，宜居星球，气态巨行星，环形世界 | E46: add_anomaly UHB_ANCIENT_RUINS_1_CAT | F46: 标本纪念碑影像
A47: 45 | B47: 令人玩味的遗迹 | C47: 3 | D47: 小行星，气态巨行星，环形世界 非机械智能 | E47: add_anomaly GEN_PLAYGROUND_CAT | F47: 标本螺旋吸引装置
A48: 46 | B48: 被雕琢的小行星 | C48: 3 | D48: 小行星，非AI，人类或母星为太 阳系的帝国，非格式塔，非屹立于巨人之肩 | E48: add_anomaly AST_SHRINE_1_CAT | F48: 古神神殿事件链
A49: 47 | B49: 深夜天籁 | C49: 5 | D49: 宜居星球 | E49: add_anomaly HBL_MUSIC_1_CAT | F49: 玩具工厂，科技异种生物学，标本塑料玩具，[星球名称]管乐队
A50: 48 | B50: 冰冻巨行星 | C50: 6 | D50: 气态巨行星，有蒸馏泽珞 | E50: add_anomaly GAS_ZRO_ICE_CAT
A51: 49 | B51: 辐射小行星 | C51: 7 | D51: 小行星 | E51: add_anomaly AST_ILLICIT_DARK_CAT | F51: 标本[星球名称]虫洞锚
A52: 50 | B52: 斑斓毒星 | C52: 7 | D52: 剧毒星球，非格式塔 | E52: add_anomaly TOX_PURPLE_RAIN_CAT | F52: 标本紫雨复兴
A53: 51 | B53: 冰冻荒原 | C53: 2 | D53: 冰封星球，非格式塔 | E53: add_anomaly FROZ_BASE_CAT | F53: 流亡者
A54: 52 | B54: 疾行 | C54: 3 | D54: 热带星球 | E54: add_anomaly TROP_PETS_CAT | F54: 标本红色的小家伙
A55: 53 | B55: 荒芜平原 | C55: 5 | D55: 荒芜星球，非格式塔 | E55: add_anomaly BARR_BASE_CAT | F55: 生死弥留事件链
A56: 54 | B56: 奇异无比 | C56: 3 | D56: 有卫星的非宜居星球 | E56: add_anomaly PROJ_MOON_CAT
A57: 55 | B57: 变幻莫测 | C57: 2 | D57: 海洋星球 | E57: add_anomaly SEA_CAT | F57: 标本聚合物水网
A58: 56 | B58: 剧热律动 | C58: 2 | D58: 熔融星球 | E58: add_anomaly MOLTEN_BASE_CAT
A59: 57 | B59: 蒸汽翻腾 | C59: 1 | D59: 宜居星球 | E59: add_anomaly LEVELED_CAT
A60: 58 | B60: 维度扰动 | C60: 6 | D60: 小行星 | E60: add_anomaly DIMENSIONAL_POCKET_CAT | F60: 跃迁引擎科研船
A61: 59 | B61: 点点绿意 | C61: 4 | D61: 热带，陆地，海洋星球 | E61: add_anomaly HAB_CORN_CAT | F61: 标本超肥沃土
A62: 60 | B62: 金属闪烁 | C62: 4 | D62: 热带，陆地，干旱星球 | E62: add_anomaly HAB_MAT_CAT
A63: 61 | B63: 大气异常现象 | C63: 3 | D63: 小行星，环形世界，宜居星球，死寂星球，气态巨行星 | E63: add_anomaly ATM_ANOMALY_CAT
A64: 62 | B64: 瞬息万变 | C64: 5 | D64: 10-25格的荒芜星球 | E64: add_anomaly FRBR_GRIMACING_CAT
A65: 63 | B65: 冰雪发光 | C65: 3 | D65: 冰封星球，有红激光无紫激光以上 | E65: add_anomaly FROZ_ILLUMINATED_CAT
A66: 64 | B66: 云舞 | C66: 1 | D66: 气态巨行星 | E66: add_anomaly GAS_CLOUDY_CAT
A67: 65 | B67: 似是天堂 | C67: 3 | D67: 盖亚星球 | E67: add_anomaly GAIA_MOVE_CAT
A68: 66 | B68: 暗藏玄机 | C68: 2 | D68: 冰封星球 | E68: add_anomaly FROZ_BOX_CAT | F68: 标本嗅盘
A69: 67 | B69: 行星伤痕 | C69: 4 | D69: 陆地，热带，苔原星球 | E69: add_anomaly CONT_SIGNS_CAT | F69: 下一级激光导弹动能武器，粒子光矛，动能火炮，蜂群导弹，标本警示碑塔
A70: 68 | B70: 冰雪平原 | C70: 4 | D70: 极地星球 | E70: add_anomaly FROZ_BASE2_CAT
A71: 69 | B71: 尘暴区 | C71: 1 | D71: 小行星 | E71: add_anomaly AST_CRATER_CAT | F71: 科技离子推进器，标本行星发动机
A72: 70 | B72: 俯瞰 | C72: 6 | D72: 荒芜星球 | E72: add_anomaly BAR_COLONY_CAT
A73: 71 | B73: 剧毒外表 | C73: 2 | D73: 剧毒星球 | E73: add_anomaly TOX_MAT_CAT | F73: 标本反应石
A74: 72 | B74: 矿群 | C74: 3 | D74: 小行星 | E74: add_anomaly AST_CLUSTER_CAT | F74: 标本最后一本《君主论》
A75: 73 | B75: 扫雷 | C75: 2 | D75: 盖亚星球 | E75: add_anomaly GAEA_CHECKERED_CAT | F75: 获得新世界理论特质
A76: 74 | B76: 停泊 | C76: 8 | D76: 陆地，干旱星球 | E76: add_anomaly GEN_ABANDONED_SHIP_CAT
A77: 75 | B77: 沙丘 | C77: 3 | D77: 沙漠星球 | E77: add_anomaly GEN_DESERT_CAT | F77: 毛巾携带者特质
A78: 76 | B78: 剧毒建筑 | C78: 8 | D78: 剧毒星球 | E78: add_anomaly TOX_STRUCTURES_CAT
A79: 77 | B79: 森林国度 | C79: 3 | D79: 热带星球 | E79: add_anomaly TROP_WOODS_CAT
A80: 78 | B80: 黑暗中的彩虹 | C80: 5 | D80: 黑洞 | E80: add_anomaly HOLE_RADIATION_CAT | F80: 坑，偏执
A81: 79 | B81: 多普勒效应 | C81: 3 | D81: 非宜居球，死寂星球，非格式塔 | E81: add_anomaly UHB_BUOY_CAT | F81: 星际绑架者事件链
A82: 80 | B82: 破釜沉舟 | C82: 7 | D82: 盖亚星球，陆地星球 | E82: add_anomaly GAIA_RECORD_CAT | F82: 漂流的战场事件链
A83: 81 | B83: 古代工厂 | C83: 3 | D83: 有3-6小行星与0-4颗行星的星系 | E83: add_anomaly CRYSTAL_MANUFACTORY_CAT | F83: 古代工厂事件链
A84: 82 | B84: 热带奇谭 | C84: 3 | D84: 热带星球 | E84: add_anomaly TROP_BIOLOGY_CAT | F84: 标本酸性孢子
A85: 83 | B85: 留心矿物 | C85: 2 | D85: 小行星 | E85: add_anomaly AST_MINING_CAT
A86: 84 | B86: 求救信号 | C86: 2 | D86: 苔原，荒芜星球，非机械 | E86: add_anomaly GEN_DERELICT_SHIP_CAT
A87: 85 | B87: 古怪读数 | C87: 6 | D87: 小行星 | E87: add_anomaly GEN_LOST_CARGO_CAT | F87: 提升舰船速度修正，标本[物种名称]第一位宇航员
A88: 86 | B88: 钢之追寻 | C88: 2 | D88: 荒芜，剧毒，死寂星球 | E88: add_anomaly GEN_OLD_WAR_CAT | F88: 大师的教诲:战争国度(格式塔)，标本破烂的巨型引擎
A89: 87 | B89: 沙中迷藏 | C89: 4 | D89: 沙漠星球 | E89: add_anomaly DES_BURIED_CAT | F89: 大师的教诲：上上善道
A90: 88 | B90: 令人疑惑的宇宙射线 | C90: 5 | D90: 沙漠，干旱星球 | E90: add_anomaly SUN_RAYS_CAT | F90: 恒星异常现象事件链
A91: 89 | B91: 沧海一粟 | C91: 3 | D91: 海洋星球，非格式塔，不予干涉 | E91: add_anomaly WAT_PLANET_CAT
A92: 90 | B92: 潜在发现 | C92: 3 | D92: 冰封，荒芜星球 | E92: add_anomaly COLD_RESEARCH_CAT | F92: 大师的教诲：哲学思辩；增强太阳能修正；下一级护盾，标本特丽莎科学专论
A93: 91 | B93: 不可能的轨道 | C93: 5 | D93: K级或M级恒星 | E93: add_anomaly SUN_TEAPOT_CAT | F93: 高维洞见，标本高维度茶壶
A94: 92 | B94: 惊人的小行星 | C94: 6 | D94: 小行星 | E94: add_anomaly AST_GEAR_CAT
A95: 93 | B95: 丛林之间 | C95: 3 | D95: 热带星球非失控机仆的机械智能 | E95: add_anomaly TROP_CONDITIONS_CAT | F95: 标本玛娜果
A96: 94 | B96: 荒无人烟 | C96: 6 | D96: 干旱星球 | E96: add_anomaly ARID_SENSOR_CAT | F96: 广泛传感器搜寻
A97: 95 | B97: 大陆上的发现 | C97: 1 | D97: 陆地星球 | E97: add_anomaly CON_BIOLOGY_CAT | F97: 动物劳役修正，标本[星球名称]超级根茎
A98: 96 | B98: 毒性 | C98: 3 | D98: 剧毒星球 | E98: add_anomaly TOX_PLANET_CAT | F98: 专长推进力学特质
A99: 97 | B99: 荒凉沙漠 | C99: 1 | D99: 沙漠星球 | E99: add_anomaly DES_PLANET_CAT
A100: 98 | B100: 谜团 | C100: 7 | D100: 小行星，非格式塔 | E100: add_anomaly GEN_MYSTICAL_CAT | F100: 不老药，标本“生命树”标本
...

Sheet 巨构
A1: 4.0.22巨构代码（2025.08.24）
A2: 定位栏 | B2: {=HYPERLINK("#"&ADDRESS(MATCH("航道类巨构生成代码",A:A,0),COLUMN(B:B)),"航道类巨构")} -> 航道类巨构 | C2: {=HYPERLINK("#"&ADDRESS(MATCH("殖民地类巨构生成代码",A:A,0),COLUMN(A:A)),"殖民地类巨构")} -> 殖民地类巨构 | D2: {=HYPERLINK("#"&ADDRESS(MATCH("恒星基地类巨构生成代码",A:A,0),COLUMN(A:A)),"恒星基地类巨构")} -> 恒星基地类巨构 | E2: {=HYPERLINK("#"&ADDRESS(MATCH("其他巨构生成代码",A:A,0),COLUMN(A:A)),"其他巨构")} -> 其他巨构 | F2: 注:选中恒星或星球输入即可，部分代码有额外条件，注意查看。 清除标识看代码类型，planet_flag选中对应星球，country_flag不选任何物体。
A3: 其他代码 | B3: 选中巨构输入移除该巨构 | D3: 选中巨构立刻完成升级
B4: effect remove_megastructure = this | D4: effect finish_upgrade = yes
B5: 设定国家已完成完整巨构（解锁星河奇迹） | D5: 选中星球移除该星球为巨构标识 | F5: 选中星球移除该星球已有巨构标识
B6: effect set_country_flag = has_built_or_repaired_megastructure | D6: effect remove_planet_flag = megastructure | F6: effect remove_planet_flag = has_megastructure
A7: 设定栏 | B7: 生成距离 | C7: 0 | D7: 生成角度 | E7: 0 | F7: 模型类别 | G7: 人型生物
A8: 巨构类别 | B8: 巨构名称 | C8: 生成代码 | G8: key
A9: 航道类巨构生成代码
A10: 注：选中恒星输入，如果星门或L-星门生成后无法使用，请输入激活星门指令。
B11: 激活星门指令 | C11: effect activate_gateway = this
A12: 中继器 超空间 | B12: 超空间中继器 | C12: =_xlfn.CONCAT("effect = { solar_system = { spawn_megastructure = { type = ",G12," orbit_angle = ",$E$7," orbit_distance = ",$C$7," random_pos = yes graphical_culture = ",_xlfn.XLOOKUP($G$7,扩展代码!$B$670:$B$686,扩展代码!$C$670:$C$686)," }}}") -> effect = { solar_system = { spawn_megastructure = { type = hyper_relay orbit_angle = 0 orbit_distance = 0 random_pos = yes graphical_culture = humanoid_01 }}} | G12: hyper_relay
B13: 损毁的超空间中继器 | C13: =_xlfn.CONCAT("effect = { solar_system = { spawn_megastructure = { type = ",G13," orbit_angle = ",$E$7," orbit_distance = ",$C$7," random_pos = yes graphical_culture = ",_xlfn.XLOOKUP($G$7,扩展代码!$B$670:$B$686,扩展代码!$C$670:$C$686)," }}}") -> effect = { solar_system = { spawn_megastructure = { type = hyper_relay_ruined orbit_angle = 0 orbit_distance = 0 random_pos = yes graphical_culture = humanoid_01 }}} | G13: hyper_relay_ruined
B14: 超空间中继器（修复） | C14: =_xlfn.CONCAT("effect = { solar_system = { spawn_megastructure = { type = ",G14," orbit_angle = ",$E$7," orbit_distance = ",$C$7," random_pos = yes graphical_culture = ",_xlfn.XLOOKUP($G$7,扩展代码!$B$670:$B$686,扩展代码!$C$670:$C$686)," }}}") -> effect = { solar_system = { spawn_megastructure = { type = hyper_relay_restored orbit_angle = 0 orbit_distance = 0 random_pos = yes graphical_culture = humanoid_01 }}} | G14: hyper_relay_restored
A15: 星门 | B15: 星门基址 | C15: =_xlfn.CONCAT("effect = { solar_system = { spawn_megastructure = { type = ",G15," orbit_angle = ",$E$7," orbit_distance = ",$C$7," random_pos = yes graphical_culture = ",_xlfn.XLOOKUP($G$7,扩展代码!$B$670:$B$686,扩展代码!$C$670:$C$686)," }}}") -> effect = { solar_system = { spawn_megastructure = { type = gateway_0 orbit_angle = 0 orbit_distance = 0 random_pos = yes graphical_culture = humanoid_01 }}} | G15: gateway_0
B16: 星门 | C16: =_xlfn.CONCAT("effect = { solar_system = { spawn_megastructure = { type = ",G16," orbit_angle = ",$E$7," orbit_distance = ",$C$7," random_pos = yes graphical_culture = ",_xlfn.XLOOKUP($G$7,扩展代码!$B$670:$B$686,扩展代码!$C$670:$C$686)," }}}") -> effect = { solar_system = { spawn_megastructure = { type = gateway_final orbit_angle = 0 orbit_distance = 0 random_pos = yes graphical_culture = humanoid_01 }}} | G16: gateway_final
B17: 失效的星门 | C17: =_xlfn.CONCAT("effect = { solar_system = { spawn_megastructure = { type = ",G17," orbit_angle = ",$E$7," orbit_distance = ",$C$7," random_pos = yes graphical_culture = ",_xlfn.XLOOKUP($G$7,扩展代码!$B$670:$B$686,扩展代码!$C$670:$C$686)," }}}") -> effect = { solar_system = { spawn_megastructure = { type = gateway_ruined orbit_angle = 0 orbit_distance = 0 random_pos = yes graphical_culture = humanoid_01 }}} | G17: gateway_ruined
B18: 星门 | C18: =_xlfn.CONCAT("effect = { solar_system = { spawn_megastructure = { type = ",G18," orbit_angle = ",$E$7," orbit_distance = ",$C$7," random_pos = yes graphical_culture = ",_xlfn.XLOOKUP($G$7,扩展代码!$B$670:$B$686,扩展代码!$C$670:$C$686)," }}}") -> effect = { solar_system = { spawn_megastructure = { type = gateway_restored orbit_angle = 0 orbit_distance = 0 random_pos = yes graphical_culture = humanoid_01 }}} | G18: gateway_restored
B19: 废弃星门 | C19: =_xlfn.CONCAT("effect = { solar_system = { spawn_megastructure = { type = ",G19," orbit_angle = ",$E$7," orbit_distance = ",$C$7," random_pos = yes graphical_culture = ",_xlfn.XLOOKUP($G$7,扩展代码!$B$670:$B$686,扩展代码!$C$670:$C$686)," }}}") -> effect = { solar_system = { spawn_megastructure = { type = gateway_derelict orbit_angle = 0 orbit_distance = 0 random_pos = yes graphical_culture = humanoid_01 }}} | G19: gateway_derelict
B20: 失效的星门（寻宝猎人） | C20: =_xlfn.CONCAT("effect = { solar_system = { spawn_megastructure = { type = ",G20," orbit_angle = ",$E$7," orbit_distance = ",$C$7," random_pos = yes graphical_culture = ",_xlfn.XLOOKUP($G$7,扩展代码!$B$670:$B$686,扩展代码!$C$670:$C$686)," }}}") -> effect = { solar_system = { spawn_megastructure = { type = gateway_ness_ruined orbit_angle = 0 orbit_distance = 0 random_pos = yes graphical_culture = humanoid_01 }}} | G20: gateway_ness_ruined
B21: 星门（寻宝猎人） | C21: =_xlfn.CONCAT("effect = { solar_system = { spawn_megastructure = { type = ",G21," orbit_angle = ",$E$7," orbit_distance = ",$C$7," random_pos = yes graphical_culture = ",_xlfn.XLOOKUP($G$7,扩展代码!$B$670:$B$686,扩展代码!$C$670:$C$686)," }}}") -> effect = { solar_system = { spawn_megastructure = { type = gateway_ness_restored orbit_angle = 0 orbit_distance = 0 random_pos = yes graphical_culture = humanoid_01 }}} | G21: gateway_ness_restored
A22: L-星门 | B22: 注意：连结星门只能通往节点星门，节点星门也只能通往连结星门，默认终端出口为连结星门。 仅有节点星门允许使用维度锁。生成时请选中恒星输入。
B23: L-星门节点星门 | C23: =_xlfn.CONCAT("effect = { solar_system = { set_star_flag = lgate spawn_megastructure = { type = ",G23," orbit_angle = ",$E$7," orbit_distance = ",$C$7," random_pos = no owner = owner }}}") -> effect = { solar_system = { set_star_flag = lgate spawn_megastructure = { type = lgate_base orbit_angle = 0 orbit_distance = 0 random_pos = no owner = owner }}} | G23: lgate_base | H23: （node）
B24: L-星门连结星门 | C24: =_xlfn.CONCAT("effect = { solar_system = { set_star_flag = lcluster1 spawn_megastructure = { type = ",G24," orbit_angle = ",$E$7," orbit_distance = ",$C$7," random_pos = no owner = owner }}}") -> effect = { solar_system = { set_star_flag = lcluster1 spawn_megastructure = { type = lgate_base orbit_angle = 0 orbit_distance = 0 random_pos = no owner = owner }}} | G24: lgate_base | H24: （nexus）
B25: 转换为节点星门 | C25: effect solar_system = { remove_star_flag = lcluster1 set_star_flag = lgate}
B26: 转换为连结星门 | C26: effect solar_system = { remove_star_flag = lgate set_star_flag = lcluster1 }
A27: 殖民地类巨构生成代码
A28: 注：选中恒星输入即可。
A29: 环形世界 | B29: 注：以下自动生成全部环世界（四段），先输入移除星球代码（也可以不输，将保留星系内其他星球），然后选中恒星输入。
B30: 删除星系内其他星球 | C30: effect = { solar_system = { every_system_planet = { limit = { is_star = no } remove_planet = yes }}}
B31: 废弃的环形世界区段 | C31: effect = { solar_system = {spawn_megastructure = { type = "ring_world_ruined" orbit_angle = 0 orbit_distance = 45 }spawn_megastructure = { type = "ring_world_ruined" orbit_angle = 90 orbit_distance = 45 }spawn_megastructure = { type = "ring_world_ruined" orbit_angle = 180 orbit_distance = 45 }spawn_megastructure = { type = "ring_world_ruined" orbit_angle = 270 orbit_distance = 45 }}} | G31: ring_world_ruined
B32: 环形世界框架 | C32: effect = { solar_system = {spawn_megastructure = { type = "ring_world_2" orbit_angle = 0 orbit_distance = 45 }spawn_megastructure = { type = "ring_world_2" orbit_angle = 90 orbit_distance = 45 }spawn_megastructure = { type = "ring_world_2" orbit_angle = 180 orbit_distance = 45 }spawn_megastructure = { type = "ring_world_2" orbit_angle = 270 orbit_distance = 45 }}} | G32: ring_world_2
B33: 已完成的环形世界区段 | C33: effect = { solar_system = {spawn_megastructure = { type = "ring_world_3_intermediate" orbit_angle = 0 orbit_distance = 45 }spawn_megastructure = { type = "ring_world_3_intermediate" orbit_angle = 90 orbit_distance = 45 }spawn_megastructure = { type = "ring_world_3_intermediate" orbit_angle = 180 orbit_distance = 45 }spawn_megastructure = { type = "ring_world_3_intermediate" orbit_angle = 270 orbit_distance = 45 }}} | G33: ring_world_3_intermediate
B34: 已完成的环形世界区段（修复） | C34: effect = { solar_system = {spawn_megastructure = { type = "ring_world_restored" orbit_angle = 0 orbit_distance = 45 }spawn_megastructure = { type = "ring_world_restored" orbit_angle = 90 orbit_distance = 45 }spawn_megastructure = { type = "ring_world_restored" orbit_angle = 180 orbit_distance = 45 }spawn_megastructure = { type = "ring_world_restored" orbit_angle = 270 orbit_distance = 45 }}} | G34: ring_world_restored
B35: 注：以下为生成单段环世界，可以自由调整生成位置，然后选中星球输入。
B36: 环形世界基址 | C36: =_xlfn.CONCAT("effect = { solar_system = { spawn_megastructure = { type = ",G36," orbit_angle = ",$E$7," orbit_distance = ",$C$7," random_pos = no planet = from graphical_culture = ",_xlfn.XLOOKUP($G$7,扩展代码!$B$670:$B$686,扩展代码!$C$670:$C$686)," }}}") -> effect = { solar_system = { spawn_megastructure = { type = ring_world_1 orbit_angle = 0 orbit_distance = 0 random_pos = no planet = from graphical_culture = humanoid_01 }}} | G36: ring_world_1
B37: 环形世界框架 | C37: =_xlfn.CONCAT("effect = { solar_system = { spawn_megastructure = { type = ",G37," orbit_angle = ",$E$7," orbit_distance = ",$C$7," random_pos = no planet = from graphical_culture = ",_xlfn.XLOOKUP($G$7,扩展代码!$B$670:$B$686,扩展代码!$C$670:$C$686)," }}}") -> effect = { solar_system = { spawn_megastructure = { type = ring_world_2 orbit_angle = 0 orbit_distance = 0 random_pos = no planet = from graphical_culture = humanoid_01 }}} | G37: ring_world_2
B38: 已完成的环形世界区段 | C38: =_xlfn.CONCAT("effect = { solar_system = { spawn_megastructure = { type = ",G38," orbit_angle = ",$E$7," orbit_distance = ",$C$7," random_pos = no planet = from graphical_culture = ",_xlfn.XLOOKUP($G$7,扩展代码!$B$670:$B$686,扩展代码!$C$670:$C$686)," }}}") -> effect = { solar_system = { spawn_megastructure = { type = ring_world_3_intermediate orbit_angle = 0 orbit_distance = 0 random_pos = no planet = from graphical_culture = humanoid_01 }}} | G38: ring_world_3_intermediate
B39: 废弃的环形世界区段 | C39: =_xlfn.CONCAT("effect = { solar_system = { spawn_megastructure = { type = ",G39," orbit_angle = ",$E$7," orbit_distance = ",$C$7," random_pos = no planet = from graphical_culture = ",_xlfn.XLOOKUP($G$7,扩展代码!$B$670:$B$686,扩展代码!$C$670:$C$686)," }}}") -> effect = { solar_system = { spawn_megastructure = { type = ring_world_ruined orbit_angle = 0 orbit_distance = 0 random_pos = no planet = from graphical_culture = humanoid_01 }}} | G39: ring_world_ruined
B40: 已完成的环形世界区段（修复） | C40: =_xlfn.CONCAT("effect = { solar_system = { spawn_megastructure = { type = ",G40," orbit_angle = ",$E$7," orbit_distance = ",$C$7," random_pos = no planet = from graphical_culture = ",_xlfn.XLOOKUP($G$7,扩展代码!$B$670:$B$686,扩展代码!$C$670:$C$686)," }}}") -> effect = { solar_system = { spawn_megastructure = { type = ring_world_restored orbit_angle = 0 orbit_distance = 0 random_pos = no planet = from graphical_culture = humanoid_01 }}} | G40: ring_world_restored
A41: 居住站 | B41: 移除居住站标识 | C41: effect remove_planet_flag = habitat | E41: 注：选中居住站输入此代码可以在星系内再建一个居住站，新建的也可以再移除再建。
B42: 居住站中心复合体 | C42: =_xlfn.CONCAT("effect = { solar_system = { spawn_megastructure = { type = ",G42," orbit_angle = ",$E$7," orbit_distance = ",$C$7," random_pos = no planet = from graphical_culture = ",_xlfn.XLOOKUP($G$7,扩展代码!$B$670:$B$686,扩展代码!$C$670:$C$686)," }}}") -> effect = { solar_system = { spawn_megastructure = { type = habitat_central_complex orbit_angle = 0 orbit_distance = 0 random_pos = no planet = from graphical_culture = humanoid_01 }}} | G42: habitat_central_complex
B43: 被毁的居住站中心复合体 | C43: =_xlfn.CONCAT("effect = { solar_system = { spawn_megastructure = { type = ",G43," random_pos = no planet = from graphical_culture = ",_xlfn.XLOOKUP($G$7,扩展代码!$B$670:$B$686,扩展代码!$C$670:$C$686)," }}}") -> effect = { solar_system = { spawn_megastructure = { type = habitat_central_complex_ruined random_pos = no planet = from graphical_culture = humanoid_01 }}} | G43: habitat_central_complex_ruined
B44: 居住站中心复合体（修复） | C44: =_xlfn.CONCAT("effect = { solar_system = { spawn_megastructure = { type = ",G44," random_pos = no planet = from graphical_culture = ",_xlfn.XLOOKUP($G$7,扩展代码!$B$670:$B$686,扩展代码!$C$670:$C$686)," }}}") -> effect = { solar_system = { spawn_megastructure = { type = habitat_central_complex_restored random_pos = no planet = from graphical_culture = humanoid_01 }}} | G44: habitat_central_complex_restored
B45: 大型轨道站（已没用） | C45: =_xlfn.CONCAT("effect = { solar_system = { spawn_megastructure = { type = ",G45," random_pos = no planet = from graphical_culture = ",_xlfn.XLOOKUP($G$7,扩展代码!$B$670:$B$686,扩展代码!$C$670:$C$686)," }}}") -> effect = { solar_system = { spawn_megastructure = { type = habitat_major_orbital random_pos = no planet = from graphical_culture = humanoid_01 }}} | G45: habitat_major_orbital
B46: 小型轨道站（已没用） | C46: =_xlfn.CONCAT("effect = { solar_system = { spawn_megastructure = { type = ",G46," random_pos = no planet = from graphical_culture = ",_xlfn.XLOOKUP($G$7,扩展代码!$B$670:$B$686,扩展代码!$C$670:$C$686)," }}}") -> effect = { solar_system = { spawn_megastructure = { type = habitat_minor_orbital random_pos = no planet = from graphical_culture = humanoid_01 }}} | G46: habitat_minor_orbital
A47: 凝练机 突 触 | B47: 移除突触凝练机计数 | C47: effect remove_country_flag = cosmogenesis_world_built
B48: 突触凝练机 | C48: =_xlfn.CONCAT("effect = { solar_system = { spawn_megastructure = { type = ",G48," orbit_angle = ",$E$7," orbit_distance = ",$C$7," random_pos = no planet = from graphical_culture = ",_xlfn.XLOOKUP($G$7,扩展代码!$B$670:$B$686,扩展代码!$C$670:$C$686)," }}}") -> effect = { solar_system = { spawn_megastructure = { type = cosmogenesis_world_0 orbit_angle = 0 orbit_distance = 0 random_pos = no planet = from graphical_culture = humanoid_01 }}} | G48: cosmogenesis_world_0
B49: 被毁的突触凝练机 | C49: =_xlfn.CONCAT("effect = { solar_system = { spawn_megastructure = { type = ",G49," orbit_angle = ",$E$7," orbit_distance = ",$C$7," random_pos = no planet = from graphical_culture = ",_xlfn.XLOOKUP($G$7,扩展代码!$B$670:$B$686,扩展代码!$C$670:$C$686)," }}}") -> effect = { solar_system = { spawn_megastructure = { type = cosmogenesis_world_ruined orbit_angle = 0 orbit_distance = 0 random_pos = no planet = from graphical_culture = humanoid_01 }}} | G49: cosmogenesis_world_ruined
A50: 恒星基地类巨构生成代码
A51: 注：需要对应科技才可正常生成，使用前不选中任何输入设定归属权后，再输入以下代码，否则在无主星系生成时会导致闪退；星环基地可以给任意星球添加，但未殖民的星球无法升级，直接生成3级星环请查看“全局舰船”条目。
A52: 星环基地 | B52: 设定恒星基地归属权 | C52: effect = { save_global_event_target_as = playercountry} | G52: 此行代码必须输入
B53: 星环基地 | C53: =_xlfn.CONCAT("effect = { solar_system = { spawn_megastructure = { type = ",G53," orbit_angle = ",$E$7," orbit_distance = ",$C$7," owner = event_target:playercountry random_pos = no planet = from graphical_culture = ",_xlfn.XLOOKUP($G$7,扩展代码!$B$670:$B$686,扩展代码!$C$670:$C$686)," }}}") -> effect = { solar_system = { spawn_megastructure = { type = orbital_ring orbit_angle = 0 orbit_distance = 0 owner = event_target:playercountry random_pos = no planet = from graphical_culture = humanoid_01 }}} | G53: orbital_ring
B54: 可修复星环基地标识 | C54: effect set_planet_flag = ruined_orbital_ring_planet
B55: 废弃的星环基地 | C55: =_xlfn.CONCAT("effect = { solar_system = { spawn_megastructure = { type = ",G55," orbit_angle = ",$E$7," orbit_distance = ",$C$7," owner = event_target:playercountry random_pos = no planet = from graphical_culture = ",_xlfn.XLOOKUP($G$7,扩展代码!$B$670:$B$686,扩展代码!$C$670:$C$686)," }}}") -> effect = { solar_system = { spawn_megastructure = { type = orbital_ring_ruined orbit_angle = 0 orbit_distance = 0 owner = event_target:playercountry random_pos = no planet = from graphical_culture = humanoid_01 }}} | G55: orbital_ring_ruined
B56: 星环基地（修复） | C56: =_xlfn.CONCAT("effect = { solar_system = { spawn_megastructure = { type = ",G56," orbit_angle = ",$E$7," orbit_distance = ",$C$7," owner = event_target:playercountry random_pos = no planet = from graphical_culture = ",_xlfn.XLOOKUP($G$7,扩展代码!$B$670:$B$686,扩展代码!$C$670:$C$686)," }}}") -> effect = { solar_system = { spawn_megastructure = { type = orbital_ring_restored orbit_angle = 0 orbit_distance = 0 owner = event_target:playercountry random_pos = no planet = from graphical_culture = humanoid_01 }}} | G56: orbital_ring_restored
A57: 深空擎天堡 | B57: 深空擎天堡 | C57: =_xlfn.CONCAT("effect = { solar_system = { spawn_megastructure = { type = ",G57," orbit_angle = ",$E$7," orbit_distance = ",$C$7," owner = event_target:playercountry random_pos = no planet = from graphical_culture = ",_xlfn.XLOOKUP($G$7,扩展代码!$B$670:$B$686,扩展代码!$C$670:$C$686)," }}}") -> effect = { solar_system = { spawn_megastructure = { type = deep_space_citadel_0 orbit_angle = 0 orbit_distance = 0 owner = event_target:playercountry random_pos = no planet = from graphical_culture = humanoid_01 }}} | G57: deep_space_citadel_0
A58: 其他巨构生成代码
A59: 注：选中星球使用即可，清除上限计数等不需要选中任何东西。电弧熔炉建议从开头升级，直接用代码生成的电弧熔炉不会对星系内的其他星球产生矿藏。
A60: 戴森球 | B60: 清空戴森球上限计数 | C60: effect = { remove_country_flag = built_dyson_sphere remove_country_flag = built_dyson_sphere_contingency remove_country_flag = built_dyson_sphere_contingency_swarm remove_country_flag = built_dyson_sphere_swarm }
B61: 解锁建造奇迹球 | C61: effect set_country_flag = can_build_disco_sphere
B62: 戴森球基址 | C62: =_xlfn.CONCAT("effect = { solar_system = { spawn_megastructure = { type = ",G62," orbit_angle = ",$E$7," orbit_distance = ",$C$7," random_pos = no planet = from graphical_culture = ",_xlfn.XLOOKUP($G$7,扩展代码!$B$670:$B$686,扩展代码!$C$670:$C$686)," }}}") -> effect = { solar_system = { spawn_megastructure = { type = dyson_sphere_0 orbit_angle = 0 orbit_distance = 0 random_pos = no planet = from graphical_culture = humanoid_01 }}} | G62: dyson_sphere_0
B63: 戴森球框架 | C63: =_xlfn.CONCAT("effect = { solar_system = { spawn_megastructure = { type = ",G63," orbit_angle = ",$E$7," orbit_distance = ",$C$7," random_pos = no planet = from graphical_culture = ",_xlfn.XLOOKUP($G$7,扩展代码!$B$670:$B$686,扩展代码!$C$670:$C$686)," }}}") -> effect = { solar_system = { spawn_megastructure = { type = dyson_sphere_1 orbit_angle = 0 orbit_distance = 0 random_pos = no planet = from graphical_culture = humanoid_01 }}} | G63: dyson_sphere_1
B64: 戴森球：初始 | C64: =_xlfn.CONCAT("effect = { solar_system = { spawn_megastructure = { type = ",G64," orbit_angle = ",$E$7," orbit_distance = ",$C$7," random_pos = no planet = from graphical_culture = ",_xlfn.XLOOKUP($G$7,扩展代码!$B$670:$B$686,扩展代码!$C$670:$C$686)," }}}") -> effect = { solar_system = { spawn_megastructure = { type = dyson_sphere_2 orbit_angle = 0 orbit_distance = 0 random_pos = no planet = from graphical_culture = humanoid_01 }}} | G64: dyson_sphere_2
B65: 戴森球：中段 | C65: =_xlfn.CONCAT("effect = { solar_system = { spawn_megastructure = { type = ",G65," orbit_angle = ",$E$7," orbit_distance = ",$C$7," random_pos = no planet = from graphical_culture = ",_xlfn.XLOOKUP($G$7,扩展代码!$B$670:$B$686,扩展代码!$C$670:$C$686)," }}}") -> effect = { solar_system = { spawn_megastructure = { type = dyson_sphere_3 orbit_angle = 0 orbit_distance = 0 random_pos = no planet = from graphical_culture = humanoid_01 }}} | G65: dyson_sphere_3
B66: 戴森球：将成 | C66: =_xlfn.CONCAT("effect = { solar_system = { spawn_megastructure = { type = ",G66," orbit_angle = ",$E$7," orbit_distance = ",$C$7," random_pos = no planet = from graphical_culture = ",_xlfn.XLOOKUP($G$7,扩展代码!$B$670:$B$686,扩展代码!$C$670:$C$686)," }}}") -> effect = { solar_system = { spawn_megastructure = { type = dyson_sphere_4 orbit_angle = 0 orbit_distance = 0 random_pos = no planet = from graphical_culture = humanoid_01 }}} | G66: dyson_sphere_4
B67: 戴森球 | C67: =_xlfn.CONCAT("effect = { solar_system = { spawn_megastructure = { type = ",G67," orbit_angle = ",$E$7," orbit_distance = ",$C$7," random_pos = no planet = from graphical_culture = ",_xlfn.XLOOKUP($G$7,扩展代码!$B$670:$B$686,扩展代码!$C$670:$C$686)," }}}") -> effect = { solar_system = { spawn_megastructure = { type = dyson_sphere_5 orbit_angle = 0 orbit_distance = 0 random_pos = no planet = from graphical_culture = humanoid_01 }}} | G67: dyson_sphere_5
B68: 废弃的戴森球（无法修复） | C68: =_xlfn.CONCAT("effect = { solar_system = { spawn_megastructure = { type = ",G68," orbit_angle = ",$E$7," orbit_distance = ",$C$7," random_pos = no planet = from graphical_culture = ",_xlfn.XLOOKUP($G$7,扩展代码!$B$670:$B$686,扩展代码!$C$670:$C$686)," }}}") -> effect = { solar_system = { spawn_megastructure = { type = dyson_sphere_permanently_ruined orbit_angle = 0 orbit_distance = 0 random_pos = no planet = from graphical_culture = humanoid_01 }}} | G68: dyson_sphere_permanently_ruined
